Workbook

Sheet Inputs
A1: Experiment inputs
A2: Edit the blue cells. The consumables, order-totals and cost sheets all recalculate from these.
A4: Parameter | B4: Value | D4: Basis | E4: Count | G4: Cost by scaling level | H4: Total cost ($)
A5: Samples | B5: 54 | D5: per sample | E5: =Inputs!$B$5 -> 54 | G5: per sample | H5: =SUMIFS(Pre_GEM_Consumables!$N$2:$N$102,Pre_GEM_Consumables!$E$2:$E$102,G5)+SUMIFS(Post_GEM_Consumables!$N$2:$N$97,Post_GEM_Consumables!$E$2:$E$97,G5) -> 751.55244
A6: Genetic pools | B6: 6 | D6: per genetic pool | E6: =Inputs!$B$6 -> 6 | G6: per genetic pool | H6: =SUMIFS(Pre_GEM_Consumables!$N$2:$N$102,Pre_GEM_Consumables!$E$2:$E$102,G6)+SUMIFS(Post_GEM_Consumables!$N$2:$N$97,Post_GEM_Consumables!$E$2:$E$97,G6) -> 819.26207
A7: Super-pools (combined stain/load units) | B7: 1 | D7: per super-pool | E7: =Inputs!$B$7 -> 1 | G7: per super-pool | H7: =SUMIFS(Pre_GEM_Consumables!$N$2:$N$102,Pre_GEM_Consumables!$E$2:$E$102,G7)+SUMIFS(Post_GEM_Consumables!$N$2:$N$97,Post_GEM_Consumables!$E$2:$E$97,G7) -> 6011.4482
A8: HTO batches (hashtag kits) | B8: 1 | D8: per HTO batch | E8: =Inputs!$B$8 -> 1 | G8: per lane | H8: =SUMIFS(Pre_GEM_Consumables!$N$2:$N$102,Pre_GEM_Consumables!$E$2:$E$102,G8)+SUMIFS(Post_GEM_Consumables!$N$2:$N$97,Post_GEM_Consumables!$E$2:$E$97,G8) -> 0
A9: Workers | B9: 3 | D9: per worker | E9: =Inputs!$B$9 -> 3 | G9: per worker | H9: =SUMIFS(Pre_GEM_Consumables!$N$2:$N$102,Pre_GEM_Consumables!$E$2:$E$102,G9)+SUMIFS(Post_GEM_Consumables!$N$2:$N$97,Post_GEM_Consumables!$E$2:$E$97,G9) -> 0
A10: GEM lanes / channels (generic) | B10: 8 | D10: per lane | E10: =Inputs!$B$10 -> 8 | G10: per run | H10: =SUMIFS(Pre_GEM_Consumables!$N$2:$N$102,Pre_GEM_Consumables!$E$2:$E$102,G10)+SUMIFS(Post_GEM_Consumables!$N$2:$N$97,Post_GEM_Consumables!$E$2:$E$97,G10) -> 0
A11: 5' GEM channels | B11: 8 | D11: per 5' GEM channel | E11: =Inputs!$B$11 -> 8 | G11: per 5' GEM channel | H11: =SUMIFS(Pre_GEM_Consumables!$N$2:$N$102,Pre_GEM_Consumables!$E$2:$E$102,G11)+SUMIFS(Post_GEM_Consumables!$N$2:$N$97,Post_GEM_Consumables!$E$2:$E$97,G11) -> 13743.368
A12: ATAC GEM channels | B12: 2 | D12: per ATAC GEM channel | E12: =Inputs!$B$12 -> 2 | G12: per 5'-GEX library | H12: =SUMIFS(Pre_GEM_Consumables!$N$2:$N$102,Pre_GEM_Consumables!$E$2:$E$102,G12)+SUMIFS(Post_GEM_Consumables!$N$2:$N$97,Post_GEM_Consumables!$E$2:$E$97,G12) -> 838.8997
A13: 5'-GEX libraries | B13: 8 | D13: per 5'-GEX library | E13: =Inputs!$B$13 -> 8 | G13: per 5'-VDJ library | H13: =SUMIFS(Pre_GEM_Consumables!$N$2:$N$102,Pre_GEM_Consumables!$E$2:$E$102,G13)+SUMIFS(Post_GEM_Consumables!$N$2:$N$97,Post_GEM_Consumables!$E$2:$E$97,G13) -> 1265.9806
A14: 5'-VDJ libraries | B14: 8 | D14: per 5'-VDJ library | E14: =Inputs!$B$14 -> 8 | G14: per 5'-ADT library | H14: =SUMIFS(Pre_GEM_Consumables!$N$2:$N$102,Pre_GEM_Consumables!$E$2:$E$102,G14)+SUMIFS(Post_GEM_Consumables!$N$2:$N$97,Post_GEM_Consumables!$E$2:$E$97,G14) -> 499.34238
A15: 5'-ADT libraries | B15: 8 | D15: per 5'-ADT library | E15: =Inputs!$B$15 -> 8 | G15: per ATAC library | H15: =SUMIFS(Pre_GEM_Consumables!$N$2:$N$102,Pre_GEM_Consumables!$E$2:$E$102,G15)+SUMIFS(Post_GEM_Consumables!$N$2:$N$97,Post_GEM_Consumables!$E$2:$E$97,G15) -> 3555.5977
A16: ATAC-ADT libraries | B16: 2 | D16: per ATAC-ADT library | E16: =Inputs!$B$16 -> 2 | G16: per ATAC-ADT library | H16: =SUMIFS(Pre_GEM_Consumables!$N$2:$N$102,Pre_GEM_Consumables!$E$2:$E$102,G16)+SUMIFS(Post_GEM_Consumables!$N$2:$N$97,Post_GEM_Consumables!$E$2:$E$97,G16) -> 25.049979
A17: ATAC libraries | B17: 2 | D17: per ATAC library | E17: =Inputs!$B$17 -> 2 | G17: per ATAC GEM channel | H17: =SUMIFS(Pre_GEM_Consumables!$N$2:$N$102,Pre_GEM_Consumables!$E$2:$E$102,G17)+SUMIFS(Post_GEM_Consumables!$N$2:$N$97,Post_GEM_Consumables!$E$2:$E$97,G17) -> 3542
A18: (fixed) | B18: 1 | D18: per run | E18: =Inputs!$B$18 -> 1 | G18: per Flex sample | H18: =SUMIFS(Pre_GEM_Consumables!$N$2:$N$102,Pre_GEM_Consumables!$E$2:$E$102,G18)+SUMIFS(Post_GEM_Consumables!$N$2:$N$97,Post_GEM_Consumables!$E$2:$E$97,G18) -> 0
G19: per Flex pool | H19: =SUMIFS(Pre_GEM_Consumables!$N$2:$N$102,Pre_GEM_Consumables!$E$2:$E$102,G19)+SUMIFS(Post_GEM_Consumables!$N$2:$N$97,Post_GEM_Consumables!$E$2:$E$97,G19) -> 0
A20: Default overage (extra to prepare) | B20: 0.1 | G20: per Flex library | H20: =SUMIFS(Pre_GEM_Consumables!$N$2:$N$102,Pre_GEM_Consumables!$E$2:$E$102,G20)+SUMIFS(Post_GEM_Consumables!$N$2:$N$97,Post_GEM_Consumables!$E$2:$E$97,G20) -> 0
A21: Flex v2 samples (fixation + hyb rxns) | B21: 0 | D21: per Flex sample | E21: =Inputs!$B$21 -> 0
A22: Flex v2 pools (GEM reactions) | B22: 0 | D22: per Flex pool | E22: =Inputs!$B$22 -> 0
A23: Flex v2 libraries | B23: 0 | D23: per Flex library | E23: =Inputs!$B$23 -> 0
A24: Flex v2 is an opt-in track: set the three counts above > 0 to include Flex reagents in totals (leave 0 for a 5'/ASAP/sort-only plan).

Sheet README
A1: Single-Cell Pipeline — Master Data Schema
A2: Tsang Lab | Draft schema for the experiment planning tool | Built from existing lab spreadsheets & protocols
A4: Tab color | B4: Meaning | C4: Who edits it | D4: How
A5: Red | B5: Admin-only — reference/pricing data | C5: PI, lab manager, or tool admin | D5: Lock the tab (Protect sheet / Protected ranges) in Google Sheets so only admins can edit
A6: Green | B6: Lab-editable — day-to-day updates | C6: Anyone in the lab | D6: Open editing, but structured as an append-only log where possible (see Inventory_Transactions)
A7: Purple | B7: Auto-computed / rarely touched | C7: No one manually — formulas or the tool write here | D7: Protect from manual edits; values come from formulas or the web app
A10: Sheet map
A11: Sheet | B11: Purpose | C11: Key column(s) | D11: Tier
A12: Kit_Catalog | B12: Every 10x kit/reagent: part numbers, kit size, price, reactions per kit | C12: kit_id (PK) | D12: Admin
A13: Antibody_HTO_Catalog | B13: TotalSeq HTO/ADT cocktails and hashtag antibodies | C13: item_id (PK) | D13: Admin
A14: Additional_Reagents_Catalog | B14: Third-party consumables (SPRI, ethanol, tips, QC kits, etc.) | C14: item_id (PK) | D14: Admin
A15: Per_Channel_Consumables | B15: How much SPRI/ethanol/EB each protocol needs per channel | C15: protocol (FK) | D15: Admin
A16: Sequencing_Pricing | B16: YCGA / external sequencing platform pricing | C16: platform_id (PK) | D16: Admin
A17: Modality_Definitions | B17: scRNAseq/CITEseq/ASAPseq/Flex definitions, required stages, default cell targets | C17: modality_id (PK) | D17: Admin
A18: Protocol_Stages | B18: Modular workflow building blocks (thaw, pool, stain, sort, stim, library prep...) | C18: stage_id (PK) | D18: Admin
A19: Stage_Reagent_Requirements | B19: Links each protocol stage to catalog items + amount per sample/channel/pool | C19: stage_id, item_id (FK) | D19: Admin
A20: Personnel_Roster | B20: Who can run which stage, current availability | C20: person_id (PK) | D20: Lab-editable
A21: Live_Inventory | B21: Current on-hand quantity per catalog item (computed from transactions) | C21: item_id (FK) | D21: Purple = auto-computed
A22: Inventory_Transactions | B22: Append-only log: every receipt or use of a reagent | C22: txn_id (PK) | D22: Lab-editable
A23: Experiment_Log | B23: Historical record of past experiments — plans, actuals, costs | C23: experiment_id (PK) | D23: Lab-editable
A26: Design principles
A27: 1. Catalog data (kits, pricing, protocols) is admin-locked — it changes rarely and errors here break every calculation downstream.
A28: 2. Inventory is NEVER edited by typing a new stock number directly. Everyone logs a transaction (+received / -used); Live_Inventory's stock column is a SUMIFS formula over the log. This avoids two people overwriting each other's edits and gives you a use history for free.
A29: 3. Every table has a stable *_id primary key so the future web app (and other sheets) can reference rows reliably even if names or prices change.
A30: 4. Protocol_Stages + Stage_Reagent_Requirements are the bridge between 'what modalities did you pick' and 'what do you need to order' — this is what replaces the fragmented one-off protocols.
A31: 5. This workbook is the template to recreate as a Google Sheets file (one tab = one sheet). Once migrated, use Data > Protected sheets and ranges to enforce the admin/lab-editable split.
A33: ARCHITECTURE NOTE (updated):
A34: Live inventory, inventory transactions, and the experiment log now live in the separate
A35: Live_Inventory workbook on Google Drive (single source of truth). This schema holds only
A36: reference data: catalogs, consumables recipes, pricing, modality/protocol definitions, and calculators.

Sheet Kit_Catalog
A1: Kit_Catalog
A2: Admin-only. Source: 10X_Reagent_Ordering_Tracker.xlsx (June 2026) + 10x Genomics official price list PDFs (verified 2026-07-01).
A4: kit_id | B4: chemistry | C4: category | D4: kit_name | E4: part_number | F4: kit_size | G4: reactions_per_kit | H4: price_usd | I4: price_verified_date | J4: price_source | K4: notes
A5: K001 | B5: 3' v4 | C5: GEX | D5: Chromium GEM-X Single Cell 3' Kit v4 | E5: PN-1000691 | F5: 16 rxn | G5: 16 | H5: 23670 | I5: unverified | J5: 10X_Reagent_Ordering_Tracker.xlsx (June 2026) - not in July 2026 price list export, unverified | K5: Includes GEM Kit, Gel Bead Kit, Dynabeads, LCK C.
A6: K002 | B6: 3' v4 | C6: GEX | D6: Chromium GEM-X Single Cell 3' Chip Kit v4 | E6: PN-1000690 | F6: 4 chips | G6: 16 | H6: 1250 | I6: unverified | J6: 10X_Reagent_Ordering_Tracker.xlsx (June 2026) - not in July 2026 price list export, unverified | K6: 16 (4 channels/chip).
A7: K003 | B7: 3' v4 | C7: Surface Protein | D7: Feature Barcode Kit v4 (3') | E7: PN-1000702 | F7: 16 rxn | G7: 16 | H7: 670 | I7: 2026-07-01 | J7: 10x Genomics store price list PDF (exported 2026-07-01)
A8: K004 | B8: 3' v4 | C8: Library | D8: Dual Index Kit NT, Set A | E8: PN-1000242 | F8: 96 rxn | G8: 96 | H8: 960 | I8: 2026-07-01 | J8: 10x Genomics store price list PDF (exported 2026-07-01) | K8: Cell-surface-protein library indices. Shared part: this same kit (PN-1000242) is also used as the Feature Barcode/Protein index kit for the 5' v3 OCM (multiplex) workflow - not a separate SKU, don't order twice.
A9: K005 | B9: 3' v4 OCM | C9: GEX | D9: GEM-X OCM 3' Chip Kit v4 4-plex (2 chips) | E9: PN-1000747 | F9: 2 chips | H9: 600 | I9: 2026-07-01 | J9: 10x Genomics store price list PDF (exported 2026-07-01) | K9: OCM hardware multiplexing chip for 3' chemistry.
A10: K006 | B10: 3' v4 OCM | C10: GEX | D10: GEM-X OCM 3' Chip Kit v4 4-plex (1 chip) | E10: PN-1000953 | F10: 1 chip | H10: 300 | I10: 2026-07-01 | J10: 10x Genomics store price list PDF (exported 2026-07-01)
A11: K007 | B11: 3' v4 OCM | C11: GEX | D11: GEM-X Universal 3' GEX v4 4-plex core reagents (16 samples) | E11: PN-1000779 | F11: 16 samp | G11: 16 | H11: 5994 | I11: 2026-07-01 | J11: 10x Genomics store price list PDF (exported 2026-07-01) | K11: Core reagents for OCM 4-plex workflow - pairs with K031/K032 chip.
A12: K008 | B12: 3' v4 OCM | C12: GEX | D12: GEM-X Universal 3' GEX v4 4-plex core reagents (8 samples) | E12: PN-1000957 | F12: 8 samp | G12: 8 | H12: 3994 | I12: 2026-07-01 | J12: 10x Genomics store price list PDF (exported 2026-07-01)
A13: K009 | B13: 5' v3 | C13: GEX | D13: Chromium GEM-X Single Cell 5' Kit v3 | E13: PN-1000699 | F13: 16 rxn | G13: 16 | H13: 23670 | I13: 2026-07-01 | J13: 10x Genomics store price list PDF (exported 2026-07-01) | K13: Core 5' assay. Includes Gel Beads, Dynabeads MyOne SILANE.
A14: K010 | B14: 5' v3 | C14: GEX | D14: Chromium GEM-X Single Cell 5' Kit v3 (4 rxn) | E14: PN-1000695 | F14: 4 rxn | G14: 4 | H14: 6498 | I14: 2026-07-01 | J14: 10x Genomics store price list PDF (exported 2026-07-01) | K14: Core 5' assay, small format.
A15: K011 | B15: 5' v3 | C15: GEX | D15: Chromium GEM-X Single Cell 5' Chip Kit | E15: PN-1000698 | F15: 4 chips | G15: 16 | H15: 1250 | I15: 2026-07-01 | J15: 10x Genomics store price list PDF (exported 2026-07-01) | K15: CORRECTED 2026-07-01: catalog previously listed this as PN-1000748 / 2 chips / $600, which is actually the OCM 4-plex chip variant, not the standard chip. Standard Chromium GEM-X Single Cell 5' Chip Kit v3 (4 chips, 16 channels) is PN-1000698, $1,250.
A16: K012 | B16: 5' v3 | C16: GEX/Library | D16: Library Construction Kit C | E16: PN-1000694 | F16: 16 rxn | G16: 16 | H16: 1250 | I16: 2026-07-01 | J16: 10x Genomics store price list PDF (exported 2026-07-01) | K16: Extra LCK C may be needed when building both V(D)J and 5' GEX libraries from same cDNA.
A17: K013 | B17: 5' v3 | C17: Library | D17: Dual Index Kit TT, Set A | E17: PN-1000215 | F17: 96 rxn | G17: 96 | H17: 960 | I17: 2026-07-01 | J17: 10x Genomics store price list PDF (exported 2026-07-01) | K17: Library indices (GEX).
A18: K014 | B18: 5' v3 | C18: V(D)J | D18: V(D)J Amplification Kit, Human TCR | E18: PN-1000252 | F18: 16 rxn | G18: 16 | H18: 360 | I18: 2026-07-01 | J18: 10x Genomics store price list PDF (exported 2026-07-01) | K18: Order kit matching species + chain.
A19: K015 | B19: 5' v3 | C19: V(D)J | D19: V(D)J Amplification Kit, Human BCR | E19: PN-1000253 | F19: 16 rxn | G19: 16 | H19: 360 | I19: 2026-07-01 | J19: 10x Genomics store price list PDF (exported 2026-07-01) | K19: Order kit matching species + chain.
A20: K016 | B20: 5' v3 | C20: Surface Protein | D20: Feature Barcode Kit v3 | E20: PN-1000703 | F20: 16 rxn | G20: 16 | H20: 670 | I20: 2026-07-01 | J20: 10x Genomics store price list PDF (exported 2026-07-01)
A21: K017 | B21: 5' v3 | C21: Library | D21: Dual Index Kit TN, Set A | E21: PN-1000250 | F21: 96 rxn | G21: 96 | H21: 960 | I21: 2026-07-01 | J21: 10x Genomics store price list PDF (exported 2026-07-01) | K21: Cell-surface-protein library indices.
A22: K018 | B22: 5' v3 | C22: CRISPR | D22: 5' CRISPR Kit | E22: PN-1000451 | F22: 16 rxn | G22: 16 | H22: 670 | I22: 2026-07-01 | J22: 10x Genomics store price list PDF (exported 2026-07-01)
A23: K019 | B23: 5' v3 | C23: GEX | D23: GEM-X Universal 5' GEX cDNA Kit v3, 16 samples | E23: PN-1000826 | F23: 16 samp | G23: 16 | H23: 22420 | I23: 2026-07-01 | J23: 10x Genomics store price list PDF (exported 2026-07-01) | K23: Optional standalone cDNA-only reagent format - alternative to the all-in-one core reagents kit (K001) if buying cDNA and gel bead/chip components separately.
A24: K020 | B24: 5' v3 | C24: GEX | D24: GEM-X Universal 5' GEX cDNA Kit v3, Automated, 16 samples | E24: PN-1000889 | F24: 16 samp | G24: 16 | H24: 23225 | I24: 2026-07-01 | J24: 10x Genomics store price list PDF (exported 2026-07-01) | K24: Automated-workflow version of K037.
A25: K021 | B25: 5' v3 | C25: GEX/Library | D25: Library Construction Kit C, Automated 24 rxns / Manual 32 rxns | E25: PN-1000774 | F25: 24-32 rxn | G25: 24 | H25: 2400 | I25: 2026-07-01 | J25: 10x Genomics store price list PDF (exported 2026-07-01) | K25: Higher-throughput alternative to K004 (16 rxn kit) - cheaper per-reaction at scale.
A26: K022 | B26: 5' v3 | C26: V(D)J | D26: V(D)J Amplification Kit, Mouse TCR | E26: PN-1000254 | F26: 16 rxn | G26: 16 | H26: 360 | I26: 2026-07-01 | J26: 10x Genomics store price list PDF (exported 2026-07-01) | K26: Mouse equivalent of K006 (Human TCR). Only needed for mouse studies.
A27: K023 | B27: 5' v3 | C27: V(D)J | D27: V(D)J Amplification Kit, Mouse BCR | E27: PN-1000255 | F27: 16 rxn | G27: 16 | H27: 360 | I27: 2026-07-01 | J27: 10x Genomics store price list PDF (exported 2026-07-01) | K27: Mouse equivalent of K007 (Human BCR). Only needed for mouse studies.
A28: K024 | B28: 5' v3 OCM | C28: GEX | D28: GEM-X OCM 5' Chip Kit v3 4-plex (2 chips) | E28: PN-1000748 | F28: 2 chips | H28: 600 | I28: 2026-07-01 | J28: 10x Genomics store price list PDF (exported 2026-07-01) | K28: On-Chip Multiplexing (OCM) chip - 10x's native hardware multiplexing, an alternative to hashtag-oligo pooling. NEW: not yet reflected in Modality_Definitions/Protocol_Stages.
A29: K025 | B29: 5' v3 OCM | C29: GEX | D29: GEM-X OCM 5' Chip Kit v3 4-plex (1 chip) | E29: PN-1000955 | F29: 1 chip | H29: 300 | I29: 2026-07-01 | J29: 10x Genomics store price list PDF (exported 2026-07-01) | K29: Smaller-format OCM chip.
A30: K026 | B30: 5' v3 OCM | C30: GEX | D30: GEM-X Universal 5' GEX v3 4-plex core reagents (16 samples) | E30: PN-1000780 | F30: 16 samp | G30: 16 | H30: 5994 | I30: 2026-07-01 | J30: 10x Genomics store price list PDF (exported 2026-07-01) | K30: Core reagents for OCM 4-plex workflow - pairs with K027/K028 chip.
A31: K027 | B31: 5' v3 OCM | C31: GEX | D31: GEM-X Universal 5' GEX v3 4-plex core reagents (8 samples) | E31: PN-1000956 | F31: 8 samp | G31: 8 | H31: 3994 | I31: 2026-07-01 | J31: 10x Genomics store price list PDF (exported 2026-07-01)
A32: K028 | B32: Any (nuclei-based) | C32: Sample Prep | D32: Nuclei Isolation Kit with RNase Inhibitor v2 | E32: PN-1001101 | F32: 16 rxn | G32: 16 | H32: 2500 | I32: 2026-07-01 | J32: 10x Genomics store price list PDF (exported 2026-07-01) | K32: Optional add-on for ATAC/Multiome or nuclei-based workflows. Also listed on both the standard and OCM/multiplex 5' kit pages - same part, usable with 5' v3 if starting from nuclei.
A33: K029 | B33: Any (nuclei-based) | C33: Sample Prep | D33: Chromium Nuclei Isolation Kit with RNase Inhibitor | E33: PN-1000494 | F33: 16 rxn | G33: 16 | H33: 2060 | I33: 2026-07-01 | J33: 10x Genomics store price list PDF (exported 2026-07-01) | K33: Older-format alternative to K035. Also appears on both 5' v3 kit pages (standard + OCM).
A34: K030 | B34: Epi ATAC v2 | C34: ATAC | D34: Chromium Next GEM Single Cell ATAC Kit v2 | E34: PN-1000390 | F34: 16 rxn | G34: 16 | H34: 25000 | I34: 2026-07-01 | J34: 10x Genomics store price list PDF (exported 2026-07-01) | K34: Core assay kit. Includes Dynabeads MyOne SILANE.
A35: K031 | B35: Epi ATAC v2 | C35: ATAC | D35: Chromium Next GEM Chip H Single Cell Kit | E35: PN-1000161 | F35: 48 rxn | G35: 48 | H35: 1800 | I35: 2026-07-01 | J35: 10x Genomics store price list PDF (exported 2026-07-01) | K35: Microfluidic chips + gaskets.
A36: K032 | B36: Epi ATAC v2 | C36: ATAC | D36: Chromium Next GEM Chip H Single Cell Kit (16 rxn) | E36: PN-1000162 | F36: 16 rxn | G36: 16 | H36: 620 | I36: 2026-07-01 | J36: 10x Genomics store price list PDF (exported 2026-07-01)
A37: K033 | B37: Epi ATAC v2 | C37: Library | D37: Single Index Kit N, Set A | E37: PN-1000212 | F37: 96 rxn | G37: 96 | H37: 960 | I37: 2026-07-01 | J37: 10x Genomics store price list PDF (exported 2026-07-01) | K37: ATAC library indices.
A38: K034 | B38: Epi Multiome | C38: Multiome | D38: GEM-X Epi Multiome Kit | E38: PN-1000979 | F38: 16 samp | G38: 16 | H38: 35500 | I38: 2026-07-01 | J38: 10x Genomics store price list PDF (exported 2026-07-01) | K38: Includes GEM, Amp, Gel Bead, Dynabeads, ATAC kits.
A39: K035 | B39: Epi Multiome | C39: Multiome | D39: GEM-X Epi Multiome Chip Kit | E39: PN-1000951 | F39: 4 chips | G39: 16 | H39: 1250 | I39: 2026-07-01 | J39: 10x Genomics store price list PDF (exported 2026-07-01)
A40: K036 | B40: Flex v2 | C40: GEX | D40: GEM-X Flex v2 Core Reagents (16 samp) | E40: PN-1000927 | F40: 16 samp | G40: 16 | H40: 10200 | I40: 2026-07-01 | J40: 10x Genomics store price list PDF (exported 2026-07-01) | K40: Fixation/quench/permeabilization reagents.
A41: K037 | B41: Flex v2 | C41: GEX | D41: GEM-X Flex v2 Core Reagents (96 samp) | E41: PN-1000928 | F41: 96 samp | G41: 96 | H41: 24480 | I41: 2026-07-01 | J41: 10x Genomics store price list PDF (exported 2026-07-01)
A42: K038 | B42: Flex v2 | C42: GEX | D42: GEM-X Flex Gene Expression Chip Kit | E42: PN-1000791 | F42: 4 chips | G42: 16 | H42: 1250 | I42: 2026-07-01 | J42: 10x Genomics store price list PDF (exported 2026-07-01) | K42: Inferred 16 rxn/kit (4 channels x 4 chips), matches K011 5' GEM-X chip kit; verify.
A43: K039 | B43: Flex v2 | C43: Library | D43: Dual Index Kit TS, Set A | E43: PN-1000251 | F43: 96 rxn | G43: 96 | H43: 960 | I43: 2026-07-01 | J43: 10x Genomics store price list PDF (exported 2026-07-01) | K43: GEX library indices.
A44: K040 | B44: Flex v2 | C44: Protein | D44: Flex Feature Barcode Kit | E44: PN-1000628 | F44: 64 rxn | G44: 64 | H44: 2200 | I44: 2026-07-01 | J44: 10x Genomics store price list PDF (exported 2026-07-01)
A45: K041 | B45: Flex v2 | C45: Sample Prep | D45: GEM-X Flex Sample Preparation v2 Kit | E45: PN-1000781 | F45: - | G45: 48 | H45: 800 | I45: 2026-07-01 | J45: 10x Genomics store price list PDF (exported 2026-07-01) | K45: Processes 48 cell-surface or 24 intracellular samples. Processes 48 samples (CG000782/CG000834).
A46: K042 | B46: Flex v2 | C46: GEX/Library | D46: GEM-X Flex GEM & Library Kit v2 | E46: PN-1000918 | F46: 4 rxn | G46: 4 | I46: unverified | J46: CG000834 Rev C names PN-1000918 (4 rxns) for Amp Mix C / GEM & library reagents | K46: Price not in current price list export - VERIFY. Some GEM/library reagents may already be within Core Reagents (K036/K037); listed to avoid omission, left uncosted to avoid double-count.

Sheet Additional_Supply_Catalog
A1: Additional_Supply_Catalog
A2: Admin-only. Third-party consumables. Source: 10X_Reagent_Ordering_Tracker.xlsx + Reagents list.xlsx
A4: item_id | B4: applies_to_protocol | C4: reagent | D4: vendor | E4: catalog_number | F4: notes | G4: Price | H4: Stock Size (Units) | I4: Stock Units | J4: last_purchase_date | K4: sourcing_note
A5: Reagents
A6: R001 | B6: ASAP-seq | C6: Sterile Water | D6: Fisher Sci- Stockroom | E6: 10977015 | G6: 13.86 | H6: 500 | I6: mL | K6: No purchase record found for 'Sterile Water' as a standalone item - likely sourced from a shared stockroom supply not tracked as an individual purchase, or made in-house (autoclaved). Recommend confirming with lab manager.
A7: R002 | B7: ASAP-seq, CITE-seq, Sort | C7: PBS | D7: Stockroom | E7: 10010-023 | G7: 19.02 | H7: 500 | I7: mL | J7: 2025-02-12 | K7: PBS 1X, pH 7.4. Price has been rising slightly across recent orders ($16.70 -> $19.02).
A8: R003 | B8: 5' Library Prep | C8: Ethanol, 200 proof anhydrous | D8: Millipore Sigma | E8: E7023-500ML | F8: Make fresh 80% day-of. | G8: 109 | H8: 500 | I8: mL | K8: No purchase record found for this exact catalog number (Millipore Sigma E7023-500ML). Closest recent related purchases are a different brand/grade: RPI Reagent Grade Ethanol 4L, $69.53-$80 (most recent 2025-02-25) - verify these are interchangeable for your protocol before substituting.
A9: R004 | B9: 5' Library Prep | C9: Buffer EB | D9: QIAGEN | E9: 19086 | F9: Elution buffer, summed across elution steps. | G9: 49.9 | H9: 250 | I9: mL | J9: 2025-11-22 | K9: Price stable ~$49-50 across last 2 orders (special order via stockroom).
A10: R005 | B10: 5' Library Prep | C10: SPRIselect Reagent Kit | D10: Beckman Coulter | E10: B23318 | F10: Size selection / cleanups. | G10: 1635.9 | H10: 60 | I10: mL | J10: 2025-04-08 | K10: Price has varied significantly across orders ($1,558-$1,669 range); most recent shown.
A11: R006 | B11: All | C11: Qubit dsDNA HS Assay kit | D11: Thermo | E11: Q32854 | F11: 500 samples | G11: 426.65 | H11: 500 | I11: sample | K11: No exact match for PN Q32854. Closest possible successor product found: 'QUBIT 1X dsDNA HS Assay Kit, 500 rxn' (PN Q33231), Fisher Scientific, $381.65, purchased 2024-04-17 - may be a renumbered version of this kit; verify before ordering. Existing values below left unchanged.
A12: R007 | B12: All | C12: TapeStation HS D1000. | D12: Agilent Technologies | E12: 5067-5584 (ScreenTape) + 5067-5585 (Reagents) + 5067-5587 (Ladder) | G12: 606.25 | H12: 1 | I12: kit | J12: 2025-04-08 | K12: Price = sum of most recent purchases of all 3 required TapeStation components (ScreenTape $398.67 + Reagents $135.80 + Ladder $71.78). Original catalog_number also listed 5067-4626, which is actually the Bioanalyzer HS DNA kit (different, older instrument) - not part of this TapeStation bundle. Lane/sample count per kit not specified in purchase record - verify with vendor.
A13: R008 | B13: All | C13: 10% Tween 20 | D13: Bio-Rad Laboratories | E13: 1662404 | F13: Component of Elution Solution I. | G13: 40.52 | H13: 5 | I13: mL | J13: 2024-01-08 | K13: Only 1 purchase record in history (Jan 2024) - consider reverifying current price before large orders.
A14: R009 | B14: All | C14: KAPA Library Quantification Kit | D14: Roche/KAPA | E14: KK4824 | K14: No purchase record found for KAPA Library Quantification Kit (KK4824) in the provided lab spend history - vendor/price below are carried over from the original tracker, unverified.
A15: R010 | B15: ASAP-seq | C15: 16% formaldehyde | D15: Life Technologies (special order) | E15: 28906 | G15: 47 | H15: 1000 | I15: uL | J15: 2024-06-01 | K15: Pierce 16% Formaldehyde, methanol-free. A 10-ampule pack of the same PN is also available for $62.25 total (~$6.23/mL) - cheaper per-mL if buying in bulk.
A16: R011 | B16: ASAP-seq | C16: 2M Glycine | D16: Thermo Fisher Scientific | E16: A13816.36 | G16: 46.2 | H16: 500 | I16: g | J16: 2024-01-08 | K16: Glycine, 99% - only 1 purchase record found.
A17: R012 | C17: IPEGAL
A18: R013 | C18: empty place
A19: R014 | B19: ASAP-seq | C19: 1uM Bridge Oligo | I19: uL | K19: No purchase record found for '1uM Bridge Oligo' - this is a custom/specialty oligo (likely made-to-order from IDT or similar), not something that would appear as a standard catalog purchase. Recommend sourcing directly from an oligo synthesis vendor.
A20: R015 | B20: CITE-seq, ASAP-seq | C20: ADT TotalseqA antibody cocktail | D20: BioLegend | E20: 399907 (TotalSeq-A) | G20: 4546.5 | H20: 5 | I20: vial | J20: 2025-01-09 | K20: ADT = TotalSeq Universal Cocktail, used for CITE-seq/ASAP-seq antibody-derived tags. TotalSeq-C (5 test) = $4,546.50 (2025-01-09); TotalSeq-A (5 test) = $4,878.00 (2025-04-03). Price shown is for the C version; use A version price if that's what the protocol calls for.
A21: R016 | B21: CITE-seq, ASAP-seq | C21: ADT TotalseqC antibody cocktail | D21: BioLegend | E21: 399905 (TotalSeq-C) | G21: 4546.5 | H21: 5 | I21: vial | J21: 2025-01-09 | K21: ADT = TotalSeq Universal Cocktail, used for CITE-seq/ASAP-seq antibody-derived tags. TotalSeq-C (5 test) = $4,546.50 (2025-01-09); TotalSeq-A (5 test) = $4,878.00 (2025-04-03). Price shown is for the C version; use A version price if that's what the protocol calls for.
A22: R017 | B22: CITE-seq, ASAP-seq, Sort | C22: HTO TotalseqA | D22: BioLegend | E22: e.g. 394661-394689 (TotalSeq-C0251-0265 Hashtags) | G22: 517 | H22: 20 | I22: uL
A23: R018 | B23: CITE-seq, ASAP-seq, Sort | C23: HTO TotalseqC | D23: BioLegend | E23: e.g. 394661-394689 (TotalSeq-C0251-0265 Hashtags) | G23: 517 | H23: 20 | I23: uL | J23: 2025-11-22 | K23: HTO = individual TotalSeq Hashtag antibody vials, one per pool/sample. Price is per hashtag vial (recent purchases of hashtags 3, 4, 5, 15 all priced at $517 each). Need one vial per pool - do not reuse a hashtag within a batch.
A24: R019 | B24: CITE-seq, ASAP-seq, Sort | C24: Human TruStain FcX (Fc block) | D24: BioLegend | E24: 422302 | F24: OR TruStain FcX PLUS at 2 uL/sample. | G24: 229 | H24: 1000 | I24: uL
A25: R020 | B25: ASAP-seq | C25: RPxx or D7xx | I25: uL | K25: No purchase record found for 'RPxx or D7xx' - these are typically Illumina/10x sample index primer names, not a separately purchased consumable (they usually come from the Dual Index Kit already in Kit_Catalog, e.g. K005/K009/K014). Recommend removing this row or cross-referencing Kit_Catalog instead.
A26: R021 | B26: ASAP-seq | C26: 1M Tris-HCl pH 7.5 | D26: Cayman Chemical Company | E26: 600201 | G26: 44 | H26: 250 | I26: mL | J26: 2023-08-01 | K26: 1M Tris-HCl, pH 7.5. Only 1 purchase record found (2023) - reverify current price, it's 3 years stale.
A27: R022 | B27: ASAP-seq | C27: 5M NaCl | D27: Santa Cruz Biotechnology | E27: sc-295832 | G27: 14.55 | H27: 1000 | I27: mL | J27: 2023-07-31 | K27: 5M/1M NaCl solution. Only 1 purchase record found (2023) - reverify current price.
A28: R023 | B28: ASAP-seq | C28: 1M MgCl2 | D28: Thermo Fisher Scientific | E28: AM9530G | G28: 57 | H28: 100 | I28: mL | J28: 2024-03-19 | K28: 1M MgCl2.
A29: R024 | B29: ASAP-seq | C29: NP40 | D29: Thermo Fisher Scientific | E29: J19628.AP | G29: 106 | H29: 500 | I29: mL | J29: 2024-01-10 | K29: Nonidet P40 Substitute (NP-40 equivalent) - only 1 purchase record found.
A30: R025 | B30: ASAP-seq | C30: 5% Digitonin | D30: Life Technologies | E30: BN2006 | G30: 124.65 | H30: 1 | I30: mL | J30: 2025-11-05 | K30: Digitonin (5% stock).
A31: R026 | B31: ASAP-seq, CITE-seq | C31: BSA (powder) | D31: VWR | E31: 0332-25g | G31: 103.8 | H31: 25 | I31: g | J31: 2023-08-17 | K31: 10% Bovine Serum Albumin, Aqueous, Nuclease-Free - best available match for '10% BSA'. Only 1 purchase record found (2023) - reverify current price. A different product, MACS BSA Stock Solution (Miltenyi, 130-091-376), was also purchased more recently (Jan 2024) if that's an acceptable substitute.
A32: R027 | B32: Thaw | C32: RPMI | D32: Various (stockroom) | E32: 11875-093 | F32: Thawing/wash media. | G32: 6.78 | H32: 500 | I32: mL | J32: 2026-07-01 | K32: RPMI +L-Glutamine - price has been very stable (~$6.24-6.78) across the last 2+ years.
A33: R028 | B33: Thaw | C33: HEPES | D33: Cayman Chemical Company | E33: 600212 | G33: 32 | H33: 100 | I33: mL | J33: 2023-08-01 | K33: 1M HEPES stock solution. Only 1 purchase record found (2023) - reverify current price.
A34: R029 | B34: Thaw | C34: DNase (stock 10 mg/mL) | D34: STEMCELL Technologies | E34: 07470 | F34: High conc. for thaw, low conc. after. | G34: 388 | H34: 100 | I34: mg | J34: 2026-04-20 | K34: DNase I - price has been completely stable at $388 across 6 recent orders.
A35: R030 | B35: Thaw | C35: APOI Dye | D35: Revvity | E35: CS2-0106-25ML | G35: 606 | H35: 25 | I35: mL | K35: No confident match found for 'APOI Dye' - likely a viability/live-dead stain but the exact product is unclear from this name. If this refers to a Zombie fixable viability dye, BioLegend's Zombie UV Fixable Viability Kit (PN 423108, ~$89-335 depending on pack size, most recent 2025-12-04) is the closest match in purchase history - please confirm the intended product.
A36: R031 | B36: Sort | C36: Flow Antibodies | K36: 'Flow Antibodies' is too generic to match to a single SKU - the specific antibody panel depends on which markers are being sorted for. Recommend listing each antibody as its own catalog row once the sort panel is finalized.
A37: R032 | B37: Thaw, Sort | C37: FBS | D37: Stockroom | E37: A5256801 | G37: 356.71 | H37: 500 | I37: mL | J37: 2024-09-16 | K37: FBS (value grade). A higher-grade alternative, BenchMark FBS (GeminiBio, 100-106-500), was purchased more recently in smaller volume history - compare grades before restocking.
A38: R033 | B38: Stim | C38: Stimulation Reagents/ treatments | K38: 'Stimulation Reagents/treatments' is condition-dependent - see the existing Immune_Cell_Stimulation... reference table for specific stimulant catalog numbers per assay; not matchable to one SKU here.
A39: R034 | B39: Bulk RNA | C39: Trizol | D39: Stockroom / Thermo Fisher Scientific | E39: 10296-010 | G39: 263.34 | H39: 100 | I39: mL | J39: 2025-03-07 | K39: TRIzol LS Reagent, 100 mL.
A41: R035 | B41: Flex v2 | C41: Formaldehyde 37% (Fisher BioReagents) | D41: Fisher Scientific | E41: BP531-25 | F41: Fisher BioReagents BP531-25, 25 mL. List ~$101.25 (Cole-Parmer, 2026) - verify institutional price. | G41: 101.25 | H41: 25 | I41: mL | K41: Flex Fixation Buffer B (60 uL/sample). Price not on file - VERIFY.
A42: R036 | B42: Flex v2 | C42: Glycerol, >=99% (mol. biology) | D42: Millipore Sigma | E42: G5516-100ML | F42: Sigma G5516-100ML, 100 mL. List ~$62.79 (Midland Sci, 2026) - verify institutional price. | G42: 62.79 | H42: 100 | I42: mL | K42: 50% glycerol for -80C storage / unused chip wells (CG000782/CG000834). Price not on file - VERIFY.
A43: Supplies
A45: S001 | B45: All | C45: 1000 µl pipette tips | D45: Rainin (Mettler-Toledo) | E45: 17007089 | F45: As needed | G45: 46.71 | H45: 1536 | I45: tip | J45: 2025-04-03
A46: S002 | B46: All | C46: 200 µl pipette tips | D46: Rainin (Mettler-Toledo) | E46: 30389187 | F46: As needed | G46: 180.4 | H46: 9600 | I46: tip | J46: 2026-04-20 | K46: Filtered/low-retention variant (RT UNV...FL) chosen for RNA-sensitive work. A non-filtered 'GP UNV' version (PN 30389266) is available for $166/box if filtering isn't required.
A47: S003 | B47: All | C47: 20 µl pipette tips | D47: Rainin | F47: As needed | G47: 180.4 | H47: 9600 | I47: tip | K47: No matching purchase record found for 20 uL Rainin tips specifically. Purchase history only shows the L-20XLS+ pipette instrument itself, plus 200uL/1000uL tip refills. Recommend checking directly with the vendor or stockroom.
A48: S004 | B48: All | C48: DNA LoBind Tubes 1.5mL | D48: Eppendorf | E48: 022431021 | G48: 44.89 | H48: 250 | I48: tube | J48: 2026-06-25 | K48: Purchase history only shows the 1.5 mL, 250-tube pack (022431021); the 2.0 mL variant (022431048) referenced in catalog_number had no matching purchase record.
A49: S005 | C49: DNA LoBind Tubes 2mL | D49: Eppendorf | G49: 44.89 | H49: 250 | I49: tube | J49: 2026-06-25 | K49: Purchase history only shows the 1.5 mL, 250-tube pack (022431021); the 2.0 mL variant (022431048) referenced in catalog_number had no matching purchase record.
A50: S006 | C50: 15mL Conical Tube | D50: Stockroom | E50: 352097 | G50: 11.11 | H50: 50 | I50: tube
A51: S007 | C51: 50mL Conical Tube | D51: Stockroom | E51: 352070 | G51: 6.1 | H51: 25 | I51: tube
A52: S008 | B52: All | C52: PCR 8-Tube Strips (0.2 mL) | D52: USA Scientific | E52: 1402-1800 | F52: Thermal cycling. | G52: 97.55 | H52: 125 | I52: strip | J52: 2026-04-20
A53: S009 | B53: Thaw | C53: Nexcelom Counting Plate | D53: Revvity | E53: CHM24-A100-020 | G53: 5107 | H53: 200 | I53: plate | K53: No purchase record found for 'Nexcelom Counting Plate' - Nexcelom-specific consumables didn't appear in this export. Recommend checking directly with Nexcelom/PerkinElmer or the stockroom.
A54: S010 | B54: Thaw | C54: Thawsomes | D54: Aridica | G54: 195 | H54: 50 | I54: each | K54: No purchase record found for 'Thawsomes' - not a standard catalog item name (possibly an in-house nickname for cell-freezing containers, e.g. Mr. Frosty/CoolCell equivalents). Recommend clarifying the actual product with whoever wrote the original protocol.
A55: S011 | B55: ASAP-seq | C55: 40um Flowmi Strainer | D55: Sigma Aldrich | E55: BAH136800070-50EA | G55: 114 | H55: 50 | I55: each | J55: 2024-01-29 | K55: 40um Flowmi Cell Strainers.
A56: S012 | B56: All | C56: Qubit™ Assay Tubes | D56: Thermo | E56: Q32856 | F56: 500 samples | G56: 135 | H56: 500 | I56: tube | K56: No exact match for PN Q32856. If the lab has moved to the Qubit Flex platform, note that 'Qubit Flex Pyrogen-Free Tube Strip' (PN Q32893) was purchased most recently (2026-06-10, $296/120 = $2.47/tube) - confirm which platform is in current use. Existing values below left unchanged.
A57: S013 | C57: 5mL FACS Tube | D57: Falcon | E57: 352235 | F57: 5 mL round-bottom tube w/ cell-strainer cap. Price not on file - VERIFY. | G57: 19.16 | H57: 12
A58: R053 | B58: Flex v2 / QC / sort | C58: TapeStation HS D5000 | D58: Agilent | E58: 5067-5592 (ScreenTape) + 5067-5593 (reagents) | F58: cDNA/amplicon QC. Price not on file - VERIFY. (Per-sample costing needs kit sample capacity.) | H58: 1 | I58: kit | K58: cDNA/amplicon QC. Price not on file - VERIFY. (Per-sample costing needs kit sample capacity.)
A59: R054 | B59: Flex v2 / QC / sort | C59: RNA Isolation Kit | D59: Qiagen/Zymo | E59: VERIFY | F59: Bulk RNA extraction. Vendor/PN/price not on file - VERIFY. | H59: 1 | I59: sample | K59: Bulk RNA extraction. Vendor/PN/price not on file - VERIFY.
A60: R055 | B60: Flex v2 / QC / sort | C60: Sort Antibody Cocktail | D60: BioLegend | E60: custom panel | F60: FACS sort panel - lab-specific. Price not on file - VERIFY. | H60: 1 | I60: sample | K60: FACS sort panel - lab-specific. Price not on file - VERIFY.
A61: R056 | B61: Flex v2 / QC / sort | C61: L/D Zombie Red (viability dye) | D61: BioLegend | E61: 423109 | F61: Viability stain. Price not on file - VERIFY. | H61: 100 | I61: test | K61: Viability stain. Price not on file - VERIFY.
A62: R057 | B62: Flex v2 / QC / sort | C62: Compensation beads | D62: Thermo/BD | E62: 01-2222-42 | F62: Flow compensation. Price not on file - VERIFY. | H62: 1 | I62: kit | K62: Flow compensation. Price not on file - VERIFY.
A63: R059 | B63: Flex v2 / QC / sort | C63: 2x KAPA HiFi HotStart ReadyMix | D63: Roche | E63: KK2602 | F63: ASAP tag PCR. Price not on file - VERIFY. | H63: 1 | I63: mL | K63: ASAP tag PCR. Price not on file - VERIFY.
A64: R060 | B64: Flex v2 / QC / sort | C64: ASAP-P5 / index primer (custom oligo) | D64: IDT | E64: custom | F64: ASAP tag PCR primers. Price not on file - VERIFY. | H64: 1 | I64: nmol | K64: ASAP tag PCR primers. Price not on file - VERIFY.
A65: S014 | B65: Flex v2 / QC / sort | C65: FACS tube filter cap (35um) | D65: Falcon | E65: 352235 | F65: 5 mL round-bottom tube w/ cell-strainer cap. Price not on file - VERIFY. | G65: 19.16 | H65: 12 | I65: cap | K65: 5 mL round-bottom tube w/ cell-strainer cap. Price not on file - VERIFY.

Sheet Cell Pooling Calculator
A1: Batch X
A2: # | B2: sample ID | C2: Visit | D2: Group | E2: Pool | F2: Live % | G2: Total Viable Cell Count (/mL) | H2: Vol. Dilute for count (mL) | I2: Total Viable Cells | J2: Cells pooled for sort | K2: Pool Volume (uL) -- sort | L2: Cells pooled for unsort | M2: Pool Volume (uL) -- unsort | N2: Cells to RNA | O2: Volume to RNA (uL)
A3: 1 | B3: 1006 | C3: V00 | D3: P | E3: 1 | F3: 0.9 | G3: 1370000 | H3: 2.3 | I3: 3150000 | J3: 1500000 | K3: 1094.89 | N3: 500000 | O3: 364.96

Sheet Modality_Definitions
A1: Modality_Definitions
A2: Admin-only. Source: Handbook_Setting up a Single Cell Experiment (Ayers/Benmelech). Drives which stages + kits a plan pulls in.
A4: modality_id | B4: modality | C4: chemistry | D4: required_stage_ids | E4: default_target_recovered_cells | F4: typical_doublet_rate | G4: notes
A5: M001 | B5: scRNAseq | C5: GEM-X 5' v3 | E5: 8000-10000 (single sample/channel) | F5: 7.6% at 10k | G5: Standard immune profiling.
A6: M002 | B6: CITEseq | C6: GEM-X 5' v3 | E6: 5000/sample if 4-plex (20000/channel) | F6: ~15% at 20k, mitigated by hashtag demux | G6: Adds ADT library; needs antibody panel + Fc block.
A7: M003 | B7: ASAPseq | C7: Epi ATAC (TotalSeq-A) | E7: 3000-5000 (FACS-enriched) | F7: Lower; enrichment reduces load needed | G7: Nuclei prep, Tn5 tagmentation - time sensitive.
A8: M004 | B8: VDJ (TCR/BCR) | C8: GEM-X GEM-X 5' v3 (add-on) | E8: N/A - derived from GEX cDNA | F8: N/A | G8: Needs enough T/B cells for clonal expansion (~250+ cells min.).
A9: M005 | B9: Cell sorting (FACS enrichment) | C9: N/A | E9: Depends on target population | F9: N/A | G9: ~0.5% of PBMCs for pDCs, e.g.; send more cells for rare populations.
A10: M006 | B10: In vitro stimulation | C10: N/A | E10: N/A | F10: N/A | G10: Reserve 100-500k cells/sample pre-stim; see Immune Cell Stimulation Assays Table.
A11: M007 | B11: Flex (fixed RNA profiling) | C11: Flex v2 | E11: 10000-27000/sample (no sort) | F11: Lower - probe-based, less doublet-sensitive | G11: Good for banked/fixed samples; different sample-prep track.

Sheet Protocol_Stages
A1: Protocol_Stages
A2: Admin-only. Modular building blocks replacing the fragmented per-experiment protocols. Source: in-progress Handbook + MADI/IDVax batch docs.
A4: stage_id | B4: stage_name | C4: stage_description | D4: typical_time_window | E4: personnel_rule | F4: prerequisite_stage_id | G4: source_protocol_doc | H4: notes
A5: ST1 | B5: thaw | C5: Cell thawing / PBMC prep & Pooling | D5: 7-10am | E5: 1 worker per ~18 samples | G5: PBMC_Isolation_120225_AAannotated.docx / Handbook | H5: Warm media 20 min ahead; centrifuge thaw 10 min @350g.
A6: ST2 | B6: hash | C6: Pool & hash (sample pooling, HTO labeling) | D6: Immediately after thaw | E6: 1 worker per ~27 samples | G6: Handbook Batch Organization section | H6: No 2 samples from same donor/related subject in one pool.
A7: ST3 | B7: CITE-seq | C7: CITE-seq antibody staining | D7: After pooling | E7: 1 dedicated worker | G7: CITE-seq Batch2 protocol - AJ.docx; CITEseq_protocol_full.pdf | H7: Fc block first; titrate antibody panel in advance.
A8: ST4 | B8: ASAP-seq | C8: ASAP-seq nuclei prep / tagmentation | D8: After pooling, parallel to ST3 | E8: 1 dedicated worker | G8: ASAP_protocol_CHI.pdf | H8: Time-sensitive Tn5 step - do not delay.
A9: ST5 | B9: sort | C9: Cell sorting (FACS) | D9: Parallel to ST3/ST4 | E9: 1 dedicated worker + Flow Core slot | G9: Handbook Hoods/sorter section | H9: Book Yale Flow Core in advance; separate sort vs. unsort tubes.
A10: ST6 | B10: 5'-GEM | C10: 5' GEM generation & loading | D10: After staining/sorting complete | E10: 1-2 workers | G10: 10x user guides (CG000733 etc.) | H10: Superload per lab convention (skip water dilution step).
A11: ST7 | B11: ATAC-GEM | C11: Epi ATAC GEM generation & loading
A12: ST8 | B12: 5'-GEX | C12: 5' GEX Library construction & QC | D12: Days 1-5 post GEM | E12: 1-2 workers, ~1 week | G12: 10x user guides; SPRIselect User Guide | H12: cDNA QC -> library construction -> library QC -> submit to YCGA.
A13: ST9 | B13: 5'-VDJ | C13: 5' V(D)J Library Construction
A14: ST10 | B14: 5'-ADT | C14: 5' ADT Library Construction
A15: ST11 | B15: ATAC-ADT | C15: Epi ATAC ADT Library Construction
A16: ST12 | B16: ATAC | C16: Epi ATAC Library Construction
A17: ST13 | B17: stim | C17: In vitro stimulation assay | D17: Parallel track, separate reserved cells | E17: 1 worker | G17: Immune Cell Stimulation Assays Table.xlsx | H17: Reserve leftover cells after pooling; assay per stim condition chosen.
A18: ST14 | B18: Bulk-RNA | C18: Bulk RNA (Trizol) reserve | D18: After pooling, opportunistic | E18: 1-2 workers | G18: Trizol RNA Isolation SOP.pdf | H18: Reserve 100-500k leftover cells per sample.
A19: ST15 | B19: sequence | C19: Sequencing submission (YCGA) | D19: After library QC | E19: 1 worker | G19: YCGA submission.docx | H19: Submit via iLAB; confirm grant to charge with lab manager.
A20: ST16 | C20: Flex fixation / sample prep | D20: Pre-experiment or day-of (fixed samples) | E20: 1-2 workers | G20: GEM-X Flex v2 protocols (CG000833/834/835) | H20: Different track from live-cell thaw; can be banked ahead of time.

Sheet Sequencing_Pricing
A1: Sequencing_Pricing
A2: Admin-only. Source: Sequencing Options and Pricing.xlsx (2025/2026 quotes). Refresh yearly.
A4: platform_id | B4: platform | C4: configuration | D4: price_usd | E4: price_per_M_reads | F4: reads | G4: max_cycles | H4: notes
A5: S001 | B5: Nextseq 2000 (YCGA) | C5: 50c P4 | D5: 1800 | E5: 1 | F5: 1.8B | G5: 88 | H5: Walk-up, requires iLAB reservation + training.
A6: S002 | B6: Nextseq 2000 (YCGA) | C6: 100c P4 | D6: 2160 | E6: 1.46 | G6: 138
A7: S003 | B7: Nextseq 2000 (YCGA) | C7: 100c P3 | D7: 1515.8 | E7: 1.61 | F7: 1.2B | G7: 138
A8: S004 | B8: Nextseq 2000 (YCGA) | C8: 100c P2 | D8: 982.8 | E8: 3.15 | F8: 400M | G8: 138
A9: S005 | B9: Novaseq (YCGA) | C9: 2x150 group flowcell | E9: 1.049 | G9: 338 | H9: Purchase by # reads; pooled with other labs. + $25/sample QC.
A10: S006 | B10: Novaseq (YCGA) | C10: SP 2x150 (full flowcell) | D10: 2617 | E10: 3.27 | F10: 650-800M | H10: Purchase entire flowcell. + $25/sample QC.
A11: S007 | B11: MiSeq (YCGA) | C11: 500c | D11: 1905 | E11: 76.2 | F11: 22-25M | G11: 529 | H11: Purchase entire flowcell. + $25/sample QC.
A12: S008 | B12: Aviti (YCGA) | C12: 2x150 High Output | D12: 2856 | E12: 2.86 | F12: 1B | H12: + $25/sample QC.
A13: S009 | B13: Nanopore MinION | C13: Long read | D13: 800 | F13: 48Gb | H13: Available in Chung Lab; reagents extra.
A14: S010 | B14: Ultima (Novogene, external) | C14: 300bp single end | D14: 3499 | E14: 0.35 | F14: 10B | H14: V(D)J library sequencing NOT supported.

Sheet Personnel_Roster
A1: Personnel_Roster
A2: Lab-editable. Replace example rows with your real roster. trained_stage_ids references Protocol_Stages (comma-separated).
A4: person_id | B4: name | C4: role | D4: trained_stage_ids | E4: weekly_availability | F4: active | G4: notes
A5: P001 | B5: Example: Person A | C5: Grad student | D5: ST1,ST2,ST6,ST7 | E5: Mon/Wed/Fri | F5: Yes | G5: EXAMPLE ROW - replace with real roster
A6: P002 | B6: Example: Person B | C6: Research assistant | D6: ST1,ST3,ST6 | E6: Tue/Thu | F6: Yes | G6: EXAMPLE ROW - replace with real roster
A7: P003 | B7: Example: Person C | C7: Postdoc | D7: ST4,ST5,ST8 | E7: Flexible | F7: Yes | G7: EXAMPLE ROW - replace with real roster

Sheet Cell_Flow_Assumptions
A1: Cell_Flow_Assumptions
A2: Editable cell-count assumptions for the cell-flow diagram (planner Workflow tab). Edit default_value cells and re-upload; keep assumption_id and column headers unchanged.
A4: assumption_id | B4: label | C4: default_value | D4: units | E4: notes
A5: cells_per_sample_start | B5: Assumed cells available per sample | C5: 5000000 | D5: cells/sample | E5: Context only; the pooling take is fixed regardless of a sample’s actual count.
A6: cells_per_sample_pooling | B6: Cells taken per sample for pooling (CITE-seq staining input) | C6: 1500000 | D6: cells/sample | E6: Fixed amount added from each sample into its genetic pool, regardless of how many cells the sample had.
A7: cells_per_sample_bulk | B7: Cells reserved per sample for bulk RNA-seq | C7: 500000 | D7: cells/sample | E7: Set aside per sample (Trizol) for bulk RNA-seq. Required when pooling, for SNP demux.
A8: cells_per_sample_bulk_low | B8: Minimum bulk reserve for low-count samples | C8: 100000 | D8: cells/sample | E8: Floor for samples that don’t have enough to spare the full bulk reserve.
A9: cells_per_sample_stim | B9: Extra cells reserved per sample for stim | C9: 200000 | D9: cells/sample | E9: Saved per sample for the stim track.
A10: cells_per_pool_load | B10: Cells taken from each genetic pool per non-sort droplet load | C10: 1200000 | D10: cells/pool | E10: 1.2M/pool for unsort & ASAP; each per-pool tube HTO-stained (TotalSeq-C for CITE, TotalSeq-A for ASAP). Sort takes the remainder.
A11: cells_for_panel_stain | B11: Cells subsampled from the combined pool for surface-panel staining | C11: 1500000 | D11: cells/load | E11: After per-pool tubes combine, 1.5M taken for lyo-panel staining (3 vials).
A12: cells_at_load | B12: Target cells at loading / transposition | C12: 1200000 | D12: cells/load | E12: Super-load target after panel-stain washes (~1.1–1.2M).
A13: allcells_control_fraction | B13: ALLCELLS control added per pool (fraction of pooled cells) | C13: 0.25 | D13: fraction | E13: Leukopak ALLCELLS spike-in per pool (~25%). Set 0 to exclude.

Sheet Pre_GEM_Consumables
A1: Section | B1: Type | C1: Item / supply | D1: Item ID | E1: Scaling basis | F1: Amount per unit | G1: Unit | H1: Overage | I1: Count (x) | J1: Total needed | K1: Order (rounded) | L1: Unit price ($) | M1: Cost per basis-unit ($) | N1: Total cost ($) | O1: Notes | P1: _price | Q1: _stock | R1: _stockUnit
A2: II. PBMC prep | B2: BUFFER ▸ prepare | C2: RPMI-DNase (thaw media) | E2: (prep total) | G2: mL | J2: =(12*Inputs!$B$5)*(1+Inputs!$B$20) -> 712.8 | O2: Standard-recipe volume to prepare; costed components are the item rows below (see Buffer recipes).
A3: II. PBMC prep | B3: BUFFER ▸ prepare | C3: RPMI-DNase-low | E3: (prep total) | G3: mL | J3: =(50*Inputs!$B$9)*(1+Inputs!$B$20) -> 165 | O3: Standard-recipe volume to prepare; costed components are the item rows below (see Buffer recipes).
A4: II. PBMC prep | B4: Item | C4: 15mL conical | D4: S006 | E4: per sample | F4: 1 | G4: tube | H4: =Inputs!$B$20 -> 0.1 | I4: =VLOOKUP(E4,Inputs!$D$5:$E$23,2,FALSE()) -> 54 | J4: =F4*I4*(1+H4) -> 59.4 | K4: =IF(ISNUMBER(MATCH(G4,{"tube","each","plate","vial","kit","bottle","aliquot","strainer","cap","lane-rxn","tip","strip","lane","channel","library","sample"},0)),ROUNDUP(J4,0),ROUND(J4,2)) -> 60 | L4: =IFERROR(IF(OR(D4="",P4="",Q4="",Q4=0),"",IF(VLOOKUP(R4,Unit_Conversions!$A$5:$C$28,3,FALSE())=VLOOKUP(G4,Unit_Conversions!$A$5:$C$28,3,FALSE()),P4*VLOOKUP(G4,Unit_Conversions!$A$5:$C$28,2,FALSE())/(Q4*VLOOKUP(R4,Unit_Conversions!$A$5:$C$28,2,FALSE())),"")),"") -> 0.2222 | M4: =IFERROR(F4*L4,"") -> 0.2222 | N4: =IFERROR(J4*L4,"") -> 13.19868 | O4: [no catalog price] | P4: =IFERROR(IF(LEFT(D4,1)="K",VLOOKUP(D4,Kit_Catalog!$A:$K,8,FALSE()),VLOOKUP(D4,Additional_Supply_Catalog!$A:$K,7,FALSE())),"") -> 11.11 | Q4: =IFERROR(IF(LEFT(D4,1)="K",VLOOKUP(D4,Kit_Catalog!$A:$K,7,FALSE()),VLOOKUP(D4,Additional_Supply_Catalog!$A:$K,8,FALSE())),"") -> 50 | R4: =IFERROR(IF(LEFT(D4,1)="K","rxn",VLOOKUP(D4,Additional_Supply_Catalog!$A:$K,9,FALSE())),"") -> tube
A5: II. PBMC prep | B5: Item | C5: Nexcelom counting plate (24 samples/plate) | D5: S009 | E5: per sample | F5: 0.041667 | G5: plate | H5: =Inputs!$B$20 -> 0.1 | I5: =VLOOKUP(E5,Inputs!$D$5:$E$23,2,FALSE()) -> 54 | J5: =F5*I5*(1+H5) -> 2.4750198 | K5: =IF(ISNUMBER(MATCH(G5,{"tube","each","plate","vial","kit","bottle","aliquot","strainer","cap","lane-rxn","tip","strip","lane","channel","library","sample"},0)),ROUNDUP(J5,0),ROUND(J5,2)) -> 3 | L5: =IFERROR(IF(OR(D5="",P5="",Q5="",Q5=0),"",IF(VLOOKUP(R5,Unit_Conversions!$A$5:$C$28,3,FALSE())=VLOOKUP(G5,Unit_Conversions!$A$5:$C$28,3,FALSE()),P5*VLOOKUP(G5,Unit_Conversions!$A$5:$C$28,2,FALSE())/(Q5*VLOOKUP(R5,Unit_Conversions!$A$5:$C$28,2,FALSE())),"")),"") -> 25.535 | M5: =IFERROR(F5*L5,"") -> 1.0639668 | N5: =IFERROR(J5*L5,"") -> 63.199631 | O5: [no catalog price] | P5: =IFERROR(IF(LEFT(D5,1)="K",VLOOKUP(D5,Kit_Catalog!$A:$K,8,FALSE()),VLOOKUP(D5,Additional_Supply_Catalog!$A:$K,7,FALSE())),"") -> 5107 | Q5: =IFERROR(IF(LEFT(D5,1)="K",VLOOKUP(D5,Kit_Catalog!$A:$K,7,FALSE()),VLOOKUP(D5,Additional_Supply_Catalog!$A:$K,8,FALSE())),"") -> 200 | R5: =IFERROR(IF(LEFT(D5,1)="K","rxn",VLOOKUP(D5,Additional_Supply_Catalog!$A:$K,9,FALSE())),"") -> plate
A6: II. PBMC prep | B6: Item | C6: Thawsome | D6: S010 | E6: per sample | F6: 1 | G6: sample | H6: =Inputs!$B$20 -> 0.1 | I6: =VLOOKUP(E6,Inputs!$D$5:$E$23,2,FALSE()) -> 54 | J6: =F6*I6*(1+H6) -> 59.4 | K6: =IF(ISNUMBER(MATCH(G6,{"tube","each","plate","vial","kit","bottle","aliquot","strainer","cap","lane-rxn","tip","strip","lane","channel","library","sample"},0)),ROUNDUP(J6,0),ROUND(J6,2)) -> 60 | L6: =IFERROR(IF(OR(D6="",P6="",Q6="",Q6=0),"",IF(VLOOKUP(R6,Unit_Conversions!$A$5:$C$28,3,FALSE())=VLOOKUP(G6,Unit_Conversions!$A$5:$C$28,3,FALSE()),P6*VLOOKUP(G6,Unit_Conversions!$A$5:$C$28,2,FALSE())/(Q6*VLOOKUP(R6,Unit_Conversions!$A$5:$C$28,2,FALSE())),"")),"") -> 3.9 | M6: =IFERROR(F6*L6,"") -> 3.9 | N6: =IFERROR(J6*L6,"") -> 231.66 | O6: [no catalog price] | P6: =IFERROR(IF(LEFT(D6,1)="K",VLOOKUP(D6,Kit_Catalog!$A:$K,8,FALSE()),VLOOKUP(D6,Additional_Supply_Catalog!$A:$K,7,FALSE())),"") -> 195 | Q6: =IFERROR(IF(LEFT(D6,1)="K",VLOOKUP(D6,Kit_Catalog!$A:$K,7,FALSE()),VLOOKUP(D6,Additional_Supply_Catalog!$A:$K,8,FALSE())),"") -> 50 | R6: =IFERROR(IF(LEFT(D6,1)="K","rxn",VLOOKUP(D6,Additional_Supply_Catalog!$A:$K,9,FALSE())),"") -> each
A7: II. PBMC prep | B7: Item | C7: RPMI (mL) | D7: R027 | E7: per sample | F7: 13.2 | G7: mL | H7: =Inputs!$B$20 -> 0.1 | I7: =VLOOKUP(E7,Inputs!$D$5:$E$23,2,FALSE()) -> 54 | J7: =J2+J3 -> 877.8 | K7: =IF(ISNUMBER(MATCH(G7,{"tube","each","plate","vial","kit","bottle","aliquot","strainer","cap","lane-rxn","tip","strip","lane","channel","library","sample"},0)),ROUNDUP(J7,0),ROUND(J7,2)) -> 877.8 | L7: =IFERROR(IF(OR(D7="",P7="",Q7="",Q7=0),"",IF(VLOOKUP(R7,Unit_Conversions!$A$5:$C$28,3,FALSE())=VLOOKUP(G7,Unit_Conversions!$A$5:$C$28,3,FALSE()),P7*VLOOKUP(G7,Unit_Conversions!$A$5:$C$28,2,FALSE())/(Q7*VLOOKUP(R7,Unit_Conversions!$A$5:$C$28,2,FALSE())),"")),"") -> 0.01356 | M7: =IFERROR(F7*L7,"") -> 0.178992 | N7: =IFERROR(J7*L7,"") -> 11.902968 | O7: RPMI base for both media: thaw (J2) + low (J3). 1 mL RPMI per mL media. | P7: =IFERROR(IF(LEFT(D7,1)="K",VLOOKUP(D7,Kit_Catalog!$A:$K,8,FALSE()),VLOOKUP(D7,Additional_Supply_Catalog!$A:$K,7,FALSE())),"") -> 6.78 | Q7: =IFERROR(IF(LEFT(D7,1)="K",VLOOKUP(D7,Kit_Catalog!$A:$K,7,FALSE()),VLOOKUP(D7,Additional_Supply_Catalog!$A:$K,8,FALSE())),"") -> 500 | R7: =IFERROR(IF(LEFT(D7,1)="K","rxn",VLOOKUP(D7,Additional_Supply_Catalog!$A:$K,9,FALSE())),"") -> mL
A8: II. PBMC prep | B8: Item | C8: HEPES | D8: R028 | E8: per sample | F8: 0.3 | G8: mL | H8: =Inputs!$B$20 -> 0.1 | I8: =VLOOKUP(E8,Inputs!$D$5:$E$23,2,FALSE()) -> 54 | J8: =F8*I8*(1+H8) -> 17.82 | K8: =IF(ISNUMBER(MATCH(G8,{"tube","each","plate","vial","kit","bottle","aliquot","strainer","cap","lane-rxn","tip","strip","lane","channel","library","sample"},0)),ROUNDUP(J8,0),ROUND(J8,2)) -> 17.82 | L8: =IFERROR(IF(OR(D8="",P8="",Q8="",Q8=0),"",IF(VLOOKUP(R8,Unit_Conversions!$A$5:$C$28,3,FALSE())=VLOOKUP(G8,Unit_Conversions!$A$5:$C$28,3,FALSE()),P8*VLOOKUP(G8,Unit_Conversions!$A$5:$C$28,2,FALSE())/(Q8*VLOOKUP(R8,Unit_Conversions!$A$5:$C$28,2,FALSE())),"")),"") -> 0.32 | M8: =IFERROR(F8*L8,"") -> 0.096 | N8: =IFERROR(J8*L8,"") -> 5.7024 | P8: =IFERROR(IF(LEFT(D8,1)="K",VLOOKUP(D8,Kit_Catalog!$A:$K,8,FALSE()),VLOOKUP(D8,Additional_Supply_Catalog!$A:$K,7,FALSE())),"") -> 32 | Q8: =IFERROR(IF(LEFT(D8,1)="K",VLOOKUP(D8,Kit_Catalog!$A:$K,7,FALSE()),VLOOKUP(D8,Additional_Supply_Catalog!$A:$K,8,FALSE())),"") -> 100 | R8: =IFERROR(IF(LEFT(D8,1)="K","rxn",VLOOKUP(D8,Additional_Supply_Catalog!$A:$K,9,FALSE())),"") -> mL
A9: II. PBMC prep | B9: Item | C9: Dnase | D9: R029 | E9: per sample | F9: 1.05 | G9: mg | H9: =Inputs!$B$20 -> 0.1 | I9: =VLOOKUP(E9,Inputs!$D$5:$E$23,2,FALSE()) -> 54 | J9: =J2*0.1+J3*0.025 -> 75.405 | K9: =IF(ISNUMBER(MATCH(G9,{"tube","each","plate","vial","kit","bottle","aliquot","strainer","cap","lane-rxn","tip","strip","lane","channel","library","sample"},0)),ROUNDUP(J9,0),ROUND(J9,2)) -> 75.41 | L9: =IFERROR(IF(OR(D9="",P9="",Q9="",Q9=0),"",IF(VLOOKUP(R9,Unit_Conversions!$A$5:$C$28,3,FALSE())=VLOOKUP(G9,Unit_Conversions!$A$5:$C$28,3,FALSE()),P9*VLOOKUP(G9,Unit_Conversions!$A$5:$C$28,2,FALSE())/(Q9*VLOOKUP(R9,Unit_Conversions!$A$5:$C$28,2,FALSE())),"")),"") -> 3.88 | M9: =IFERROR(L9,"") -> 3.88 | N9: =IFERROR(J9*L9,"") -> 292.5714 | O9: DNase from RPMI-DNase media: thaw 0.1 mg/mL + low 0.025 mg/mL (10 mg/mL stock at recipe dilution). | P9: =IFERROR(IF(LEFT(D9,1)="K",VLOOKUP(D9,Kit_Catalog!$A:$K,8,FALSE()),VLOOKUP(D9,Additional_Supply_Catalog!$A:$K,7,FALSE())),"") -> 388 | Q9: =IFERROR(IF(LEFT(D9,1)="K",VLOOKUP(D9,Kit_Catalog!$A:$K,7,FALSE()),VLOOKUP(D9,Additional_Supply_Catalog!$A:$K,8,FALSE())),"") -> 100 | R9: =IFERROR(IF(LEFT(D9,1)="K","rxn",VLOOKUP(D9,Additional_Supply_Catalog!$A:$K,9,FALSE())),"") -> mg
A10: II. PBMC prep | B10: Item | C10: APOI Dye | D10: R030 | E10: per sample | F10: 20 | G10: uL | H10: =Inputs!$B$20 -> 0.1 | I10: =VLOOKUP(E10,Inputs!$D$5:$E$23,2,FALSE()) -> 54 | J10: =F10*I10*(1+H10) -> 1188 | K10: =IF(ISNUMBER(MATCH(G10,{"tube","each","plate","vial","kit","bottle","aliquot","strainer","cap","lane-rxn","tip","strip","lane","channel","library","sample"},0)),ROUNDUP(J10,0),ROUND(J10,2)) -> 1188 | L10: =IFERROR(IF(OR(D10="",P10="",Q10="",Q10=0),"",IF(VLOOKUP(R10,Unit_Conversions!$A$5:$C$28,3,FALSE())=VLOOKUP(G10,Unit_Conversions!$A$5:$C$28,3,FALSE()),P10*VLOOKUP(G10,Unit_Conversions!$A$5:$C$28,2,FALSE())/(Q10*VLOOKUP(R10,Unit_Conversions!$A$5:$C$28,2,FALSE())),"")),"") -> 0.02424 | M10: =IFERROR(F10*L10,"") -> 0.4848 | N10: =IFERROR(J10*L10,"") -> 28.79712 | O10: [no catalog price] | P10: =IFERROR(IF(LEFT(D10,1)="K",VLOOKUP(D10,Kit_Catalog!$A:$K,8,FALSE()),VLOOKUP(D10,Additional_Supply_Catalog!$A:$K,7,FALSE())),"") -> 606 | Q10: =IFERROR(IF(LEFT(D10,1)="K",VLOOKUP(D10,Kit_Catalog!$A:$K,7,FALSE()),VLOOKUP(D10,Additional_Supply_Catalog!$A:$K,8,FALSE())),"") -> 25 | R10: =IFERROR(IF(LEFT(D10,1)="K","rxn",VLOOKUP(D10,Additional_Supply_Catalog!$A:$K,9,FALSE())),"") -> mL
A11: II. PBMC prep | B11: Item | C11: 50mL conical | D11: S007 | E11: per genetic pool | F11: 1 | G11: tube | H11: =Inputs!$B$20 -> 0.1 | I11: =VLOOKUP(E11,Inputs!$D$5:$E$23,2,FALSE()) -> 6 | J11: =F11*I11*(1+H11) -> 6.6 | K11: =IF(ISNUMBER(MATCH(G11,{"tube","each","plate","vial","kit","bottle","aliquot","strainer","cap","lane-rxn","tip","strip","lane","channel","library","sample"},0)),ROUNDUP(J11,0),ROUND(J11,2)) -> 7 | L11: =IFERROR(IF(OR(D11="",P11="",Q11="",Q11=0),"",IF(VLOOKUP(R11,Unit_Conversions!$A$5:$C$28,3,FALSE())=VLOOKUP(G11,Unit_Conversions!$A$5:$C$28,3,FALSE()),P11*VLOOKUP(G11,Unit_Conversions!$A$5:$C$28,2,FALSE())/(Q11*VLOOKUP(R11,Unit_Conversions!$A$5:$C$28,2,FALSE())),"")),"") -> 0.244 | M11: =IFERROR(F11*L11,"") -> 0.244 | N11: =IFERROR(J11*L11,"") -> 1.6104 | O11: [no catalog price] | P11: =IFERROR(IF(LEFT(D11,1)="K",VLOOKUP(D11,Kit_Catalog!$A:$K,8,FALSE()),VLOOKUP(D11,Additional_Supply_Catalog!$A:$K,7,FALSE())),"") -> 6.1 | Q11: =IFERROR(IF(LEFT(D11,1)="K",VLOOKUP(D11,Kit_Catalog!$A:$K,7,FALSE()),VLOOKUP(D11,Additional_Supply_Catalog!$A:$K,8,FALSE())),"") -> 25 | R11: =IFERROR(IF(LEFT(D11,1)="K","rxn",VLOOKUP(D11,Additional_Supply_Catalog!$A:$K,9,FALSE())),"") -> tube
A12: II. PBMC prep | B12: Item | C12: 50mL conical | D12: S007 | E12: per super-pool | F12: 1 | G12: tube | H12: =Inputs!$B$20 -> 0.1 | I12: =VLOOKUP(E12,Inputs!$D$5:$E$23,2,FALSE()) -> 1 | J12: =F12*I12*(1+H12) -> 1.1 | K12: =IF(ISNUMBER(MATCH(G12,{"tube","each","plate","vial","kit","bottle","aliquot","strainer","cap","lane-rxn","tip","strip","lane","channel","library","sample"},0)),ROUNDUP(J12,0),ROUND(J12,2)) -> 2 | L12: =IFERROR(IF(OR(D12="",P12="",Q12="",Q12=0),"",IF(VLOOKUP(R12,Unit_Conversions!$A$5:$C$28,3,FALSE())=VLOOKUP(G12,Unit_Conversions!$A$5:$C$28,3,FALSE()),P12*VLOOKUP(G12,Unit_Conversions!$A$5:$C$28,2,FALSE())/(Q12*VLOOKUP(R12,Unit_Conversions!$A$5:$C$28,2,FALSE())),"")),"") -> 0.244 | M12: =IFERROR(F12*L12,"") -> 0.244 | N12: =IFERROR(J12*L12,"") -> 0.2684 | O12: [no catalog price] | P12: =IFERROR(IF(LEFT(D12,1)="K",VLOOKUP(D12,Kit_Catalog!$A:$K,8,FALSE()),VLOOKUP(D12,Additional_Supply_Catalog!$A:$K,7,FALSE())),"") -> 6.1 | Q12: =IFERROR(IF(LEFT(D12,1)="K",VLOOKUP(D12,Kit_Catalog!$A:$K,7,FALSE()),VLOOKUP(D12,Additional_Supply_Catalog!$A:$K,8,FALSE())),"") -> 25 | R12: =IFERROR(IF(LEFT(D12,1)="K","rxn",VLOOKUP(D12,Additional_Supply_Catalog!$A:$K,9,FALSE())),"") -> tube
A13: II. PBMC prep | B13: Item | C13: ALLCELLS control aliquot | E13: per genetic pool | F13: 1 | G13: aliquot | H13: =Inputs!$B$20 -> 0.1 | I13: =VLOOKUP(E13,Inputs!$D$5:$E$23,2,FALSE()) -> 6 | J13: =F13*I13*(1+H13) -> 6.6 | K13: =IF(ISNUMBER(MATCH(G13,{"tube","each","plate","vial","kit","bottle","aliquot","strainer","cap","lane-rxn","tip","strip","lane","channel","library","sample"},0)),ROUNDUP(J13,0),ROUND(J13,2)) -> 7 | L13: =IFERROR(IF(OR(D13="",P13="",Q13="",Q13=0),"",IF(VLOOKUP(R13,Unit_Conversions!$A$5:$C$28,3,FALSE())=VLOOKUP(G13,Unit_Conversions!$A$5:$C$28,3,FALSE()),P13*VLOOKUP(G13,Unit_Conversions!$A$5:$C$28,2,FALSE())/(Q13*VLOOKUP(R13,Unit_Conversions!$A$5:$C$28,2,FALSE())),"")),"") | M13: =IFERROR(F13*L13,"") | N13: =IFERROR(J13*L13,"") | O13: ADDED (was missing): one control per pool. [no catalog price] | P13: =IFERROR(IF(LEFT(D13,1)="K",VLOOKUP(D13,Kit_Catalog!$A:$K,8,FALSE()),VLOOKUP(D13,Additional_Supply_Catalog!$A:$K,7,FALSE())),"") | Q13: =IFERROR(IF(LEFT(D13,1)="K",VLOOKUP(D13,Kit_Catalog!$A:$K,7,FALSE()),VLOOKUP(D13,Additional_Supply_Catalog!$A:$K,8,FALSE())),"") | R13: =IFERROR(IF(LEFT(D13,1)="K","rxn",VLOOKUP(D13,Additional_Supply_Catalog!$A:$K,9,FALSE())),"")
A14: III. Unsort CITE-seq stain | B14: BUFFER ▸ prepare | C14: Staining buffer (PBS+2% BSA) | E14: (prep total) | G14: mL | J14: =(14*Inputs!$B$6 + 3.1*Inputs!$B$7)*(1+Inputs!$B$20) -> 95.81 | O14: Standard-recipe volume to prepare; costed components are the item rows below (see Buffer recipes).
A15: III. Unsort CITE-seq stain | B15: Item | C15: 2mL eppendorf | D15: S005 | E15: per genetic pool | F15: 1 | G15: each | H15: =Inputs!$B$20 -> 0.1 | I15: =VLOOKUP(E15,Inputs!$D$5:$E$23,2,FALSE()) -> 6 | J15: =F15*I15*(1+H15) -> 6.6 | K15: =IF(ISNUMBER(MATCH(G15,{"tube","each","plate","vial","kit","bottle","aliquot","strainer","cap","lane-rxn","tip","strip","lane","channel","library","sample"},0)),ROUNDUP(J15,0),ROUND(J15,2)) -> 7 | L15: =IFERROR(IF(OR(D15="",P15="",Q15="",Q15=0),"",IF(VLOOKUP(R15,Unit_Conversions!$A$5:$C$28,3,FALSE())=VLOOKUP(G15,Unit_Conversions!$A$5:$C$28,3,FALSE()),P15*VLOOKUP(G15,Unit_Conversions!$A$5:$C$28,2,FALSE())/(Q15*VLOOKUP(R15,Unit_Conversions!$A$5:$C$28,2,FALSE())),"")),"") -> 0.17956 | M15: =IFERROR(F15*L15,"") -> 0.17956 | N15: =IFERROR(J15*L15,"") -> 1.185096 | P15: =IFERROR(IF(LEFT(D15,1)="K",VLOOKUP(D15,Kit_Catalog!$A:$K,8,FALSE()),VLOOKUP(D15,Additional_Supply_Catalog!$A:$K,7,FALSE())),"") -> 44.89 | Q15: =IFERROR(IF(LEFT(D15,1)="K",VLOOKUP(D15,Kit_Catalog!$A:$K,7,FALSE()),VLOOKUP(D15,Additional_Supply_Catalog!$A:$K,8,FALSE())),"") -> 250 | R15: =IFERROR(IF(LEFT(D15,1)="K","rxn",VLOOKUP(D15,Additional_Supply_Catalog!$A:$K,9,FALSE())),"") -> tube
A16: III. Unsort CITE-seq stain | B16: Item | C16: 50mL conical | D16: S007 | E16: per genetic pool | F16: 1 | G16: tube | H16: =Inputs!$B$20 -> 0.1 | I16: =VLOOKUP(E16,Inputs!$D$5:$E$23,2,FALSE()) -> 6 | J16: =F16*I16*(1+H16) -> 6.6 | K16: =IF(ISNUMBER(MATCH(G16,{"tube","each","plate","vial","kit","bottle","aliquot","strainer","cap","lane-rxn","tip","strip","lane","channel","library","sample"},0)),ROUNDUP(J16,0),ROUND(J16,2)) -> 7 | L16: =IFERROR(IF(OR(D16="",P16="",Q16="",Q16=0),"",IF(VLOOKUP(R16,Unit_Conversions!$A$5:$C$28,3,FALSE())=VLOOKUP(G16,Unit_Conversions!$A$5:$C$28,3,FALSE()),P16*VLOOKUP(G16,Unit_Conversions!$A$5:$C$28,2,FALSE())/(Q16*VLOOKUP(R16,Unit_Conversions!$A$5:$C$28,2,FALSE())),"")),"") -> 0.244 | M16: =IFERROR(F16*L16,"") -> 0.244 | N16: =IFERROR(J16*L16,"") -> 1.6104 | O16: [no catalog price] | P16: =IFERROR(IF(LEFT(D16,1)="K",VLOOKUP(D16,Kit_Catalog!$A:$K,8,FALSE()),VLOOKUP(D16,Additional_Supply_Catalog!$A:$K,7,FALSE())),"") -> 6.1 | Q16: =IFERROR(IF(LEFT(D16,1)="K",VLOOKUP(D16,Kit_Catalog!$A:$K,7,FALSE()),VLOOKUP(D16,Additional_Supply_Catalog!$A:$K,8,FALSE())),"") -> 25 | R16: =IFERROR(IF(LEFT(D16,1)="K","rxn",VLOOKUP(D16,Additional_Supply_Catalog!$A:$K,9,FALSE())),"") -> tube
A17: III. Unsort CITE-seq stain | B17: Item | C17: 40um Flowmi Strainer | D17: S011 | E17: per genetic pool | F17: 1 | G17: sample | H17: =Inputs!$B$20 -> 0.1 | I17: =VLOOKUP(E17,Inputs!$D$5:$E$23,2,FALSE()) -> 6 | J17: =F17*I17*(1+H17) -> 6.6 | K17: =IF(ISNUMBER(MATCH(G17,{"tube","each","plate","vial","kit","bottle","aliquot","strainer","cap","lane-rxn","tip","strip","lane","channel","library","sample"},0)),ROUNDUP(J17,0),ROUND(J17,2)) -> 7 | L17: =IFERROR(IF(OR(D17="",P17="",Q17="",Q17=0),"",IF(VLOOKUP(R17,Unit_Conversions!$A$5:$C$28,3,FALSE())=VLOOKUP(G17,Unit_Conversions!$A$5:$C$28,3,FALSE()),P17*VLOOKUP(G17,Unit_Conversions!$A$5:$C$28,2,FALSE())/(Q17*VLOOKUP(R17,Unit_Conversions!$A$5:$C$28,2,FALSE())),"")),"") -> 2.28 | M17: =IFERROR(F17*L17,"") -> 2.28 | N17: =IFERROR(J17*L17,"") -> 15.048 | P17: =IFERROR(IF(LEFT(D17,1)="K",VLOOKUP(D17,Kit_Catalog!$A:$K,8,FALSE()),VLOOKUP(D17,Additional_Supply_Catalog!$A:$K,7,FALSE())),"") -> 114 | Q17: =IFERROR(IF(LEFT(D17,1)="K",VLOOKUP(D17,Kit_Catalog!$A:$K,7,FALSE()),VLOOKUP(D17,Additional_Supply_Catalog!$A:$K,8,FALSE())),"") -> 50 | R17: =IFERROR(IF(LEFT(D17,1)="K","rxn",VLOOKUP(D17,Additional_Supply_Catalog!$A:$K,9,FALSE())),"") -> each
A18: III. Unsort CITE-seq stain | B18: Item | C18: 5mL FACS tube | D18: S013 | E18: per genetic pool | F18: 1 | G18: tube | H18: =Inputs!$B$20 -> 0.1 | I18: =VLOOKUP(E18,Inputs!$D$5:$E$23,2,FALSE()) -> 6 | J18: =F18*I18*(1+H18) -> 6.6 | K18: =IF(ISNUMBER(MATCH(G18,{"tube","each","plate","vial","kit","bottle","aliquot","strainer","cap","lane-rxn","tip","strip","lane","channel","library","sample"},0)),ROUNDUP(J18,0),ROUND(J18,2)) -> 7 | L18: =IFERROR(IF(OR(D18="",P18="",Q18="",Q18=0),"",IF(VLOOKUP(R18,Unit_Conversions!$A$5:$C$28,3,FALSE())=VLOOKUP(G18,Unit_Conversions!$A$5:$C$28,3,FALSE()),P18*VLOOKUP(G18,Unit_Conversions!$A$5:$C$28,2,FALSE())/(Q18*VLOOKUP(R18,Unit_Conversions!$A$5:$C$28,2,FALSE())),"")),"") | M18: =IFERROR(F18*L18,"") | N18: =IFERROR(J18*L18,"") | O18: [no catalog price] | P18: =IFERROR(IF(LEFT(D18,1)="K",VLOOKUP(D18,Kit_Catalog!$A:$K,8,FALSE()),VLOOKUP(D18,Additional_Supply_Catalog!$A:$K,7,FALSE())),"") -> 19.16 | Q18: =IFERROR(IF(LEFT(D18,1)="K",VLOOKUP(D18,Kit_Catalog!$A:$K,7,FALSE()),VLOOKUP(D18,Additional_Supply_Catalog!$A:$K,8,FALSE())),"") -> 12 | R18: =IFERROR(IF(LEFT(D18,1)="K","rxn",VLOOKUP(D18,Additional_Supply_Catalog!$A:$K,9,FALSE())),"") -> 0
A19: III. Unsort CITE-seq stain | B19: Item | C19: TotalseqC HTO | D19: R018 | E19: per genetic pool | F19: 2 | G19: uL | H19: =Inputs!$B$20 -> 0.1 | I19: =VLOOKUP(E19,Inputs!$D$5:$E$23,2,FALSE()) -> 6 | J19: =F19*I19*(1+H19) -> 13.2 | K19: =IF(ISNUMBER(MATCH(G19,{"tube","each","plate","vial","kit","bottle","aliquot","strainer","cap","lane-rxn","tip","strip","lane","channel","library","sample"},0)),ROUNDUP(J19,0),ROUND(J19,2)) -> 13.2 | L19: =IFERROR(IF(OR(D19="",P19="",Q19="",Q19=0),"",IF(VLOOKUP(R19,Unit_Conversions!$A$5:$C$28,3,FALSE())=VLOOKUP(G19,Unit_Conversions!$A$5:$C$28,3,FALSE()),P19*VLOOKUP(G19,Unit_Conversions!$A$5:$C$28,2,FALSE())/(Q19*VLOOKUP(R19,Unit_Conversions!$A$5:$C$28,2,FALSE())),"")),"") -> 25.85 | M19: =IFERROR(F19*L19,"") -> 51.7 | N19: =IFERROR(J19*L19,"") -> 341.22 | P19: =IFERROR(IF(LEFT(D19,1)="K",VLOOKUP(D19,Kit_Catalog!$A:$K,8,FALSE()),VLOOKUP(D19,Additional_Supply_Catalog!$A:$K,7,FALSE())),"") -> 517 | Q19: =IFERROR(IF(LEFT(D19,1)="K",VLOOKUP(D19,Kit_Catalog!$A:$K,7,FALSE()),VLOOKUP(D19,Additional_Supply_Catalog!$A:$K,8,FALSE())),"") -> 20 | R19: =IFERROR(IF(LEFT(D19,1)="K","rxn",VLOOKUP(D19,Additional_Supply_Catalog!$A:$K,9,FALSE())),"") -> uL
A20: III. Unsort CITE-seq stain | B20: Item | C20: Fc Block | D20: R019 | E20: per genetic pool | F20: 10 | G20: uL | H20: =Inputs!$B$20 -> 0.1 | I20: =VLOOKUP(E20,Inputs!$D$5:$E$23,2,FALSE()) -> 6 | J20: =F20*I20*(1+H20) -> 66 | K20: =IF(ISNUMBER(MATCH(G20,{"tube","each","plate","vial","kit","bottle","aliquot","strainer","cap","lane-rxn","tip","strip","lane","channel","library","sample"},0)),ROUNDUP(J20,0),ROUND(J20,2)) -> 66 | L20: =IFERROR(IF(OR(D20="",P20="",Q20="",Q20=0),"",IF(VLOOKUP(R20,Unit_Conversions!$A$5:$C$28,3,FALSE())=VLOOKUP(G20,Unit_Conversions!$A$5:$C$28,3,FALSE()),P20*VLOOKUP(G20,Unit_Conversions!$A$5:$C$28,2,FALSE())/(Q20*VLOOKUP(R20,Unit_Conversions!$A$5:$C$28,2,FALSE())),"")),"") -> 0.229 | M20: =IFERROR(F20*L20,"") -> 2.29 | N20: =IFERROR(J20*L20,"") -> 15.114 | P20: =IFERROR(IF(LEFT(D20,1)="K",VLOOKUP(D20,Kit_Catalog!$A:$K,8,FALSE()),VLOOKUP(D20,Additional_Supply_Catalog!$A:$K,7,FALSE())),"") -> 229 | Q20: =IFERROR(IF(LEFT(D20,1)="K",VLOOKUP(D20,Kit_Catalog!$A:$K,7,FALSE()),VLOOKUP(D20,Additional_Supply_Catalog!$A:$K,8,FALSE())),"") -> 1000 | R20: =IFERROR(IF(LEFT(D20,1)="K","rxn",VLOOKUP(D20,Additional_Supply_Catalog!$A:$K,9,FALSE())),"") -> uL
A21: III. Unsort CITE-seq stain | B21: Item | C21: BSA (powder) | D21: R026 | E21: per genetic pool | F21: 0.38 | G21: g | H21: =Inputs!$B$20 -> 0.1 | I21: =VLOOKUP(E21,Inputs!$D$5:$E$23,2,FALSE()) -> 6 | J21: =F21*I21*(1+H21) -> 2.508 | K21: =IF(ISNUMBER(MATCH(G21,{"tube","each","plate","vial","kit","bottle","aliquot","strainer","cap","lane-rxn","tip","strip","lane","channel","library","sample"},0)),ROUNDUP(J21,0),ROUND(J21,2)) -> 2.51 | L21: =IFERROR(IF(OR(D21="",P21="",Q21="",Q21=0),"",IF(VLOOKUP(R21,Unit_Conversions!$A$5:$C$28,3,FALSE())=VLOOKUP(G21,Unit_Conversions!$A$5:$C$28,3,FALSE()),P21*VLOOKUP(G21,Unit_Conversions!$A$5:$C$28,2,FALSE())/(Q21*VLOOKUP(R21,Unit_Conversions!$A$5:$C$28,2,FALSE())),"")),"") -> 4.152 | M21: =IFERROR(F21*L21,"") -> 1.57776 | N21: =IFERROR(J21*L21,"") -> 10.413216 | O21: BSA now tracked as grams of powder (2% w/v staining buffer = 0.02 g/mL). Enter powder $/g in Additional_Supply_Catalog R026. 0.28 g = 2% x 14 mL PBS. | P21: =IFERROR(IF(LEFT(D21,1)="K",VLOOKUP(D21,Kit_Catalog!$A:$K,8,FALSE()),VLOOKUP(D21,Additional_Supply_Catalog!$A:$K,7,FALSE())),"") -> 103.8 | Q21: =IFERROR(IF(LEFT(D21,1)="K",VLOOKUP(D21,Kit_Catalog!$A:$K,7,FALSE()),VLOOKUP(D21,Additional_Supply_Catalog!$A:$K,8,FALSE())),"") -> 25 | R21: =IFERROR(IF(LEFT(D21,1)="K","rxn",VLOOKUP(D21,Additional_Supply_Catalog!$A:$K,9,FALSE())),"") -> g
A22: III. Unsort CITE-seq stain | B22: Item | C22: 1X PBS | D22: R002 | E22: per genetic pool | F22: 19 | G22: mL | H22: =Inputs!$B$20 -> 0.1 | I22: =VLOOKUP(E22,Inputs!$D$5:$E$23,2,FALSE()) -> 6 | J22: =F22*I22*(1+H22) -> 125.4 | K22: =IF(ISNUMBER(MATCH(G22,{"tube","each","plate","vial","kit","bottle","aliquot","strainer","cap","lane-rxn","tip","strip","lane","channel","library","sample"},0)),ROUNDUP(J22,0),ROUND(J22,2)) -> 125.4 | L22: =IFERROR(IF(OR(D22="",P22="",Q22="",Q22=0),"",IF(VLOOKUP(R22,Unit_Conversions!$A$5:$C$28,3,FALSE())=VLOOKUP(G22,Unit_Conversions!$A$5:$C$28,3,FALSE()),P22*VLOOKUP(G22,Unit_Conversions!$A$5:$C$28,2,FALSE())/(Q22*VLOOKUP(R22,Unit_Conversions!$A$5:$C$28,2,FALSE())),"")),"") -> 0.03804 | M22: =IFERROR(F22*L22,"") -> 0.72276 | N22: =IFERROR(J22*L22,"") -> 4.770216 | P22: =IFERROR(IF(LEFT(D22,1)="K",VLOOKUP(D22,Kit_Catalog!$A:$K,8,FALSE()),VLOOKUP(D22,Additional_Supply_Catalog!$A:$K,7,FALSE())),"") -> 19.02 | Q22: =IFERROR(IF(LEFT(D22,1)="K",VLOOKUP(D22,Kit_Catalog!$A:$K,7,FALSE()),VLOOKUP(D22,Additional_Supply_Catalog!$A:$K,8,FALSE())),"") -> 500 | R22: =IFERROR(IF(LEFT(D22,1)="K","rxn",VLOOKUP(D22,Additional_Supply_Catalog!$A:$K,9,FALSE())),"") -> mL
A23: III. Unsort CITE-seq stain | B23: Item | C23: TotalseqC Antibody Cocktail | D23: R016 | E23: per super-pool | F23: 3 | G23: vial | H23: =Inputs!$B$20 -> 0.1 | I23: =VLOOKUP(E23,Inputs!$D$5:$E$23,2,FALSE()) -> 1 | J23: =F23*I23*(1+H23) -> 3.3 | K23: =IF(ISNUMBER(MATCH(G23,{"tube","each","plate","vial","kit","bottle","aliquot","strainer","cap","lane-rxn","tip","strip","lane","channel","library","sample"},0)),ROUNDUP(J23,0),ROUND(J23,2)) -> 4 | L23: =IFERROR(IF(OR(D23="",P23="",Q23="",Q23=0),"",IF(VLOOKUP(R23,Unit_Conversions!$A$5:$C$28,3,FALSE())=VLOOKUP(G23,Unit_Conversions!$A$5:$C$28,3,FALSE()),P23*VLOOKUP(G23,Unit_Conversions!$A$5:$C$28,2,FALSE())/(Q23*VLOOKUP(R23,Unit_Conversions!$A$5:$C$28,2,FALSE())),"")),"") -> 909.3 | M23: =IFERROR(F23*L23,"") -> 2727.9 | N23: =IFERROR(J23*L23,"") -> 3000.69 | P23: =IFERROR(IF(LEFT(D23,1)="K",VLOOKUP(D23,Kit_Catalog!$A:$K,8,FALSE()),VLOOKUP(D23,Additional_Supply_Catalog!$A:$K,7,FALSE())),"") -> 4546.5 | Q23: =IFERROR(IF(LEFT(D23,1)="K",VLOOKUP(D23,Kit_Catalog!$A:$K,7,FALSE()),VLOOKUP(D23,Additional_Supply_Catalog!$A:$K,8,FALSE())),"") -> 5 | R23: =IFERROR(IF(LEFT(D23,1)="K","rxn",VLOOKUP(D23,Additional_Supply_Catalog!$A:$K,9,FALSE())),"") -> vial
A24: III. Unsort CITE-seq stain | B24: Item | C24: 1X PBS | D24: R002 | E24: per super-pool | F24: 9 | G24: mL | H24: =Inputs!$B$20 -> 0.1 | I24: =VLOOKUP(E24,Inputs!$D$5:$E$23,2,FALSE()) -> 1 | J24: =F24*I24*(1+H24) -> 9.9 | K24: =IF(ISNUMBER(MATCH(G24,{"tube","each","plate","vial","kit","bottle","aliquot","strainer","cap","lane-rxn","tip","strip","lane","channel","library","sample"},0)),ROUNDUP(J24,0),ROUND(J24,2)) -> 9.9 | L24: =IFERROR(IF(OR(D24="",P24="",Q24="",Q24=0),"",IF(VLOOKUP(R24,Unit_Conversions!$A$5:$C$28,3,FALSE())=VLOOKUP(G24,Unit_Conversions!$A$5:$C$28,3,FALSE()),P24*VLOOKUP(G24,Unit_Conversions!$A$5:$C$28,2,FALSE())/(Q24*VLOOKUP(R24,Unit_Conversions!$A$5:$C$28,2,FALSE())),"")),"") -> 0.03804 | M24: =IFERROR(F24*L24,"") -> 0.34236 | N24: =IFERROR(J24*L24,"") -> 0.376596 | P24: =IFERROR(IF(LEFT(D24,1)="K",VLOOKUP(D24,Kit_Catalog!$A:$K,8,FALSE()),VLOOKUP(D24,Additional_Supply_Catalog!$A:$K,7,FALSE())),"") -> 19.02 | Q24: =IFERROR(IF(LEFT(D24,1)="K",VLOOKUP(D24,Kit_Catalog!$A:$K,7,FALSE()),VLOOKUP(D24,Additional_Supply_Catalog!$A:$K,8,FALSE())),"") -> 500 | R24: =IFERROR(IF(LEFT(D24,1)="K","rxn",VLOOKUP(D24,Additional_Supply_Catalog!$A:$K,9,FALSE())),"") -> mL
A25: III. Unsort CITE-seq stain | B25: Item | C25: BSA (powder) | D25: R026 | E25: per super-pool | F25: 0.18 | G25: g | H25: =Inputs!$B$20 -> 0.1 | I25: =VLOOKUP(E25,Inputs!$D$5:$E$23,2,FALSE()) -> 1 | J25: =F25*I25*(1+H25) -> 0.198 | K25: =IF(ISNUMBER(MATCH(G25,{"tube","each","plate","vial","kit","bottle","aliquot","strainer","cap","lane-rxn","tip","strip","lane","channel","library","sample"},0)),ROUNDUP(J25,0),ROUND(J25,2)) -> 0.2 | L25: =IFERROR(IF(OR(D25="",P25="",Q25="",Q25=0),"",IF(VLOOKUP(R25,Unit_Conversions!$A$5:$C$28,3,FALSE())=VLOOKUP(G25,Unit_Conversions!$A$5:$C$28,3,FALSE()),P25*VLOOKUP(G25,Unit_Conversions!$A$5:$C$28,2,FALSE())/(Q25*VLOOKUP(R25,Unit_Conversions!$A$5:$C$28,2,FALSE())),"")),"") -> 4.152 | M25: =IFERROR(F25*L25,"") -> 0.74736 | N25: =IFERROR(J25*L25,"") -> 0.822096 | O25: BSA now tracked as grams of powder (2% w/v staining buffer = 0.02 g/mL). Enter powder $/g in Additional_Supply_Catalog R026. 0.18 g = 2% x 9 mL PBS. | P25: =IFERROR(IF(LEFT(D25,1)="K",VLOOKUP(D25,Kit_Catalog!$A:$K,8,FALSE()),VLOOKUP(D25,Additional_Supply_Catalog!$A:$K,7,FALSE())),"") -> 103.8 | Q25: =IFERROR(IF(LEFT(D25,1)="K",VLOOKUP(D25,Kit_Catalog!$A:$K,7,FALSE()),VLOOKUP(D25,Additional_Supply_Catalog!$A:$K,8,FALSE())),"") -> 25 | R25: =IFERROR(IF(LEFT(D25,1)="K","rxn",VLOOKUP(D25,Additional_Supply_Catalog!$A:$K,9,FALSE())),"") -> g
A26: III. Unsort CITE-seq stain | B26: Item | C26: 2mL eppendorf | D26: S005 | E26: per super-pool | F26: 1 | G26: tube | H26: =Inputs!$B$20 -> 0.1 | I26: =VLOOKUP(E26,Inputs!$D$5:$E$23,2,FALSE()) -> 1 | J26: =F26*I26*(1+H26) -> 1.1 | K26: =IF(ISNUMBER(MATCH(G26,{"tube","each","plate","vial","kit","bottle","aliquot","strainer","cap","lane-rxn","tip","strip","lane","channel","library","sample"},0)),ROUNDUP(J26,0),ROUND(J26,2)) -> 2 | L26: =IFERROR(IF(OR(D26="",P26="",Q26="",Q26=0),"",IF(VLOOKUP(R26,Unit_Conversions!$A$5:$C$28,3,FALSE())=VLOOKUP(G26,Unit_Conversions!$A$5:$C$28,3,FALSE()),P26*VLOOKUP(G26,Unit_Conversions!$A$5:$C$28,2,FALSE())/(Q26*VLOOKUP(R26,Unit_Conversions!$A$5:$C$28,2,FALSE())),"")),"") -> 0.17956 | M26: =IFERROR(F26*L26,"") -> 0.17956 | N26: =IFERROR(J26*L26,"") -> 0.197516 | P26: =IFERROR(IF(LEFT(D26,1)="K",VLOOKUP(D26,Kit_Catalog!$A:$K,8,FALSE()),VLOOKUP(D26,Additional_Supply_Catalog!$A:$K,7,FALSE())),"") -> 44.89 | Q26: =IFERROR(IF(LEFT(D26,1)="K",VLOOKUP(D26,Kit_Catalog!$A:$K,7,FALSE()),VLOOKUP(D26,Additional_Supply_Catalog!$A:$K,8,FALSE())),"") -> 250 | R26: =IFERROR(IF(LEFT(D26,1)="K","rxn",VLOOKUP(D26,Additional_Supply_Catalog!$A:$K,9,FALSE())),"") -> tube
A27: III. Unsort CITE-seq stain | B27: Item | C27: 50mL conical | D27: S007 | E27: per super-pool | F27: 1 | G27: tube | H27: =Inputs!$B$20 -> 0.1 | I27: =VLOOKUP(E27,Inputs!$D$5:$E$23,2,FALSE()) -> 1 | J27: =F27*I27*(1+H27) -> 1.1 | K27: =IF(ISNUMBER(MATCH(G27,{"tube","each","plate","vial","kit","bottle","aliquot","strainer","cap","lane-rxn","tip","strip","lane","channel","library","sample"},0)),ROUNDUP(J27,0),ROUND(J27,2)) -> 2 | L27: =IFERROR(IF(OR(D27="",P27="",Q27="",Q27=0),"",IF(VLOOKUP(R27,Unit_Conversions!$A$5:$C$28,3,FALSE())=VLOOKUP(G27,Unit_Conversions!$A$5:$C$28,3,FALSE()),P27*VLOOKUP(G27,Unit_Conversions!$A$5:$C$28,2,FALSE())/(Q27*VLOOKUP(R27,Unit_Conversions!$A$5:$C$28,2,FALSE())),"")),"") -> 0.244 | M27: =IFERROR(F27*L27,"") -> 0.244 | N27: =IFERROR(J27*L27,"") -> 0.2684 | O27: [no catalog price] | P27: =IFERROR(IF(LEFT(D27,1)="K",VLOOKUP(D27,Kit_Catalog!$A:$K,8,FALSE()),VLOOKUP(D27,Additional_Supply_Catalog!$A:$K,7,FALSE())),"") -> 6.1 | Q27: =IFERROR(IF(LEFT(D27,1)="K",VLOOKUP(D27,Kit_Catalog!$A:$K,7,FALSE()),VLOOKUP(D27,Additional_Supply_Catalog!$A:$K,8,FALSE())),"") -> 25 | R27: =IFERROR(IF(LEFT(D27,1)="K","rxn",VLOOKUP(D27,Additional_Supply_Catalog!$A:$K,9,FALSE())),"") -> tube
A28: III. Unsort CITE-seq stain | B28: Item | C28: 40um Flowmi Strainer | D28: S011 | E28: per super-pool | F28: 1 | G28: sample | H28: =Inputs!$B$20 -> 0.1 | I28: =VLOOKUP(E28,Inputs!$D$5:$E$23,2,FALSE()) -> 1 | J28: =F28*I28*(1+H28) -> 1.1 | K28: =IF(ISNUMBER(MATCH(G28,{"tube","each","plate","vial","kit","bottle","aliquot","strainer","cap","lane-rxn","tip","strip","lane","channel","library","sample"},0)),ROUNDUP(J28,0),ROUND(J28,2)) -> 2 | L28: =IFERROR(IF(OR(D28="",P28="",Q28="",Q28=0),"",IF(VLOOKUP(R28,Unit_Conversions!$A$5:$C$28,3,FALSE())=VLOOKUP(G28,Unit_Conversions!$A$5:$C$28,3,FALSE()),P28*VLOOKUP(G28,Unit_Conversions!$A$5:$C$28,2,FALSE())/(Q28*VLOOKUP(R28,Unit_Conversions!$A$5:$C$28,2,FALSE())),"")),"") -> 2.28 | M28: =IFERROR(F28*L28,"") -> 2.28 | N28: =IFERROR(J28*L28,"") -> 2.508 | P28: =IFERROR(IF(LEFT(D28,1)="K",VLOOKUP(D28,Kit_Catalog!$A:$K,8,FALSE()),VLOOKUP(D28,Additional_Supply_Catalog!$A:$K,7,FALSE())),"") -> 114 | Q28: =IFERROR(IF(LEFT(D28,1)="K",VLOOKUP(D28,Kit_Catalog!$A:$K,7,FALSE()),VLOOKUP(D28,Additional_Supply_Catalog!$A:$K,8,FALSE())),"") -> 50 | R28: =IFERROR(IF(LEFT(D28,1)="K","rxn",VLOOKUP(D28,Additional_Supply_Catalog!$A:$K,9,FALSE())),"") -> each
A29: IV. ASAP-seq | B29: BUFFER ▸ prepare | C29: Staining buffer (PBS+2% BSA) | E29: (prep total) | G29: mL | J29: =(6*Inputs!$B$6 + 3.1*Inputs!$B$7)*(1+Inputs!$B$20) -> 43.01 | O29: Standard-recipe volume to prepare; costed components are the item rows below (see Buffer recipes).
A30: IV. ASAP-seq | B30: BUFFER ▸ prepare | C30: ASAP lysis buffer (OMNI) | E30: (prep total) | G30: uL | J30: =(100*Inputs!$B$7)*(1+Inputs!$B$20) -> 110 | O30: Standard-recipe volume to prepare; costed components are the item rows below (see Buffer recipes).
A31: IV. ASAP-seq | B31: BUFFER ▸ prepare | C31: ASAP wash buffer | E31: (prep total) | G31: uL | J31: =(1000*Inputs!$B$7)*(1+Inputs!$B$20) -> 1100 | O31: Standard-recipe volume to prepare; costed components are the item rows below (see Buffer recipes).
A32: IV. ASAP-seq | B32: BUFFER ▸ prepare | C32: 1X nuclei buffer | E32: (prep total) | G32: uL | J32: =(100*Inputs!$B$7)*(1+Inputs!$B$20) -> 110 | O32: Standard-recipe volume to prepare; costed components are the item rows below (see Buffer recipes).
A33: IV. ASAP-seq | B33: Item | C33: 2mL eppendorf | D33: S005 | E33: per genetic pool | F33: 1 | G33: each | H33: =Inputs!$B$20 -> 0.1 | I33: =VLOOKUP(E33,Inputs!$D$5:$E$23,2,FALSE()) -> 6 | J33: =F33*I33*(1+H33) -> 6.6 | K33: =IF(ISNUMBER(MATCH(G33,{"tube","each","plate","vial","kit","bottle","aliquot","strainer","cap","lane-rxn","tip","strip","lane","channel","library","sample"},0)),ROUNDUP(J33,0),ROUND(J33,2)) -> 7 | L33: =IFERROR(IF(OR(D33="",P33="",Q33="",Q33=0),"",IF(VLOOKUP(R33,Unit_Conversions!$A$5:$C$28,3,FALSE())=VLOOKUP(G33,Unit_Conversions!$A$5:$C$28,3,FALSE()),P33*VLOOKUP(G33,Unit_Conversions!$A$5:$C$28,2,FALSE())/(Q33*VLOOKUP(R33,Unit_Conversions!$A$5:$C$28,2,FALSE())),"")),"") -> 0.17956 | M33: =IFERROR(F33*L33,"") -> 0.17956 | N33: =IFERROR(J33*L33,"") -> 1.185096 | P33: =IFERROR(IF(LEFT(D33,1)="K",VLOOKUP(D33,Kit_Catalog!$A:$K,8,FALSE()),VLOOKUP(D33,Additional_Supply_Catalog!$A:$K,7,FALSE())),"") -> 44.89 | Q33: =IFERROR(IF(LEFT(D33,1)="K",VLOOKUP(D33,Kit_Catalog!$A:$K,7,FALSE()),VLOOKUP(D33,Additional_Supply_Catalog!$A:$K,8,FALSE())),"") -> 250 | R33: =IFERROR(IF(LEFT(D33,1)="K","rxn",VLOOKUP(D33,Additional_Supply_Catalog!$A:$K,9,FALSE())),"") -> tube
A34: IV. ASAP-seq | B34: Item | C34: 50mL conical | D34: S007 | E34: per genetic pool | F34: 1 | G34: tube | H34: =Inputs!$B$20 -> 0.1 | I34: =VLOOKUP(E34,Inputs!$D$5:$E$23,2,FALSE()) -> 6 | J34: =F34*I34*(1+H34) -> 6.6 | K34: =IF(ISNUMBER(MATCH(G34,{"tube","each","plate","vial","kit","bottle","aliquot","strainer","cap","lane-rxn","tip","strip","lane","channel","library","sample"},0)),ROUNDUP(J34,0),ROUND(J34,2)) -> 7 | L34: =IFERROR(IF(OR(D34="",P34="",Q34="",Q34=0),"",IF(VLOOKUP(R34,Unit_Conversions!$A$5:$C$28,3,FALSE())=VLOOKUP(G34,Unit_Conversions!$A$5:$C$28,3,FALSE()),P34*VLOOKUP(G34,Unit_Conversions!$A$5:$C$28,2,FALSE())/(Q34*VLOOKUP(R34,Unit_Conversions!$A$5:$C$28,2,FALSE())),"")),"") -> 0.244 | M34: =IFERROR(F34*L34,"") -> 0.244 | N34: =IFERROR(J34*L34,"") -> 1.6104 | O34: [no catalog price] | P34: =IFERROR(IF(LEFT(D34,1)="K",VLOOKUP(D34,Kit_Catalog!$A:$K,8,FALSE()),VLOOKUP(D34,Additional_Supply_Catalog!$A:$K,7,FALSE())),"") -> 6.1 | Q34: =IFERROR(IF(LEFT(D34,1)="K",VLOOKUP(D34,Kit_Catalog!$A:$K,7,FALSE()),VLOOKUP(D34,Additional_Supply_Catalog!$A:$K,8,FALSE())),"") -> 25 | R34: =IFERROR(IF(LEFT(D34,1)="K","rxn",VLOOKUP(D34,Additional_Supply_Catalog!$A:$K,9,FALSE())),"") -> tube
A35: IV. ASAP-seq | B35: Item | C35: 40um Flowmi Strainer | D35: S011 | E35: per genetic pool | F35: 1 | G35: sample | H35: =Inputs!$B$20 -> 0.1 | I35: =VLOOKUP(E35,Inputs!$D$5:$E$23,2,FALSE()) -> 6 | J35: =F35*I35*(1+H35) -> 6.6 | K35: =IF(ISNUMBER(MATCH(G35,{"tube","each","plate","vial","kit","bottle","aliquot","strainer","cap","lane-rxn","tip","strip","lane","channel","library","sample"},0)),ROUNDUP(J35,0),ROUND(J35,2)) -> 7 | L35: =IFERROR(IF(OR(D35="",P35="",Q35="",Q35=0),"",IF(VLOOKUP(R35,Unit_Conversions!$A$5:$C$28,3,FALSE())=VLOOKUP(G35,Unit_Conversions!$A$5:$C$28,3,FALSE()),P35*VLOOKUP(G35,Unit_Conversions!$A$5:$C$28,2,FALSE())/(Q35*VLOOKUP(R35,Unit_Conversions!$A$5:$C$28,2,FALSE())),"")),"") -> 2.28 | M35: =IFERROR(F35*L35,"") -> 2.28 | N35: =IFERROR(J35*L35,"") -> 15.048 | P35: =IFERROR(IF(LEFT(D35,1)="K",VLOOKUP(D35,Kit_Catalog!$A:$K,8,FALSE()),VLOOKUP(D35,Additional_Supply_Catalog!$A:$K,7,FALSE())),"") -> 114 | Q35: =IFERROR(IF(LEFT(D35,1)="K",VLOOKUP(D35,Kit_Catalog!$A:$K,7,FALSE()),VLOOKUP(D35,Additional_Supply_Catalog!$A:$K,8,FALSE())),"") -> 50 | R35: =IFERROR(IF(LEFT(D35,1)="K","rxn",VLOOKUP(D35,Additional_Supply_Catalog!$A:$K,9,FALSE())),"") -> each
A36: IV. ASAP-seq | B36: Item | C36: 5mL FACS tube | D36: S013 | E36: per genetic pool | F36: 1 | G36: tube | H36: =Inputs!$B$20 -> 0.1 | I36: =VLOOKUP(E36,Inputs!$D$5:$E$23,2,FALSE()) -> 6 | J36: =F36*I36*(1+H36) -> 6.6 | K36: =IF(ISNUMBER(MATCH(G36,{"tube","each","plate","vial","kit","bottle","aliquot","strainer","cap","lane-rxn","tip","strip","lane","channel","library","sample"},0)),ROUNDUP(J36,0),ROUND(J36,2)) -> 7 | L36: =IFERROR(IF(OR(D36="",P36="",Q36="",Q36=0),"",IF(VLOOKUP(R36,Unit_Conversions!$A$5:$C$28,3,FALSE())=VLOOKUP(G36,Unit_Conversions!$A$5:$C$28,3,FALSE()),P36*VLOOKUP(G36,Unit_Conversions!$A$5:$C$28,2,FALSE())/(Q36*VLOOKUP(R36,Unit_Conversions!$A$5:$C$28,2,FALSE())),"")),"") | M36: =IFERROR(F36*L36,"") | N36: =IFERROR(J36*L36,"") | O36: [no catalog price] | P36: =IFERROR(IF(LEFT(D36,1)="K",VLOOKUP(D36,Kit_Catalog!$A:$K,8,FALSE()),VLOOKUP(D36,Additional_Supply_Catalog!$A:$K,7,FALSE())),"") -> 19.16 | Q36: =IFERROR(IF(LEFT(D36,1)="K",VLOOKUP(D36,Kit_Catalog!$A:$K,7,FALSE()),VLOOKUP(D36,Additional_Supply_Catalog!$A:$K,8,FALSE())),"") -> 12 | R36: =IFERROR(IF(LEFT(D36,1)="K","rxn",VLOOKUP(D36,Additional_Supply_Catalog!$A:$K,9,FALSE())),"") -> 0
A37: IV. ASAP-seq | B37: Item | C37: TotalseqA HTO | D37: R017 | E37: per genetic pool | F37: 2 | G37: uL | H37: =Inputs!$B$20 -> 0.1 | I37: =VLOOKUP(E37,Inputs!$D$5:$E$23,2,FALSE()) -> 6 | J37: =F37*I37*(1+H37) -> 13.2 | K37: =IF(ISNUMBER(MATCH(G37,{"tube","each","plate","vial","kit","bottle","aliquot","strainer","cap","lane-rxn","tip","strip","lane","channel","library","sample"},0)),ROUNDUP(J37,0),ROUND(J37,2)) -> 13.2 | L37: =IFERROR(IF(OR(D37="",P37="",Q37="",Q37=0),"",IF(VLOOKUP(R37,Unit_Conversions!$A$5:$C$28,3,FALSE())=VLOOKUP(G37,Unit_Conversions!$A$5:$C$28,3,FALSE()),P37*VLOOKUP(G37,Unit_Conversions!$A$5:$C$28,2,FALSE())/(Q37*VLOOKUP(R37,Unit_Conversions!$A$5:$C$28,2,FALSE())),"")),"") -> 25.85 | M37: =IFERROR(F37*L37,"") -> 51.7 | N37: =IFERROR(J37*L37,"") -> 341.22 | P37: =IFERROR(IF(LEFT(D37,1)="K",VLOOKUP(D37,Kit_Catalog!$A:$K,8,FALSE()),VLOOKUP(D37,Additional_Supply_Catalog!$A:$K,7,FALSE())),"") -> 517 | Q37: =IFERROR(IF(LEFT(D37,1)="K",VLOOKUP(D37,Kit_Catalog!$A:$K,7,FALSE()),VLOOKUP(D37,Additional_Supply_Catalog!$A:$K,8,FALSE())),"") -> 20 | R37: =IFERROR(IF(LEFT(D37,1)="K","rxn",VLOOKUP(D37,Additional_Supply_Catalog!$A:$K,9,FALSE())),"") -> uL
A38: IV. ASAP-seq | B38: Item | C38: Fc Block | D38: R019 | E38: per genetic pool | F38: 10 | G38: uL | H38: =Inputs!$B$20 -> 0.1 | I38: =VLOOKUP(E38,Inputs!$D$5:$E$23,2,FALSE()) -> 6 | J38: =F38*I38*(1+H38) -> 66 | K38: =IF(ISNUMBER(MATCH(G38,{"tube","each","plate","vial","kit","bottle","aliquot","strainer","cap","lane-rxn","tip","strip","lane","channel","library","sample"},0)),ROUNDUP(J38,0),ROUND(J38,2)) -> 66 | L38: =IFERROR(IF(OR(D38="",P38="",Q38="",Q38=0),"",IF(VLOOKUP(R38,Unit_Conversions!$A$5:$C$28,3,FALSE())=VLOOKUP(G38,Unit_Conversions!$A$5:$C$28,3,FALSE()),P38*VLOOKUP(G38,Unit_Conversions!$A$5:$C$28,2,FALSE())/(Q38*VLOOKUP(R38,Unit_Conversions!$A$5:$C$28,2,FALSE())),"")),"") -> 0.229 | M38: =IFERROR(F38*L38,"") -> 2.29 | N38: =IFERROR(J38*L38,"") -> 15.114 | P38: =IFERROR(IF(LEFT(D38,1)="K",VLOOKUP(D38,Kit_Catalog!$A:$K,8,FALSE()),VLOOKUP(D38,Additional_Supply_Catalog!$A:$K,7,FALSE())),"") -> 229 | Q38: =IFERROR(IF(LEFT(D38,1)="K",VLOOKUP(D38,Kit_Catalog!$A:$K,7,FALSE()),VLOOKUP(D38,Additional_Supply_Catalog!$A:$K,8,FALSE())),"") -> 1000 | R38: =IFERROR(IF(LEFT(D38,1)="K","rxn",VLOOKUP(D38,Additional_Supply_Catalog!$A:$K,9,FALSE())),"") -> uL
A39: IV. ASAP-seq | B39: Item | C39: BSA (powder) | D39: R026 | E39: per genetic pool | F39: 0.38 | G39: g | H39: =Inputs!$B$20 -> 0.1 | I39: =VLOOKUP(E39,Inputs!$D$5:$E$23,2,FALSE()) -> 6 | J39: =F39*I39*(1+H39) -> 2.508 | K39: =IF(ISNUMBER(MATCH(G39,{"tube","each","plate","vial","kit","bottle","aliquot","strainer","cap","lane-rxn","tip","strip","lane","channel","library","sample"},0)),ROUNDUP(J39,0),ROUND(J39,2)) -> 2.51 | L39: =IFERROR(IF(OR(D39="",P39="",Q39="",Q39=0),"",IF(VLOOKUP(R39,Unit_Conversions!$A$5:$C$28,3,FALSE())=VLOOKUP(G39,Unit_Conversions!$A$5:$C$28,3,FALSE()),P39*VLOOKUP(G39,Unit_Conversions!$A$5:$C$28,2,FALSE())/(Q39*VLOOKUP(R39,Unit_Conversions!$A$5:$C$28,2,FALSE())),"")),"") -> 4.152 | M39: =IFERROR(F39*L39,"") -> 1.57776 | N39: =IFERROR(J39*L39,"") -> 10.413216 | O39: BSA (powder): ASAP HTO staining = CITE staining (0.28 g = 2% x 14 mL). Same wash procedure as unsort. | P39: =IFERROR(IF(LEFT(D39,1)="K",VLOOKUP(D39,Kit_Catalog!$A:$K,8,FALSE()),VLOOKUP(D39,Additional_Supply_Catalog!$A:$K,7,FALSE())),"") -> 103.8 | Q39: =IFERROR(IF(LEFT(D39,1)="K",VLOOKUP(D39,Kit_Catalog!$A:$K,7,FALSE()),VLOOKUP(D39,Additional_Supply_Catalog!$A:$K,8,FALSE())),"") -> 25 | R39: =IFERROR(IF(LEFT(D39,1)="K","rxn",VLOOKUP(D39,Additional_Supply_Catalog!$A:$K,9,FALSE())),"") -> g
A40: IV. ASAP-seq | B40: Item | C40: 1X PBS | D40: R002 | E40: per genetic pool | F40: 19 | G40: mL | H40: =Inputs!$B$20 -> 0.1 | I40: =VLOOKUP(E40,Inputs!$D$5:$E$23,2,FALSE()) -> 6 | J40: =F40*I40*(1+H40) -> 125.4 | K40: =IF(ISNUMBER(MATCH(G40,{"tube","each","plate","vial","kit","bottle","aliquot","strainer","cap","lane-rxn","tip","strip","lane","channel","library","sample"},0)),ROUNDUP(J40,0),ROUND(J40,2)) -> 125.4 | L40: =IFERROR(IF(OR(D40="",P40="",Q40="",Q40=0),"",IF(VLOOKUP(R40,Unit_Conversions!$A$5:$C$28,3,FALSE())=VLOOKUP(G40,Unit_Conversions!$A$5:$C$28,3,FALSE()),P40*VLOOKUP(G40,Unit_Conversions!$A$5:$C$28,2,FALSE())/(Q40*VLOOKUP(R40,Unit_Conversions!$A$5:$C$28,2,FALSE())),"")),"") -> 0.03804 | M40: =IFERROR(F40*L40,"") -> 0.72276 | N40: =IFERROR(J40*L40,"") -> 4.770216 | O40: ASAP HTO staining PBS = CITE staining (14 mL/pool). Same 3x pre + 3x post + resuspend washes as unsort. [ADAPTED to SOP: 19 mL/pool/modality (was 14).] | P40: =IFERROR(IF(LEFT(D40,1)="K",VLOOKUP(D40,Kit_Catalog!$A:$K,8,FALSE()),VLOOKUP(D40,Additional_Supply_Catalog!$A:$K,7,FALSE())),"") -> 19.02 | Q40: =IFERROR(IF(LEFT(D40,1)="K",VLOOKUP(D40,Kit_Catalog!$A:$K,7,FALSE()),VLOOKUP(D40,Additional_Supply_Catalog!$A:$K,8,FALSE())),"") -> 500 | R40: =IFERROR(IF(LEFT(D40,1)="K","rxn",VLOOKUP(D40,Additional_Supply_Catalog!$A:$K,9,FALSE())),"") -> mL
A41: IV. ASAP-seq | B41: Item | C41: 16% Formaldehyde | D41: R010 | E41: per super-pool | F41: 30 | G41: uL | H41: =Inputs!$B$20 -> 0.1 | I41: =VLOOKUP(E41,Inputs!$D$5:$E$23,2,FALSE()) -> 1 | J41: =F41*I41*(1+H41) -> 33 | K41: =IF(ISNUMBER(MATCH(G41,{"tube","each","plate","vial","kit","bottle","aliquot","strainer","cap","lane-rxn","tip","strip","lane","channel","library","sample"},0)),ROUNDUP(J41,0),ROUND(J41,2)) -> 33 | L41: =IFERROR(IF(OR(D41="",P41="",Q41="",Q41=0),"",IF(VLOOKUP(R41,Unit_Conversions!$A$5:$C$28,3,FALSE())=VLOOKUP(G41,Unit_Conversions!$A$5:$C$28,3,FALSE()),P41*VLOOKUP(G41,Unit_Conversions!$A$5:$C$28,2,FALSE())/(Q41*VLOOKUP(R41,Unit_Conversions!$A$5:$C$28,2,FALSE())),"")),"") -> 0.047 | M41: =IFERROR(F41*L41,"") -> 1.41 | N41: =IFERROR(J41*L41,"") -> 1.551 | P41: =IFERROR(IF(LEFT(D41,1)="K",VLOOKUP(D41,Kit_Catalog!$A:$K,8,FALSE()),VLOOKUP(D41,Additional_Supply_Catalog!$A:$K,7,FALSE())),"") -> 47 | Q41: =IFERROR(IF(LEFT(D41,1)="K",VLOOKUP(D41,Kit_Catalog!$A:$K,7,FALSE()),VLOOKUP(D41,Additional_Supply_Catalog!$A:$K,8,FALSE())),"") -> 1000 | R41: =IFERROR(IF(LEFT(D41,1)="K","rxn",VLOOKUP(D41,Additional_Supply_Catalog!$A:$K,9,FALSE())),"") -> uL
A42: IV. ASAP-seq | B42: Item | C42: 2M Glycine | D42: R011 | E42: per super-pool | F42: 32 | G42: uL | H42: =Inputs!$B$20 -> 0.1 | I42: =VLOOKUP(E42,Inputs!$D$5:$E$23,2,FALSE()) -> 1 | J42: =F42*I42*(1+H42) -> 35.2 | K42: =IF(ISNUMBER(MATCH(G42,{"tube","each","plate","vial","kit","bottle","aliquot","strainer","cap","lane-rxn","tip","strip","lane","channel","library","sample"},0)),ROUNDUP(J42,0),ROUND(J42,2)) -> 35.2 | L42: =IFERROR(IF(OR(D42="",P42="",Q42="",Q42=0),"",IF(VLOOKUP(R42,Unit_Conversions!$A$5:$C$28,3,FALSE())=VLOOKUP(G42,Unit_Conversions!$A$5:$C$28,3,FALSE()),P42*VLOOKUP(G42,Unit_Conversions!$A$5:$C$28,2,FALSE())/(Q42*VLOOKUP(R42,Unit_Conversions!$A$5:$C$28,2,FALSE())),"")),"") | M42: =IFERROR(F42*L42,"") | N42: =IFERROR(J42*L42,"") | P42: =IFERROR(IF(LEFT(D42,1)="K",VLOOKUP(D42,Kit_Catalog!$A:$K,8,FALSE()),VLOOKUP(D42,Additional_Supply_Catalog!$A:$K,7,FALSE())),"") -> 46.2 | Q42: =IFERROR(IF(LEFT(D42,1)="K",VLOOKUP(D42,Kit_Catalog!$A:$K,7,FALSE()),VLOOKUP(D42,Additional_Supply_Catalog!$A:$K,8,FALSE())),"") -> 500 | R42: =IFERROR(IF(LEFT(D42,1)="K","rxn",VLOOKUP(D42,Additional_Supply_Catalog!$A:$K,9,FALSE())),"") -> g
A43: IV. ASAP-seq | B43: Item | C43: 1M Tris-HCl (pH 7.5) | D43: R021 | E43: per super-pool | F43: 11 | G43: uL | H43: =Inputs!$B$20 -> 0.1 | I43: =VLOOKUP(E43,Inputs!$D$5:$E$23,2,FALSE()) -> 1 | J43: =F43*I43*(1+H43) -> 12.1 | K43: =IF(ISNUMBER(MATCH(G43,{"tube","each","plate","vial","kit","bottle","aliquot","strainer","cap","lane-rxn","tip","strip","lane","channel","library","sample"},0)),ROUNDUP(J43,0),ROUND(J43,2)) -> 12.1 | L43: =IFERROR(IF(OR(D43="",P43="",Q43="",Q43=0),"",IF(VLOOKUP(R43,Unit_Conversions!$A$5:$C$28,3,FALSE())=VLOOKUP(G43,Unit_Conversions!$A$5:$C$28,3,FALSE()),P43*VLOOKUP(G43,Unit_Conversions!$A$5:$C$28,2,FALSE())/(Q43*VLOOKUP(R43,Unit_Conversions!$A$5:$C$28,2,FALSE())),"")),"") -> 0.000176 | M43: =IFERROR(F43*L43,"") -> 0.001936 | N43: =IFERROR(J43*L43,"") -> 0.0021296 | P43: =IFERROR(IF(LEFT(D43,1)="K",VLOOKUP(D43,Kit_Catalog!$A:$K,8,FALSE()),VLOOKUP(D43,Additional_Supply_Catalog!$A:$K,7,FALSE())),"") -> 44 | Q43: =IFERROR(IF(LEFT(D43,1)="K",VLOOKUP(D43,Kit_Catalog!$A:$K,7,FALSE()),VLOOKUP(D43,Additional_Supply_Catalog!$A:$K,8,FALSE())),"") -> 250 | R43: =IFERROR(IF(LEFT(D43,1)="K","rxn",VLOOKUP(D43,Additional_Supply_Catalog!$A:$K,9,FALSE())),"") -> mL
A44: IV. ASAP-seq | B44: Item | C44: 5M NaCl | D44: R022 | E44: per super-pool | F44: 2.2 | G44: uL | H44: =Inputs!$B$20 -> 0.1 | I44: =VLOOKUP(E44,Inputs!$D$5:$E$23,2,FALSE()) -> 1 | J44: =F44*I44*(1+H44) -> 2.42 | K44: =IF(ISNUMBER(MATCH(G44,{"tube","each","plate","vial","kit","bottle","aliquot","strainer","cap","lane-rxn","tip","strip","lane","channel","library","sample"},0)),ROUNDUP(J44,0),ROUND(J44,2)) -> 2.42 | L44: =IFERROR(IF(OR(D44="",P44="",Q44="",Q44=0),"",IF(VLOOKUP(R44,Unit_Conversions!$A$5:$C$28,3,FALSE())=VLOOKUP(G44,Unit_Conversions!$A$5:$C$28,3,FALSE()),P44*VLOOKUP(G44,Unit_Conversions!$A$5:$C$28,2,FALSE())/(Q44*VLOOKUP(R44,Unit_Conversions!$A$5:$C$28,2,FALSE())),"")),"") -> 1.455e-05 | M44: =IFERROR(F44*L44,"") -> 3.201e-05 | N44: =IFERROR(J44*L44,"") -> 3.5211e-05 | P44: =IFERROR(IF(LEFT(D44,1)="K",VLOOKUP(D44,Kit_Catalog!$A:$K,8,FALSE()),VLOOKUP(D44,Additional_Supply_Catalog!$A:$K,7,FALSE())),"") -> 14.55 | Q44: =IFERROR(IF(LEFT(D44,1)="K",VLOOKUP(D44,Kit_Catalog!$A:$K,7,FALSE()),VLOOKUP(D44,Additional_Supply_Catalog!$A:$K,8,FALSE())),"") -> 1000 | R44: =IFERROR(IF(LEFT(D44,1)="K","rxn",VLOOKUP(D44,Additional_Supply_Catalog!$A:$K,9,FALSE())),"") -> mL
A45: IV. ASAP-seq | B45: Item | C45: 1M MgCl2 | D45: R023 | E45: per super-pool | F45: 3.3 | G45: uL | H45: =Inputs!$B$20 -> 0.1 | I45: =VLOOKUP(E45,Inputs!$D$5:$E$23,2,FALSE()) -> 1 | J45: =F45*I45*(1+H45) -> 3.63 | K45: =IF(ISNUMBER(MATCH(G45,{"tube","each","plate","vial","kit","bottle","aliquot","strainer","cap","lane-rxn","tip","strip","lane","channel","library","sample"},0)),ROUNDUP(J45,0),ROUND(J45,2)) -> 3.63 | L45: =IFERROR(IF(OR(D45="",P45="",Q45="",Q45=0),"",IF(VLOOKUP(R45,Unit_Conversions!$A$5:$C$28,3,FALSE())=VLOOKUP(G45,Unit_Conversions!$A$5:$C$28,3,FALSE()),P45*VLOOKUP(G45,Unit_Conversions!$A$5:$C$28,2,FALSE())/(Q45*VLOOKUP(R45,Unit_Conversions!$A$5:$C$28,2,FALSE())),"")),"") -> 0.00057 | M45: =IFERROR(F45*L45,"") -> 0.001881 | N45: =IFERROR(J45*L45,"") -> 0.0020691 | P45: =IFERROR(IF(LEFT(D45,1)="K",VLOOKUP(D45,Kit_Catalog!$A:$K,8,FALSE()),VLOOKUP(D45,Additional_Supply_Catalog!$A:$K,7,FALSE())),"") -> 57 | Q45: =IFERROR(IF(LEFT(D45,1)="K",VLOOKUP(D45,Kit_Catalog!$A:$K,7,FALSE()),VLOOKUP(D45,Additional_Supply_Catalog!$A:$K,8,FALSE())),"") -> 100 | R45: =IFERROR(IF(LEFT(D45,1)="K","rxn",VLOOKUP(D45,Additional_Supply_Catalog!$A:$K,9,FALSE())),"") -> mL
A46: IV. ASAP-seq | B46: Item | C46: 10% NP40/IPEGAL | D46: R024 | E46: per super-pool | F46: 1 | G46: uL | H46: =Inputs!$B$20 -> 0.1 | I46: =VLOOKUP(E46,Inputs!$D$5:$E$23,2,FALSE()) -> 1 | J46: =F46*I46*(1+H46) -> 1.1 | K46: =IF(ISNUMBER(MATCH(G46,{"tube","each","plate","vial","kit","bottle","aliquot","strainer","cap","lane-rxn","tip","strip","lane","channel","library","sample"},0)),ROUNDUP(J46,0),ROUND(J46,2)) -> 1.1 | L46: =IFERROR(IF(OR(D46="",P46="",Q46="",Q46=0),"",IF(VLOOKUP(R46,Unit_Conversions!$A$5:$C$28,3,FALSE())=VLOOKUP(G46,Unit_Conversions!$A$5:$C$28,3,FALSE()),P46*VLOOKUP(G46,Unit_Conversions!$A$5:$C$28,2,FALSE())/(Q46*VLOOKUP(R46,Unit_Conversions!$A$5:$C$28,2,FALSE())),"")),"") -> 0.000212 | M46: =IFERROR(F46*L46,"") -> 0.000212 | N46: =IFERROR(J46*L46,"") -> 0.0002332 | P46: =IFERROR(IF(LEFT(D46,1)="K",VLOOKUP(D46,Kit_Catalog!$A:$K,8,FALSE()),VLOOKUP(D46,Additional_Supply_Catalog!$A:$K,7,FALSE())),"") -> 106 | Q46: =IFERROR(IF(LEFT(D46,1)="K",VLOOKUP(D46,Kit_Catalog!$A:$K,7,FALSE()),VLOOKUP(D46,Additional_Supply_Catalog!$A:$K,8,FALSE())),"") -> 500 | R46: =IFERROR(IF(LEFT(D46,1)="K","rxn",VLOOKUP(D46,Additional_Supply_Catalog!$A:$K,9,FALSE())),"") -> mL
A47: IV. ASAP-seq | B47: Item | C47: 5% Digitonin | D47: R025 | E47: per super-pool | F47: 0.2 | G47: uL | H47: =Inputs!$B$20 -> 0.1 | I47: =VLOOKUP(E47,Inputs!$D$5:$E$23,2,FALSE()) -> 1 | J47: =F47*I47*(1+H47) -> 0.22 | K47: =IF(ISNUMBER(MATCH(G47,{"tube","each","plate","vial","kit","bottle","aliquot","strainer","cap","lane-rxn","tip","strip","lane","channel","library","sample"},0)),ROUNDUP(J47,0),ROUND(J47,2)) -> 0.22 | L47: =IFERROR(IF(OR(D47="",P47="",Q47="",Q47=0),"",IF(VLOOKUP(R47,Unit_Conversions!$A$5:$C$28,3,FALSE())=VLOOKUP(G47,Unit_Conversions!$A$5:$C$28,3,FALSE()),P47*VLOOKUP(G47,Unit_Conversions!$A$5:$C$28,2,FALSE())/(Q47*VLOOKUP(R47,Unit_Conversions!$A$5:$C$28,2,FALSE())),"")),"") -> 0.12465 | M47: =IFERROR(F47*L47,"") -> 0.02493 | N47: =IFERROR(J47*L47,"") -> 0.027423 | P47: =IFERROR(IF(LEFT(D47,1)="K",VLOOKUP(D47,Kit_Catalog!$A:$K,8,FALSE()),VLOOKUP(D47,Additional_Supply_Catalog!$A:$K,7,FALSE())),"") -> 124.65 | Q47: =IFERROR(IF(LEFT(D47,1)="K",VLOOKUP(D47,Kit_Catalog!$A:$K,7,FALSE()),VLOOKUP(D47,Additional_Supply_Catalog!$A:$K,8,FALSE())),"") -> 1 | R47: =IFERROR(IF(LEFT(D47,1)="K","rxn",VLOOKUP(D47,Additional_Supply_Catalog!$A:$K,9,FALSE())),"") -> mL
A48: IV. ASAP-seq | B48: Item | C48: 10% Tween 20 | D48: R008 | E48: per super-pool | F48: 1 | G48: uL | H48: =Inputs!$B$20 -> 0.1 | I48: =VLOOKUP(E48,Inputs!$D$5:$E$23,2,FALSE()) -> 1 | J48: =F48*I48*(1+H48) -> 1.1 | K48: =IF(ISNUMBER(MATCH(G48,{"tube","each","plate","vial","kit","bottle","aliquot","strainer","cap","lane-rxn","tip","strip","lane","channel","library","sample"},0)),ROUNDUP(J48,0),ROUND(J48,2)) -> 1.1 | L48: =IFERROR(IF(OR(D48="",P48="",Q48="",Q48=0),"",IF(VLOOKUP(R48,Unit_Conversions!$A$5:$C$28,3,FALSE())=VLOOKUP(G48,Unit_Conversions!$A$5:$C$28,3,FALSE()),P48*VLOOKUP(G48,Unit_Conversions!$A$5:$C$28,2,FALSE())/(Q48*VLOOKUP(R48,Unit_Conversions!$A$5:$C$28,2,FALSE())),"")),"") -> 0.008104 | M48: =IFERROR(F48*L48,"") -> 0.008104 | N48: =IFERROR(J48*L48,"") -> 0.0089144 | P48: =IFERROR(IF(LEFT(D48,1)="K",VLOOKUP(D48,Kit_Catalog!$A:$K,8,FALSE()),VLOOKUP(D48,Additional_Supply_Catalog!$A:$K,7,FALSE())),"") -> 40.52 | Q48: =IFERROR(IF(LEFT(D48,1)="K",VLOOKUP(D48,Kit_Catalog!$A:$K,7,FALSE()),VLOOKUP(D48,Additional_Supply_Catalog!$A:$K,8,FALSE())),"") -> 5 | R48: =IFERROR(IF(LEFT(D48,1)="K","rxn",VLOOKUP(D48,Additional_Supply_Catalog!$A:$K,9,FALSE())),"") -> mL
A49: IV. ASAP-seq | B49: Item | C49: 1uM Bridge Oligo | D49: OL003 | E49: per super-pool | F49: 0.5 | G49: uL | H49: =Inputs!$B$20 -> 0.1 | I49: =VLOOKUP(E49,Inputs!$D$5:$E$23,2,FALSE()) -> 1 | J49: =F49*I49*(1+H49) -> 0.55 | K49: =IF(ISNUMBER(MATCH(G49,{"tube","each","plate","vial","kit","bottle","aliquot","strainer","cap","lane-rxn","tip","strip","lane","channel","library","sample"},0)),ROUNDUP(J49,0),ROUND(J49,2)) -> 0.55 | L49: =IFERROR(IF(OR(D49="",P49="",Q49="",Q49=0),"",IF(VLOOKUP(R49,Unit_Conversions!$A$5:$C$28,3,FALSE())=VLOOKUP(G49,Unit_Conversions!$A$5:$C$28,3,FALSE()),P49*VLOOKUP(G49,Unit_Conversions!$A$5:$C$28,2,FALSE())/(Q49*VLOOKUP(R49,Unit_Conversions!$A$5:$C$28,2,FALSE())),"")),"") | M49: =IFERROR(F49*L49,"") | N49: =IFERROR(J49*L49,"") | O49: [no catalog price] | P49: =IFERROR(IF(LEFT(D49,1)="K",VLOOKUP(D49,Kit_Catalog!$A:$K,8,FALSE()),VLOOKUP(D49,Additional_Supply_Catalog!$A:$K,7,FALSE())),"") | Q49: =IFERROR(IF(LEFT(D49,1)="K",VLOOKUP(D49,Kit_Catalog!$A:$K,7,FALSE()),VLOOKUP(D49,Additional_Supply_Catalog!$A:$K,8,FALSE())),"") | R49: =IFERROR(IF(LEFT(D49,1)="K","rxn",VLOOKUP(D49,Additional_Supply_Catalog!$A:$K,9,FALSE())),"")
A50: IV. ASAP-seq | B50: Item | C50: TotalseqA Antibody Cocktail | D50: R015 | E50: per super-pool | F50: 3 | G50: vial | H50: =Inputs!$B$20 -> 0.1 | I50: =VLOOKUP(E50,Inputs!$D$5:$E$23,2,FALSE()) -> 1 | J50: =F50*I50*(1+H50) -> 3.3 | K50: =IF(ISNUMBER(MATCH(G50,{"tube","each","plate","vial","kit","bottle","aliquot","strainer","cap","lane-rxn","tip","strip","lane","channel","library","sample"},0)),ROUNDUP(J50,0),ROUND(J50,2)) -> 4 | L50: =IFERROR(IF(OR(D50="",P50="",Q50="",Q50=0),"",IF(VLOOKUP(R50,Unit_Conversions!$A$5:$C$28,3,FALSE())=VLOOKUP(G50,Unit_Conversions!$A$5:$C$28,3,FALSE()),P50*VLOOKUP(G50,Unit_Conversions!$A$5:$C$28,2,FALSE())/(Q50*VLOOKUP(R50,Unit_Conversions!$A$5:$C$28,2,FALSE())),"")),"") -> 909.3 | M50: =IFERROR(F50*L50,"") -> 2727.9 | N50: =IFERROR(J50*L50,"") -> 3000.69 | P50: =IFERROR(IF(LEFT(D50,1)="K",VLOOKUP(D50,Kit_Catalog!$A:$K,8,FALSE()),VLOOKUP(D50,Additional_Supply_Catalog!$A:$K,7,FALSE())),"") -> 4546.5 | Q50: =IFERROR(IF(LEFT(D50,1)="K",VLOOKUP(D50,Kit_Catalog!$A:$K,7,FALSE()),VLOOKUP(D50,Additional_Supply_Catalog!$A:$K,8,FALSE())),"") -> 5 | R50: =IFERROR(IF(LEFT(D50,1)="K","rxn",VLOOKUP(D50,Additional_Supply_Catalog!$A:$K,9,FALSE())),"") -> vial
A51: IV. ASAP-seq | B51: Item | C51: 1X PBS | D51: R002 | E51: per super-pool | F51: 2.45 | G51: mL | H51: =Inputs!$B$20 -> 0.1 | I51: =VLOOKUP(E51,Inputs!$D$5:$E$23,2,FALSE()) -> 1 | J51: =F51*I51*(1+H51) -> 2.695 | K51: =IF(ISNUMBER(MATCH(G51,{"tube","each","plate","vial","kit","bottle","aliquot","strainer","cap","lane-rxn","tip","strip","lane","channel","library","sample"},0)),ROUNDUP(J51,0),ROUND(J51,2)) -> 2.7 | L51: =IFERROR(IF(OR(D51="",P51="",Q51="",Q51=0),"",IF(VLOOKUP(R51,Unit_Conversions!$A$5:$C$28,3,FALSE())=VLOOKUP(G51,Unit_Conversions!$A$5:$C$28,3,FALSE()),P51*VLOOKUP(G51,Unit_Conversions!$A$5:$C$28,2,FALSE())/(Q51*VLOOKUP(R51,Unit_Conversions!$A$5:$C$28,2,FALSE())),"")),"") -> 0.03804 | M51: =IFERROR(F51*L51,"") -> 0.093198 | N51: =IFERROR(J51*L51,"") -> 0.1025178 | P51: =IFERROR(IF(LEFT(D51,1)="K",VLOOKUP(D51,Kit_Catalog!$A:$K,8,FALSE()),VLOOKUP(D51,Additional_Supply_Catalog!$A:$K,7,FALSE())),"") -> 19.02 | Q51: =IFERROR(IF(LEFT(D51,1)="K",VLOOKUP(D51,Kit_Catalog!$A:$K,7,FALSE()),VLOOKUP(D51,Additional_Supply_Catalog!$A:$K,8,FALSE())),"") -> 500 | R51: =IFERROR(IF(LEFT(D51,1)="K","rxn",VLOOKUP(D51,Additional_Supply_Catalog!$A:$K,9,FALSE())),"") -> mL
A52: IV. ASAP-seq | B52: Item | C52: Sterile Water | D52: R001 | E52: per super-pool | F52: 0.97 | G52: mL | H52: =Inputs!$B$20 -> 0.1 | I52: =VLOOKUP(E52,Inputs!$D$5:$E$23,2,FALSE()) -> 1 | J52: =F52*I52*(1+H52) -> 1.067 | K52: =IF(ISNUMBER(MATCH(G52,{"tube","each","plate","vial","kit","bottle","aliquot","strainer","cap","lane-rxn","tip","strip","lane","channel","library","sample"},0)),ROUNDUP(J52,0),ROUND(J52,2)) -> 1.07 | L52: =IFERROR(IF(OR(D52="",P52="",Q52="",Q52=0),"",IF(VLOOKUP(R52,Unit_Conversions!$A$5:$C$28,3,FALSE())=VLOOKUP(G52,Unit_Conversions!$A$5:$C$28,3,FALSE()),P52*VLOOKUP(G52,Unit_Conversions!$A$5:$C$28,2,FALSE())/(Q52*VLOOKUP(R52,Unit_Conversions!$A$5:$C$28,2,FALSE())),"")),"") -> 0.02772 | M52: =IFERROR(F52*L52,"") -> 0.0268884 | N52: =IFERROR(J52*L52,"") -> 0.02957724 | O52: [no catalog price] | P52: =IFERROR(IF(LEFT(D52,1)="K",VLOOKUP(D52,Kit_Catalog!$A:$K,8,FALSE()),VLOOKUP(D52,Additional_Supply_Catalog!$A:$K,7,FALSE())),"") -> 13.86 | Q52: =IFERROR(IF(LEFT(D52,1)="K",VLOOKUP(D52,Kit_Catalog!$A:$K,7,FALSE()),VLOOKUP(D52,Additional_Supply_Catalog!$A:$K,8,FALSE())),"") -> 500 | R52: =IFERROR(IF(LEFT(D52,1)="K","rxn",VLOOKUP(D52,Additional_Supply_Catalog!$A:$K,9,FALSE())),"") -> mL
A53: IV. ASAP-seq | B53: Item | C53: BSA (powder) | D53: R026 | E53: per super-pool | F53: 0.18 | G53: g | H53: =Inputs!$B$20 -> 0.1 | I53: =VLOOKUP(E53,Inputs!$D$5:$E$23,2,FALSE()) -> 1 | J53: =F53*I53*(1+H53) -> 0.198 | K53: =IF(ISNUMBER(MATCH(G53,{"tube","each","plate","vial","kit","bottle","aliquot","strainer","cap","lane-rxn","tip","strip","lane","channel","library","sample"},0)),ROUNDUP(J53,0),ROUND(J53,2)) -> 0.2 | L53: =IFERROR(IF(OR(D53="",P53="",Q53="",Q53=0),"",IF(VLOOKUP(R53,Unit_Conversions!$A$5:$C$28,3,FALSE())=VLOOKUP(G53,Unit_Conversions!$A$5:$C$28,3,FALSE()),P53*VLOOKUP(G53,Unit_Conversions!$A$5:$C$28,2,FALSE())/(Q53*VLOOKUP(R53,Unit_Conversions!$A$5:$C$28,2,FALSE())),"")),"") -> 4.152 | M53: =IFERROR(F53*L53,"") -> 0.74736 | N53: =IFERROR(J53*L53,"") -> 0.822096 | O53: BSA (powder): ASAP lyo-panel staining = CITE super-pool staining (0.18 g = 2% x 9 mL). | P53: =IFERROR(IF(LEFT(D53,1)="K",VLOOKUP(D53,Kit_Catalog!$A:$K,8,FALSE()),VLOOKUP(D53,Additional_Supply_Catalog!$A:$K,7,FALSE())),"") -> 103.8 | Q53: =IFERROR(IF(LEFT(D53,1)="K",VLOOKUP(D53,Kit_Catalog!$A:$K,7,FALSE()),VLOOKUP(D53,Additional_Supply_Catalog!$A:$K,8,FALSE())),"") -> 25 | R53: =IFERROR(IF(LEFT(D53,1)="K","rxn",VLOOKUP(D53,Additional_Supply_Catalog!$A:$K,9,FALSE())),"") -> g
A54: IV. ASAP-seq | B54: Item | C54: 2mL eppendorf | D54: S005 | E54: per super-pool | F54: 1 | G54: tube | H54: =Inputs!$B$20 -> 0.1 | I54: =VLOOKUP(E54,Inputs!$D$5:$E$23,2,FALSE()) -> 1 | J54: =F54*I54*(1+H54) -> 1.1 | K54: =IF(ISNUMBER(MATCH(G54,{"tube","each","plate","vial","kit","bottle","aliquot","strainer","cap","lane-rxn","tip","strip","lane","channel","library","sample"},0)),ROUNDUP(J54,0),ROUND(J54,2)) -> 2 | L54: =IFERROR(IF(OR(D54="",P54="",Q54="",Q54=0),"",IF(VLOOKUP(R54,Unit_Conversions!$A$5:$C$28,3,FALSE())=VLOOKUP(G54,Unit_Conversions!$A$5:$C$28,3,FALSE()),P54*VLOOKUP(G54,Unit_Conversions!$A$5:$C$28,2,FALSE())/(Q54*VLOOKUP(R54,Unit_Conversions!$A$5:$C$28,2,FALSE())),"")),"") -> 0.17956 | M54: =IFERROR(F54*L54,"") -> 0.17956 | N54: =IFERROR(J54*L54,"") -> 0.197516 | P54: =IFERROR(IF(LEFT(D54,1)="K",VLOOKUP(D54,Kit_Catalog!$A:$K,8,FALSE()),VLOOKUP(D54,Additional_Supply_Catalog!$A:$K,7,FALSE())),"") -> 44.89 | Q54: =IFERROR(IF(LEFT(D54,1)="K",VLOOKUP(D54,Kit_Catalog!$A:$K,7,FALSE()),VLOOKUP(D54,Additional_Supply_Catalog!$A:$K,8,FALSE())),"") -> 250 | R54: =IFERROR(IF(LEFT(D54,1)="K","rxn",VLOOKUP(D54,Additional_Supply_Catalog!$A:$K,9,FALSE())),"") -> tube
A55: IV. ASAP-seq | B55: Item | C55: 50mL conical | D55: S007 | E55: per super-pool | F55: 1 | G55: tube | H55: =Inputs!$B$20 -> 0.1 | I55: =VLOOKUP(E55,Inputs!$D$5:$E$23,2,FALSE()) -> 1 | J55: =F55*I55*(1+H55) -> 1.1 | K55: =IF(ISNUMBER(MATCH(G55,{"tube","each","plate","vial","kit","bottle","aliquot","strainer","cap","lane-rxn","tip","strip","lane","channel","library","sample"},0)),ROUNDUP(J55,0),ROUND(J55,2)) -> 2 | L55: =IFERROR(IF(OR(D55="",P55="",Q55="",Q55=0),"",IF(VLOOKUP(R55,Unit_Conversions!$A$5:$C$28,3,FALSE())=VLOOKUP(G55,Unit_Conversions!$A$5:$C$28,3,FALSE()),P55*VLOOKUP(G55,Unit_Conversions!$A$5:$C$28,2,FALSE())/(Q55*VLOOKUP(R55,Unit_Conversions!$A$5:$C$28,2,FALSE())),"")),"") -> 0.244 | M55: =IFERROR(F55*L55,"") -> 0.244 | N55: =IFERROR(J55*L55,"") -> 0.2684 | O55: [no catalog price] | P55: =IFERROR(IF(LEFT(D55,1)="K",VLOOKUP(D55,Kit_Catalog!$A:$K,8,FALSE()),VLOOKUP(D55,Additional_Supply_Catalog!$A:$K,7,FALSE())),"") -> 6.1 | Q55: =IFERROR(IF(LEFT(D55,1)="K",VLOOKUP(D55,Kit_Catalog!$A:$K,7,FALSE()),VLOOKUP(D55,Additional_Supply_Catalog!$A:$K,8,FALSE())),"") -> 25 | R55: =IFERROR(IF(LEFT(D55,1)="K","rxn",VLOOKUP(D55,Additional_Supply_Catalog!$A:$K,9,FALSE())),"") -> tube
A56: IV. ASAP-seq | B56: Item | C56: PCR strip tubes (strip) | D56: S008 | E56: per super-pool | F56: 0.125 | G56: strip | H56: =Inputs!$B$20 -> 0.1 | I56: =VLOOKUP(E56,Inputs!$D$5:$E$23,2,FALSE()) -> 1 | J56: =F56*I56*(1+H56) -> 0.1375 | K56: =IF(ISNUMBER(MATCH(G56,{"tube","each","plate","vial","kit","bottle","aliquot","strainer","cap","lane-rxn","tip","strip","lane","channel","library","sample"},0)),ROUNDUP(J56,0),ROUND(J56,2)) -> 1 | L56: =IFERROR(IF(OR(D56="",P56="",Q56="",Q56=0),"",IF(VLOOKUP(R56,Unit_Conversions!$A$5:$C$28,3,FALSE())=VLOOKUP(G56,Unit_Conversions!$A$5:$C$28,3,FALSE()),P56*VLOOKUP(G56,Unit_Conversions!$A$5:$C$28,2,FALSE())/(Q56*VLOOKUP(R56,Unit_Conversions!$A$5:$C$28,2,FALSE())),"")),"") -> 0.7804 | M56: =IFERROR(F56*L56,"") -> 0.09755 | N56: =IFERROR(J56*L56,"") -> 0.107305 | P56: =IFERROR(IF(LEFT(D56,1)="K",VLOOKUP(D56,Kit_Catalog!$A:$K,8,FALSE()),VLOOKUP(D56,Additional_Supply_Catalog!$A:$K,7,FALSE())),"") -> 97.55 | Q56: =IFERROR(IF(LEFT(D56,1)="K",VLOOKUP(D56,Kit_Catalog!$A:$K,7,FALSE()),VLOOKUP(D56,Additional_Supply_Catalog!$A:$K,8,FALSE())),"") -> 125 | R56: =IFERROR(IF(LEFT(D56,1)="K","rxn",VLOOKUP(D56,Additional_Supply_Catalog!$A:$K,9,FALSE())),"") -> strip
A57: IV. ASAP-seq | B57: Item | C57: 40um Flowmi Strainer | D57: S011 | E57: per super-pool | F57: 1 | G57: sample | H57: =Inputs!$B$20 -> 0.1 | I57: =VLOOKUP(E57,Inputs!$D$5:$E$23,2,FALSE()) -> 1 | J57: =F57*I57*(1+H57) -> 1.1 | K57: =IF(ISNUMBER(MATCH(G57,{"tube","each","plate","vial","kit","bottle","aliquot","strainer","cap","lane-rxn","tip","strip","lane","channel","library","sample"},0)),ROUNDUP(J57,0),ROUND(J57,2)) -> 2 | L57: =IFERROR(IF(OR(D57="",P57="",Q57="",Q57=0),"",IF(VLOOKUP(R57,Unit_Conversions!$A$5:$C$28,3,FALSE())=VLOOKUP(G57,Unit_Conversions!$A$5:$C$28,3,FALSE()),P57*VLOOKUP(G57,Unit_Conversions!$A$5:$C$28,2,FALSE())/(Q57*VLOOKUP(R57,Unit_Conversions!$A$5:$C$28,2,FALSE())),"")),"") -> 2.28 | M57: =IFERROR(F57*L57,"") -> 2.28 | N57: =IFERROR(J57*L57,"") -> 2.508 | P57: =IFERROR(IF(LEFT(D57,1)="K",VLOOKUP(D57,Kit_Catalog!$A:$K,8,FALSE()),VLOOKUP(D57,Additional_Supply_Catalog!$A:$K,7,FALSE())),"") -> 114 | Q57: =IFERROR(IF(LEFT(D57,1)="K",VLOOKUP(D57,Kit_Catalog!$A:$K,7,FALSE()),VLOOKUP(D57,Additional_Supply_Catalog!$A:$K,8,FALSE())),"") -> 50 | R57: =IFERROR(IF(LEFT(D57,1)="K","rxn",VLOOKUP(D57,Additional_Supply_Catalog!$A:$K,9,FALSE())),"") -> each
A58: V. Sort stain | B58: BUFFER ▸ prepare | C58: FACS buffer (PBS+50% FBS) | E58: (prep total) | G58: mL | J58: =(65*Inputs!$B$6)*(1+Inputs!$B$20) -> 429 | O58: Standard-recipe volume to prepare; costed components are the item rows below (see Buffer recipes).
A59: V. Sort stain | B59: BUFFER ▸ prepare | C59: L/D Zombie Red (diluted stain) | E59: (prep total) | G59: mL | J59: =(0.25*Inputs!$B$6)*(1+Inputs!$B$20) -> 1.65 | O59: Standard-recipe volume to prepare; costed components are the item rows below (see Buffer recipes).
A60: V. Sort stain | B60: Item | C60: 5mL FACS tube | D60: S013 | E60: per genetic pool | F60: 1 | G60: tube | H60: =Inputs!$B$20 -> 0.1 | I60: =VLOOKUP(E60,Inputs!$D$5:$E$23,2,FALSE()) -> 6 | J60: =F60*I60*(1+H60) -> 6.6 | K60: =IF(ISNUMBER(MATCH(G60,{"tube","each","plate","vial","kit","bottle","aliquot","strainer","cap","lane-rxn","tip","strip","lane","channel","library","sample"},0)),ROUNDUP(J60,0),ROUND(J60,2)) -> 7 | L60: =IFERROR(IF(OR(D60="",P60="",Q60="",Q60=0),"",IF(VLOOKUP(R60,Unit_Conversions!$A$5:$C$28,3,FALSE())=VLOOKUP(G60,Unit_Conversions!$A$5:$C$28,3,FALSE()),P60*VLOOKUP(G60,Unit_Conversions!$A$5:$C$28,2,FALSE())/(Q60*VLOOKUP(R60,Unit_Conversions!$A$5:$C$28,2,FALSE())),"")),"") | M60: =IFERROR(F60*L60,"") | N60: =IFERROR(J60*L60,"") | O60: [no catalog price] | P60: =IFERROR(IF(LEFT(D60,1)="K",VLOOKUP(D60,Kit_Catalog!$A:$K,8,FALSE()),VLOOKUP(D60,Additional_Supply_Catalog!$A:$K,7,FALSE())),"") -> 19.16 | Q60: =IFERROR(IF(LEFT(D60,1)="K",VLOOKUP(D60,Kit_Catalog!$A:$K,7,FALSE()),VLOOKUP(D60,Additional_Supply_Catalog!$A:$K,8,FALSE())),"") -> 12 | R60: =IFERROR(IF(LEFT(D60,1)="K","rxn",VLOOKUP(D60,Additional_Supply_Catalog!$A:$K,9,FALSE())),"") -> 0
A61: V. Sort stain | B61: Item | C61: Sort Antibody Cocktail | D61: R055 | E61: per genetic pool | F61: 61.5 | G61: uL | H61: =Inputs!$B$20 -> 0.1 | I61: =VLOOKUP(E61,Inputs!$D$5:$E$23,2,FALSE()) -> 6 | J61: =F61*I61*(1+H61) -> 405.9 | K61: =IF(ISNUMBER(MATCH(G61,{"tube","each","plate","vial","kit","bottle","aliquot","strainer","cap","lane-rxn","tip","strip","lane","channel","library","sample"},0)),ROUNDUP(J61,0),ROUND(J61,2)) -> 405.9 | L61: =IFERROR(IF(OR(D61="",P61="",Q61="",Q61=0),"",IF(VLOOKUP(R61,Unit_Conversions!$A$5:$C$28,3,FALSE())=VLOOKUP(G61,Unit_Conversions!$A$5:$C$28,3,FALSE()),P61*VLOOKUP(G61,Unit_Conversions!$A$5:$C$28,2,FALSE())/(Q61*VLOOKUP(R61,Unit_Conversions!$A$5:$C$28,2,FALSE())),"")),"") | M61: =IFERROR(F61*L61,"") | N61: =IFERROR(J61*L61,"") | O61: CORRECTED 200->61.5: source adds 61.5 uL Ab cocktail + 5 uL HTO to 200 uL total tube vol; only 61.5 uL is antibody. MADI/AJ sort protocol. | P61: =IFERROR(IF(LEFT(D61,1)="K",VLOOKUP(D61,Kit_Catalog!$A:$K,8,FALSE()),VLOOKUP(D61,Additional_Supply_Catalog!$A:$K,7,FALSE())),"") -> 0 | Q61: =IFERROR(IF(LEFT(D61,1)="K",VLOOKUP(D61,Kit_Catalog!$A:$K,7,FALSE()),VLOOKUP(D61,Additional_Supply_Catalog!$A:$K,8,FALSE())),"") -> 1 | R61: =IFERROR(IF(LEFT(D61,1)="K","rxn",VLOOKUP(D61,Additional_Supply_Catalog!$A:$K,9,FALSE())),"") -> sample
A62: V. Sort stain | B62: Item | C62: Fc Block | D62: R019 | E62: per genetic pool | F62: 10 | G62: uL | H62: =Inputs!$B$20 -> 0.1 | I62: =VLOOKUP(E62,Inputs!$D$5:$E$23,2,FALSE()) -> 6 | J62: =F62*I62*(1+H62) -> 66 | K62: =IF(ISNUMBER(MATCH(G62,{"tube","each","plate","vial","kit","bottle","aliquot","strainer","cap","lane-rxn","tip","strip","lane","channel","library","sample"},0)),ROUNDUP(J62,0),ROUND(J62,2)) -> 66 | L62: =IFERROR(IF(OR(D62="",P62="",Q62="",Q62=0),"",IF(VLOOKUP(R62,Unit_Conversions!$A$5:$C$28,3,FALSE())=VLOOKUP(G62,Unit_Conversions!$A$5:$C$28,3,FALSE()),P62*VLOOKUP(G62,Unit_Conversions!$A$5:$C$28,2,FALSE())/(Q62*VLOOKUP(R62,Unit_Conversions!$A$5:$C$28,2,FALSE())),"")),"") -> 0.229 | M62: =IFERROR(F62*L62,"") -> 2.29 | N62: =IFERROR(J62*L62,"") -> 15.114 | O62: CORRECTED 20->10: source (AJ sort protocol) adds 10 uL Fc block per sort tube. | P62: =IFERROR(IF(LEFT(D62,1)="K",VLOOKUP(D62,Kit_Catalog!$A:$K,8,FALSE()),VLOOKUP(D62,Additional_Supply_Catalog!$A:$K,7,FALSE())),"") -> 229 | Q62: =IFERROR(IF(LEFT(D62,1)="K",VLOOKUP(D62,Kit_Catalog!$A:$K,7,FALSE()),VLOOKUP(D62,Additional_Supply_Catalog!$A:$K,8,FALSE())),"") -> 1000 | R62: =IFERROR(IF(LEFT(D62,1)="K","rxn",VLOOKUP(D62,Additional_Supply_Catalog!$A:$K,9,FALSE())),"") -> uL
A63: V. Sort stain | B63: Item | C63: FBS | D63: R032 | E63: per genetic pool | F63: 2.5 | G63: mL | H63: =Inputs!$B$20 -> 0.1 | I63: =VLOOKUP(E63,Inputs!$D$5:$E$23,2,FALSE()) -> 6 | J63: =F63*I63*(1+H63) -> 16.5 | K63: =IF(ISNUMBER(MATCH(G63,{"tube","each","plate","vial","kit","bottle","aliquot","strainer","cap","lane-rxn","tip","strip","lane","channel","library","sample"},0)),ROUNDUP(J63,0),ROUND(J63,2)) -> 16.5 | L63: =IFERROR(IF(OR(D63="",P63="",Q63="",Q63=0),"",IF(VLOOKUP(R63,Unit_Conversions!$A$5:$C$28,3,FALSE())=VLOOKUP(G63,Unit_Conversions!$A$5:$C$28,3,FALSE()),P63*VLOOKUP(G63,Unit_Conversions!$A$5:$C$28,2,FALSE())/(Q63*VLOOKUP(R63,Unit_Conversions!$A$5:$C$28,2,FALSE())),"")),"") -> 0.71342 | M63: =IFERROR(F63*L63,"") -> 1.78355 | N63: =IFERROR(J63*L63,"") -> 11.77143 | P63: =IFERROR(IF(LEFT(D63,1)="K",VLOOKUP(D63,Kit_Catalog!$A:$K,8,FALSE()),VLOOKUP(D63,Additional_Supply_Catalog!$A:$K,7,FALSE())),"") -> 356.71 | Q63: =IFERROR(IF(LEFT(D63,1)="K",VLOOKUP(D63,Kit_Catalog!$A:$K,7,FALSE()),VLOOKUP(D63,Additional_Supply_Catalog!$A:$K,8,FALSE())),"") -> 500 | R63: =IFERROR(IF(LEFT(D63,1)="K","rxn",VLOOKUP(D63,Additional_Supply_Catalog!$A:$K,9,FALSE())),"") -> mL
A64: V. Sort stain | B64: Item | C64: 1X PBS | D64: R002 | E64: per genetic pool | F64: 6 | G64: mL | H64: =Inputs!$B$20 -> 0.1 | I64: =VLOOKUP(E64,Inputs!$D$5:$E$23,2,FALSE()) -> 6 | J64: =F64*I64*(1+H64) -> 39.6 | K64: =IF(ISNUMBER(MATCH(G64,{"tube","each","plate","vial","kit","bottle","aliquot","strainer","cap","lane-rxn","tip","strip","lane","channel","library","sample"},0)),ROUNDUP(J64,0),ROUND(J64,2)) -> 39.6 | L64: =IFERROR(IF(OR(D64="",P64="",Q64="",Q64=0),"",IF(VLOOKUP(R64,Unit_Conversions!$A$5:$C$28,3,FALSE())=VLOOKUP(G64,Unit_Conversions!$A$5:$C$28,3,FALSE()),P64*VLOOKUP(G64,Unit_Conversions!$A$5:$C$28,2,FALSE())/(Q64*VLOOKUP(R64,Unit_Conversions!$A$5:$C$28,2,FALSE())),"")),"") -> 0.03804 | M64: =IFERROR(F64*L64,"") -> 0.22824 | N64: =IFERROR(J64*L64,"") -> 1.506384 | O64: CORRECTED 65->6: source uses 2x 2 mL 1X PBS washes/pool (~4 mL) + margin; 65 was implausible. Verify intended wash volume. | P64: =IFERROR(IF(LEFT(D64,1)="K",VLOOKUP(D64,Kit_Catalog!$A:$K,8,FALSE()),VLOOKUP(D64,Additional_Supply_Catalog!$A:$K,7,FALSE())),"") -> 19.02 | Q64: =IFERROR(IF(LEFT(D64,1)="K",VLOOKUP(D64,Kit_Catalog!$A:$K,7,FALSE()),VLOOKUP(D64,Additional_Supply_Catalog!$A:$K,8,FALSE())),"") -> 500 | R64: =IFERROR(IF(LEFT(D64,1)="K","rxn",VLOOKUP(D64,Additional_Supply_Catalog!$A:$K,9,FALSE())),"") -> mL
A65: V. Sort stain | B65: Item | C65: L/D Zombie Red (diluted stain) | E65: per genetic pool | F65: 250 | G65: uL | H65: =Inputs!$B$20 -> 0.1 | I65: =VLOOKUP(E65,Inputs!$D$5:$E$23,2,FALSE()) -> 6 | J65: =F65*I65*(1+H65) -> 1650 | K65: =IF(ISNUMBER(MATCH(G65,{"tube","each","plate","vial","kit","bottle","aliquot","strainer","cap","lane-rxn","tip","strip","lane","channel","library","sample"},0)),ROUNDUP(J65,0),ROUND(J65,2)) -> 1650 | L65: =IFERROR(IF(OR(D65="",P65="",Q65="",Q65=0),"",IF(VLOOKUP(R65,Unit_Conversions!$A$5:$C$28,3,FALSE())=VLOOKUP(G65,Unit_Conversions!$A$5:$C$28,3,FALSE()),P65*VLOOKUP(G65,Unit_Conversions!$A$5:$C$28,2,FALSE())/(Q65*VLOOKUP(R65,Unit_Conversions!$A$5:$C$28,2,FALSE())),"")),"") | M65: =IFERROR(F65*L65,"") | N65: =IFERROR(J65*L65,"") | O65: ADDED (was missing): 250 uL diluted viability stain per sort pool. [no catalog price] | P65: =IFERROR(IF(LEFT(D65,1)="K",VLOOKUP(D65,Kit_Catalog!$A:$K,8,FALSE()),VLOOKUP(D65,Additional_Supply_Catalog!$A:$K,7,FALSE())),"") | Q65: =IFERROR(IF(LEFT(D65,1)="K",VLOOKUP(D65,Kit_Catalog!$A:$K,7,FALSE()),VLOOKUP(D65,Additional_Supply_Catalog!$A:$K,8,FALSE())),"") | R65: =IFERROR(IF(LEFT(D65,1)="K","rxn",VLOOKUP(D65,Additional_Supply_Catalog!$A:$K,9,FALSE())),"")
A66: V. Sort stain | B66: Item | C66: L/D Zombie Red stock | D66: R056 | E66: per genetic pool | F66: 0.25 | G66: uL | H66: =Inputs!$B$20 -> 0.1 | I66: =VLOOKUP(E66,Inputs!$D$5:$E$23,2,FALSE()) -> 6 | J66: =F66*I66*(1+H66) -> 1.65 | K66: =IF(ISNUMBER(MATCH(G66,{"tube","each","plate","vial","kit","bottle","aliquot","strainer","cap","lane-rxn","tip","strip","lane","channel","library","sample"},0)),ROUNDUP(J66,0),ROUND(J66,2)) -> 1.65 | L66: =IFERROR(IF(OR(D66="",P66="",Q66="",Q66=0),"",IF(VLOOKUP(R66,Unit_Conversions!$A$5:$C$28,3,FALSE())=VLOOKUP(G66,Unit_Conversions!$A$5:$C$28,3,FALSE()),P66*VLOOKUP(G66,Unit_Conversions!$A$5:$C$28,2,FALSE())/(Q66*VLOOKUP(R66,Unit_Conversions!$A$5:$C$28,2,FALSE())),"")),"") | M66: =IFERROR(F66*L66,"") | N66: =IFERROR(J66*L66,"") | O66: ADDED: 0.25 uL stock per pool (1:1000). [no catalog price] | P66: =IFERROR(IF(LEFT(D66,1)="K",VLOOKUP(D66,Kit_Catalog!$A:$K,8,FALSE()),VLOOKUP(D66,Additional_Supply_Catalog!$A:$K,7,FALSE())),"") -> 0 | Q66: =IFERROR(IF(LEFT(D66,1)="K",VLOOKUP(D66,Kit_Catalog!$A:$K,7,FALSE()),VLOOKUP(D66,Additional_Supply_Catalog!$A:$K,8,FALSE())),"") -> 100 | R66: =IFERROR(IF(LEFT(D66,1)="K","rxn",VLOOKUP(D66,Additional_Supply_Catalog!$A:$K,9,FALSE())),"") -> test
A67: V. Sort stain | B67: Item | C67: Compensation beads | D67: R057 | E67: per run | F67: 1 | G67: each | H67: =Inputs!$B$20 -> 0.1 | I67: =VLOOKUP(E67,Inputs!$D$5:$E$23,2,FALSE()) -> 1 | J67: =F67*I67*(1+H67) -> 1.1 | K67: =IF(ISNUMBER(MATCH(G67,{"tube","each","plate","vial","kit","bottle","aliquot","strainer","cap","lane-rxn","tip","strip","lane","channel","library","sample"},0)),ROUNDUP(J67,0),ROUND(J67,2)) -> 2 | L67: =IFERROR(IF(OR(D67="",P67="",Q67="",Q67=0),"",IF(VLOOKUP(R67,Unit_Conversions!$A$5:$C$28,3,FALSE())=VLOOKUP(G67,Unit_Conversions!$A$5:$C$28,3,FALSE()),P67*VLOOKUP(G67,Unit_Conversions!$A$5:$C$28,2,FALSE())/(Q67*VLOOKUP(R67,Unit_Conversions!$A$5:$C$28,2,FALSE())),"")),"") | M67: =IFERROR(F67*L67,"") | N67: =IFERROR(J67*L67,"") | O67: ADDED (was missing): single-stain comp for the sorter. [no catalog price] | P67: =IFERROR(IF(LEFT(D67,1)="K",VLOOKUP(D67,Kit_Catalog!$A:$K,8,FALSE()),VLOOKUP(D67,Additional_Supply_Catalog!$A:$K,7,FALSE())),"") -> 0 | Q67: =IFERROR(IF(LEFT(D67,1)="K",VLOOKUP(D67,Kit_Catalog!$A:$K,7,FALSE()),VLOOKUP(D67,Additional_Supply_Catalog!$A:$K,8,FALSE())),"") -> 1 | R67: =IFERROR(IF(LEFT(D67,1)="K","rxn",VLOOKUP(D67,Additional_Supply_Catalog!$A:$K,9,FALSE())),"") -> kit
A68: V. Sort stain | B68: Item | C68: Unstained control (leukopak) | E68: per run | F68: 1 | G68: each | H68: =Inputs!$B$20 -> 0.1 | I68: =VLOOKUP(E68,Inputs!$D$5:$E$23,2,FALSE()) -> 1 | J68: =F68*I68*(1+H68) -> 1.1 | K68: =IF(ISNUMBER(MATCH(G68,{"tube","each","plate","vial","kit","bottle","aliquot","strainer","cap","lane-rxn","tip","strip","lane","channel","library","sample"},0)),ROUNDUP(J68,0),ROUND(J68,2)) -> 2 | L68: =IFERROR(IF(OR(D68="",P68="",Q68="",Q68=0),"",IF(VLOOKUP(R68,Unit_Conversions!$A$5:$C$28,3,FALSE())=VLOOKUP(G68,Unit_Conversions!$A$5:$C$28,3,FALSE()),P68*VLOOKUP(G68,Unit_Conversions!$A$5:$C$28,2,FALSE())/(Q68*VLOOKUP(R68,Unit_Conversions!$A$5:$C$28,2,FALSE())),"")),"") | M68: =IFERROR(F68*L68,"") | N68: =IFERROR(J68*L68,"") | O68: ADDED (was missing). [no catalog price] | P68: =IFERROR(IF(LEFT(D68,1)="K",VLOOKUP(D68,Kit_Catalog!$A:$K,8,FALSE()),VLOOKUP(D68,Additional_Supply_Catalog!$A:$K,7,FALSE())),"") | Q68: =IFERROR(IF(LEFT(D68,1)="K",VLOOKUP(D68,Kit_Catalog!$A:$K,7,FALSE()),VLOOKUP(D68,Additional_Supply_Catalog!$A:$K,8,FALSE())),"") | R68: =IFERROR(IF(LEFT(D68,1)="K","rxn",VLOOKUP(D68,Additional_Supply_Catalog!$A:$K,9,FALSE())),"")
A69: V. Sort stain | B69: Item | C69: Sort collection tube (population) | D69: S013 | E69: per run | F69: 4 | G69: tube | H69: =Inputs!$B$20 -> 0.1 | I69: =VLOOKUP(E69,Inputs!$D$5:$E$23,2,FALSE()) -> 1 | J69: =F69*I69*(1+H69) -> 4.4 | K69: =IF(ISNUMBER(MATCH(G69,{"tube","each","plate","vial","kit","bottle","aliquot","strainer","cap","lane-rxn","tip","strip","lane","channel","library","sample"},0)),ROUNDUP(J69,0),ROUND(J69,2)) -> 5 | L69: =IFERROR(IF(OR(D69="",P69="",Q69="",Q69=0),"",IF(VLOOKUP(R69,Unit_Conversions!$A$5:$C$28,3,FALSE())=VLOOKUP(G69,Unit_Conversions!$A$5:$C$28,3,FALSE()),P69*VLOOKUP(G69,Unit_Conversions!$A$5:$C$28,2,FALSE())/(Q69*VLOOKUP(R69,Unit_Conversions!$A$5:$C$28,2,FALSE())),"")),"") | M69: =IFERROR(F69*L69,"") | N69: =IFERROR(J69*L69,"") | O69: ADDED (was missing): HSC/pDC/cDC/Treg. [no catalog price] | P69: =IFERROR(IF(LEFT(D69,1)="K",VLOOKUP(D69,Kit_Catalog!$A:$K,8,FALSE()),VLOOKUP(D69,Additional_Supply_Catalog!$A:$K,7,FALSE())),"") -> 19.16 | Q69: =IFERROR(IF(LEFT(D69,1)="K",VLOOKUP(D69,Kit_Catalog!$A:$K,7,FALSE()),VLOOKUP(D69,Additional_Supply_Catalog!$A:$K,8,FALSE())),"") -> 12 | R69: =IFERROR(IF(LEFT(D69,1)="K","rxn",VLOOKUP(D69,Additional_Supply_Catalog!$A:$K,9,FALSE())),"") -> 0
A70: V. Sort stain | B70: Item | C70: FACS tube filter cap | D70: S014 | E70: per genetic pool | F70: 1 | G70: cap | H70: =Inputs!$B$20 -> 0.1 | I70: =VLOOKUP(E70,Inputs!$D$5:$E$23,2,FALSE()) -> 6 | J70: =F70*I70*(1+H70) -> 6.6 | K70: =IF(ISNUMBER(MATCH(G70,{"tube","each","plate","vial","kit","bottle","aliquot","strainer","cap","lane-rxn","tip","strip","lane","channel","library","sample"},0)),ROUNDUP(J70,0),ROUND(J70,2)) -> 7 | L70: =IFERROR(IF(OR(D70="",P70="",Q70="",Q70=0),"",IF(VLOOKUP(R70,Unit_Conversions!$A$5:$C$28,3,FALSE())=VLOOKUP(G70,Unit_Conversions!$A$5:$C$28,3,FALSE()),P70*VLOOKUP(G70,Unit_Conversions!$A$5:$C$28,2,FALSE())/(Q70*VLOOKUP(R70,Unit_Conversions!$A$5:$C$28,2,FALSE())),"")),"") -> 1.5966667 | M70: =IFERROR(F70*L70,"") -> 1.5966667 | N70: =IFERROR(J70*L70,"") -> 10.538 | O70: ADDED (was missing): filter before sort. [no catalog price] | P70: =IFERROR(IF(LEFT(D70,1)="K",VLOOKUP(D70,Kit_Catalog!$A:$K,8,FALSE()),VLOOKUP(D70,Additional_Supply_Catalog!$A:$K,7,FALSE())),"") -> 19.16 | Q70: =IFERROR(IF(LEFT(D70,1)="K",VLOOKUP(D70,Kit_Catalog!$A:$K,7,FALSE()),VLOOKUP(D70,Additional_Supply_Catalog!$A:$K,8,FALSE())),"") -> 12 | R70: =IFERROR(IF(LEFT(D70,1)="K","rxn",VLOOKUP(D70,Additional_Supply_Catalog!$A:$K,9,FALSE())),"") -> cap
A71: VI. Bulk RNA (Trizol) | B71: Item | C71: 1.5mL eppendorf | D71: S004 | E71: per sample | F71: 1 | G71: each | H71: =Inputs!$B$20 -> 0.1 | I71: =VLOOKUP(E71,Inputs!$D$5:$E$23,2,FALSE()) -> 54 | J71: =F71*I71*(1+H71) -> 59.4 | K71: =IF(ISNUMBER(MATCH(G71,{"tube","each","plate","vial","kit","bottle","aliquot","strainer","cap","lane-rxn","tip","strip","lane","channel","library","sample"},0)),ROUNDUP(J71,0),ROUND(J71,2)) -> 60 | L71: =IFERROR(IF(OR(D71="",P71="",Q71="",Q71=0),"",IF(VLOOKUP(R71,Unit_Conversions!$A$5:$C$28,3,FALSE())=VLOOKUP(G71,Unit_Conversions!$A$5:$C$28,3,FALSE()),P71*VLOOKUP(G71,Unit_Conversions!$A$5:$C$28,2,FALSE())/(Q71*VLOOKUP(R71,Unit_Conversions!$A$5:$C$28,2,FALSE())),"")),"") -> 0.17956 | M71: =IFERROR(F71*L71,"") -> 0.17956 | N71: =IFERROR(J71*L71,"") -> 10.665864 | P71: =IFERROR(IF(LEFT(D71,1)="K",VLOOKUP(D71,Kit_Catalog!$A:$K,8,FALSE()),VLOOKUP(D71,Additional_Supply_Catalog!$A:$K,7,FALSE())),"") -> 44.89 | Q71: =IFERROR(IF(LEFT(D71,1)="K",VLOOKUP(D71,Kit_Catalog!$A:$K,7,FALSE()),VLOOKUP(D71,Additional_Supply_Catalog!$A:$K,8,FALSE())),"") -> 250 | R71: =IFERROR(IF(LEFT(D71,1)="K","rxn",VLOOKUP(D71,Additional_Supply_Catalog!$A:$K,9,FALSE())),"") -> tube
A72: VI. Bulk RNA (Trizol) | B72: Item | C72: RNA Isolation Kit | D72: R054 | E72: per sample | F72: 1 | G72: sample | H72: =Inputs!$B$20 -> 0.1 | I72: =VLOOKUP(E72,Inputs!$D$5:$E$23,2,FALSE()) -> 54 | J72: =F72*I72*(1+H72) -> 59.4 | K72: =IF(ISNUMBER(MATCH(G72,{"tube","each","plate","vial","kit","bottle","aliquot","strainer","cap","lane-rxn","tip","strip","lane","channel","library","sample"},0)),ROUNDUP(J72,0),ROUND(J72,2)) -> 60 | L72: =IFERROR(IF(OR(D72="",P72="",Q72="",Q72=0),"",IF(VLOOKUP(R72,Unit_Conversions!$A$5:$C$28,3,FALSE())=VLOOKUP(G72,Unit_Conversions!$A$5:$C$28,3,FALSE()),P72*VLOOKUP(G72,Unit_Conversions!$A$5:$C$28,2,FALSE())/(Q72*VLOOKUP(R72,Unit_Conversions!$A$5:$C$28,2,FALSE())),"")),"") | M72: =IFERROR(F72*L72,"") | N72: =IFERROR(J72*L72,"") | O72: [no catalog price] | P72: =IFERROR(IF(LEFT(D72,1)="K",VLOOKUP(D72,Kit_Catalog!$A:$K,8,FALSE()),VLOOKUP(D72,Additional_Supply_Catalog!$A:$K,7,FALSE())),"") -> 0 | Q72: =IFERROR(IF(LEFT(D72,1)="K",VLOOKUP(D72,Kit_Catalog!$A:$K,7,FALSE()),VLOOKUP(D72,Additional_Supply_Catalog!$A:$K,8,FALSE())),"") -> 1 | R72: =IFERROR(IF(LEFT(D72,1)="K","rxn",VLOOKUP(D72,Additional_Supply_Catalog!$A:$K,9,FALSE())),"") -> sample
A73: VI. Bulk RNA (Trizol) | B73: Item | C73: TRIzol | D73: R034 | E73: per sample | F73: 0.6 | G73: mL | H73: =Inputs!$B$20 -> 0.1 | I73: =VLOOKUP(E73,Inputs!$D$5:$E$23,2,FALSE()) -> 54 | J73: =F73*I73*(1+H73) -> 35.64 | K73: =IF(ISNUMBER(MATCH(G73,{"tube","each","plate","vial","kit","bottle","aliquot","strainer","cap","lane-rxn","tip","strip","lane","channel","library","sample"},0)),ROUNDUP(J73,0),ROUND(J73,2)) -> 35.64 | L73: =IFERROR(IF(OR(D73="",P73="",Q73="",Q73=0),"",IF(VLOOKUP(R73,Unit_Conversions!$A$5:$C$28,3,FALSE())=VLOOKUP(G73,Unit_Conversions!$A$5:$C$28,3,FALSE()),P73*VLOOKUP(G73,Unit_Conversions!$A$5:$C$28,2,FALSE())/(Q73*VLOOKUP(R73,Unit_Conversions!$A$5:$C$28,2,FALSE())),"")),"") -> 2.6334 | M73: =IFERROR(F73*L73,"") -> 1.58004 | N73: =IFERROR(J73*L73,"") -> 93.854376 | P73: =IFERROR(IF(LEFT(D73,1)="K",VLOOKUP(D73,Kit_Catalog!$A:$K,8,FALSE()),VLOOKUP(D73,Additional_Supply_Catalog!$A:$K,7,FALSE())),"") -> 263.34 | Q73: =IFERROR(IF(LEFT(D73,1)="K",VLOOKUP(D73,Kit_Catalog!$A:$K,7,FALSE()),VLOOKUP(D73,Additional_Supply_Catalog!$A:$K,8,FALSE())),"") -> 100 | R73: =IFERROR(IF(LEFT(D73,1)="K","rxn",VLOOKUP(D73,Additional_Supply_Catalog!$A:$K,9,FALSE())),"") -> mL
A74: VII. Flex v2 (fixation → GEM load) | B74: BUFFER ▸ prepare | C74: Fixation Buffer B | E74: (prep total) | G74: mL | J74: =(0.55*Inputs!$B$21)*(1+Inputs!$B$20) -> 0 | O74: Per-sample recipe (CG000782): NF water 435 + Conc. Fix & Perm Buffer B (PN-2001301) 55 + 37% formaldehyde 60 uL = 550 uL/sample. Components in Sample Prep v2 Kit; formaldehyde third-party.
A75: VII. Flex v2 (fixation → GEM load) | B75: BUFFER ▸ prepare | C75: Quenching Buffer B | E75: (prep total) | G75: mL | J75: =(1.072*Inputs!$B$21)*(1+Inputs!$B$20) -> 0 | O75: Per-sample recipe (CG000782): NF water 938 + Conc. Quench Buffer B (PN-2001300) 134 uL = ~1072 uL/sample (+0.5 mL/sample if storing).
A76: VII. Flex v2 (fixation → GEM load) | B76: BUFFER ▸ prepare | C76: Probe Hyb Mix | E76: (prep total) | G76: mL | J76: =(0.055*Inputs!$B$21)*(1+Inputs!$B$20) -> 0 | O76: Per-sample (CG000834 Step 1): Hyb Buffer B 38.5 + Enhancer 5.5 + Additive A 2.75 + WTA Probes v2 8.25 = 55 uL/sample. Components in Core Reagents.
A77: VII. Flex v2 (fixation → GEM load) | B77: BUFFER ▸ prepare | C77: Post-Hyb Wash Buffer B | E77: (prep total) | G77: mL | J77: =(0.495*Inputs!$B$21)*(1+Inputs!$B$20) -> 0 | O77: Per-sample tube (CG000834 Step 3): NF water 445 + Enhancer 25 + Conc. Post-Hyb Buffer B 25 uL = 495 uL. Used at post-hyb pooled wash.
A78: VII. Flex v2 (fixation → GEM load) | B78: BUFFER ▸ prepare | C78: GEM Master Mix | E78: (prep total) | G78: mL | J78: =(0.0333*Inputs!$B$22)*(1+Inputs!$B$20) -> 0 | O78: Per GEM reaction (CG000834 Step 4.1): GEM Reagent Mix 19.9 + Reducing Agent B 1.6 + GEM Enzyme Mix B 11.8 = 33.3 uL. Components in GEM & Library Kit / Core Reagents.
A79: VII. Flex v2 (fixation → GEM load) | B79: Item | C79: GEM-X Flex Sample Preparation v2 Kit | D79: K041 | E79: per Flex sample | F79: 1 | G79: sample | H79: =Inputs!$B$20 -> 0.1 | I79: =VLOOKUP(E79,Inputs!$D$5:$E$23,2,FALSE()) -> 0 | J79: =F79*I79*(1+H79) -> 0 | K79: =IF(ISNUMBER(MATCH(G79,{"tube","each","plate","vial","kit","bottle","aliquot","strainer","cap","lane-rxn","tip","strip","lane","channel","library","sample"},0)),ROUNDUP(J79,0),ROUND(J79,2)) -> 0 | L79: =IFERROR(IF(OR(D79="",P79="",Q79="",Q79=0),"",IF(VLOOKUP(R79,Unit_Conversions!$A$5:$C$28,3,FALSE())=VLOOKUP(G79,Unit_Conversions!$A$5:$C$28,3,FALSE()),P79*VLOOKUP(G79,Unit_Conversions!$A$5:$C$28,2,FALSE())/(Q79*VLOOKUP(R79,Unit_Conversions!$A$5:$C$28,2,FALSE())),"")),"") -> 16.666667 | M79: =IFERROR(F79*L79,"") -> 16.666667 | N79: =IFERROR(J79*L79,"") -> 0 | O79: KIT (PN-1000781). Fix/Perm B, Quench B, Enhancer, Additive C. 48 samples/kit. | P79: =IFERROR(IF(LEFT(D79,1)="K",VLOOKUP(D79,Kit_Catalog!$A:$K,8,FALSE()),VLOOKUP(D79,Additional_Supply_Catalog!$A:$K,7,FALSE())),"") -> 800 | Q79: =IFERROR(IF(LEFT(D79,1)="K",VLOOKUP(D79,Kit_Catalog!$A:$K,7,FALSE()),VLOOKUP(D79,Additional_Supply_Catalog!$A:$K,8,FALSE())),"") -> 48 | R79: =IFERROR(IF(LEFT(D79,1)="K","rxn",VLOOKUP(D79,Additional_Supply_Catalog!$A:$K,9,FALSE())),"") -> rxn
A80: VII. Flex v2 (fixation → GEM load) | B80: Item | C80: GEM-X Flex v2 Core Reagents | D80: K036 | E80: per Flex sample | F80: 1 | G80: sample | H80: =Inputs!$B$20 -> 0.1 | I80: =VLOOKUP(E80,Inputs!$D$5:$E$23,2,FALSE()) -> 0 | J80: =F80*I80*(1+H80) -> 0 | K80: =IF(ISNUMBER(MATCH(G80,{"tube","each","plate","vial","kit","bottle","aliquot","strainer","cap","lane-rxn","tip","strip","lane","channel","library","sample"},0)),ROUNDUP(J80,0),ROUND(J80,2)) -> 0 | L80: =IFERROR(IF(OR(D80="",P80="",Q80="",Q80=0),"",IF(VLOOKUP(R80,Unit_Conversions!$A$5:$C$28,3,FALSE())=VLOOKUP(G80,Unit_Conversions!$A$5:$C$28,3,FALSE()),P80*VLOOKUP(G80,Unit_Conversions!$A$5:$C$28,2,FALSE())/(Q80*VLOOKUP(R80,Unit_Conversions!$A$5:$C$28,2,FALSE())),"")),"") -> 637.5 | M80: =IFERROR(F80*L80,"") -> 637.5 | N80: =IFERROR(J80*L80,"") -> 0 | O80: KIT (PN-1000927, 16 samp). Hyb Buffer B, Additive A, WTA Probes v2, Barcoding Oligo plates, Conc. Post-Hyb Buffer B, GEM/pre-amp/library reagents. | P80: =IFERROR(IF(LEFT(D80,1)="K",VLOOKUP(D80,Kit_Catalog!$A:$K,8,FALSE()),VLOOKUP(D80,Additional_Supply_Catalog!$A:$K,7,FALSE())),"") -> 10200 | Q80: =IFERROR(IF(LEFT(D80,1)="K",VLOOKUP(D80,Kit_Catalog!$A:$K,7,FALSE()),VLOOKUP(D80,Additional_Supply_Catalog!$A:$K,8,FALSE())),"") -> 16 | R80: =IFERROR(IF(LEFT(D80,1)="K","rxn",VLOOKUP(D80,Additional_Supply_Catalog!$A:$K,9,FALSE())),"") -> rxn
A81: VII. Flex v2 (fixation → GEM load) | B81: Item | C81: GEM-X Flex Gene Expression Chip Kit | D81: K038 | E81: per Flex pool | F81: 1 | G81: channels | H81: =Inputs!$B$20 -> 0.1 | I81: =VLOOKUP(E81,Inputs!$D$5:$E$23,2,FALSE()) -> 0 | J81: =F81*I81*(1+H81) -> 0 | K81: =IF(ISNUMBER(MATCH(G81,{"tube","each","plate","vial","kit","bottle","aliquot","strainer","cap","lane-rxn","tip","strip","lane","channel","library","sample"},0)),ROUNDUP(J81,0),ROUND(J81,2)) -> 0 | L81: =IFERROR(IF(OR(D81="",P81="",Q81="",Q81=0),"",IF(VLOOKUP(R81,Unit_Conversions!$A$5:$C$28,3,FALSE())=VLOOKUP(G81,Unit_Conversions!$A$5:$C$28,3,FALSE()),P81*VLOOKUP(G81,Unit_Conversions!$A$5:$C$28,2,FALSE())/(Q81*VLOOKUP(R81,Unit_Conversions!$A$5:$C$28,2,FALSE())),"")),"") -> 78.125 | M81: =IFERROR(F81*L81,"") -> 78.125 | N81: =IFERROR(J81*L81,"") -> 0 | O81: KIT (PN-1000791). GEM-X FX Chip (PN-2001257) + Partitioning Oil B. rxn/kit inferred 16 - verify. | P81: =IFERROR(IF(LEFT(D81,1)="K",VLOOKUP(D81,Kit_Catalog!$A:$K,8,FALSE()),VLOOKUP(D81,Additional_Supply_Catalog!$A:$K,7,FALSE())),"") -> 1250 | Q81: =IFERROR(IF(LEFT(D81,1)="K",VLOOKUP(D81,Kit_Catalog!$A:$K,7,FALSE()),VLOOKUP(D81,Additional_Supply_Catalog!$A:$K,8,FALSE())),"") -> 16 | R81: =IFERROR(IF(LEFT(D81,1)="K","rxn",VLOOKUP(D81,Additional_Supply_Catalog!$A:$K,9,FALSE())),"") -> rxn
A82: VII. Flex v2 (fixation → GEM load) | B82: Item | C82: GEM-X Flex GEM & Library Kit v2 | D82: K042 | E82: per Flex pool | F82: 1 | G82: channels | H82: =Inputs!$B$20 -> 0.1 | I82: =VLOOKUP(E82,Inputs!$D$5:$E$23,2,FALSE()) -> 0 | J82: =F82*I82*(1+H82) -> 0 | K82: =IF(ISNUMBER(MATCH(G82,{"tube","each","plate","vial","kit","bottle","aliquot","strainer","cap","lane-rxn","tip","strip","lane","channel","library","sample"},0)),ROUNDUP(J82,0),ROUND(J82,2)) -> 0 | L82: =IFERROR(IF(OR(D82="",P82="",Q82="",Q82=0),"",IF(VLOOKUP(R82,Unit_Conversions!$A$5:$C$28,3,FALSE())=VLOOKUP(G82,Unit_Conversions!$A$5:$C$28,3,FALSE()),P82*VLOOKUP(G82,Unit_Conversions!$A$5:$C$28,2,FALSE())/(Q82*VLOOKUP(R82,Unit_Conversions!$A$5:$C$28,2,FALSE())),"")),"") | M82: =IFERROR(F82*L82,"") | N82: =IFERROR(J82*L82,"") | O82: KIT (PN-1000918, 4 rxn) - GEM Reagent Mix, Enzyme Mix B, Amp Mix C, Pre-Amp Primers B. Price unverified -> uncosted; may overlap Core Reagents. | P82: =IFERROR(IF(LEFT(D82,1)="K",VLOOKUP(D82,Kit_Catalog!$A:$K,8,FALSE()),VLOOKUP(D82,Additional_Supply_Catalog!$A:$K,7,FALSE())),"") -> 0 | Q82: =IFERROR(IF(LEFT(D82,1)="K",VLOOKUP(D82,Kit_Catalog!$A:$K,7,FALSE()),VLOOKUP(D82,Additional_Supply_Catalog!$A:$K,8,FALSE())),"") -> 4 | R82: =IFERROR(IF(LEFT(D82,1)="K","rxn",VLOOKUP(D82,Additional_Supply_Catalog!$A:$K,9,FALSE())),"") -> rxn
A83: VII. Flex v2 (fixation → GEM load) | B83: Item | C83: Formaldehyde 37% | D83: R035 | E83: per Flex sample | F83: 60 | G83: uL | H83: =Inputs!$B$20 -> 0.1 | I83: =VLOOKUP(E83,Inputs!$D$5:$E$23,2,FALSE()) -> 0 | J83: =F83*I83*(1+H83) -> 0 | K83: =IF(ISNUMBER(MATCH(G83,{"tube","each","plate","vial","kit","bottle","aliquot","strainer","cap","lane-rxn","tip","strip","lane","channel","library","sample"},0)),ROUNDUP(J83,0),ROUND(J83,2)) -> 0 | L83: =IFERROR(IF(OR(D83="",P83="",Q83="",Q83=0),"",IF(VLOOKUP(R83,Unit_Conversions!$A$5:$C$28,3,FALSE())=VLOOKUP(G83,Unit_Conversions!$A$5:$C$28,3,FALSE()),P83*VLOOKUP(G83,Unit_Conversions!$A$5:$C$28,2,FALSE())/(Q83*VLOOKUP(R83,Unit_Conversions!$A$5:$C$28,2,FALSE())),"")),"") -> 0.00405 | M83: =IFERROR(F83*L83,"") -> 0.243 | N83: =IFERROR(J83*L83,"") -> 0 | O83: Fixation Buffer B (CG000782). 37% BP531-25. | P83: =IFERROR(IF(LEFT(D83,1)="K",VLOOKUP(D83,Kit_Catalog!$A:$K,8,FALSE()),VLOOKUP(D83,Additional_Supply_Catalog!$A:$K,7,FALSE())),"") -> 101.25 | Q83: =IFERROR(IF(LEFT(D83,1)="K",VLOOKUP(D83,Kit_Catalog!$A:$K,7,FALSE()),VLOOKUP(D83,Additional_Supply_Catalog!$A:$K,8,FALSE())),"") -> 25 | R83: =IFERROR(IF(LEFT(D83,1)="K","rxn",VLOOKUP(D83,Additional_Supply_Catalog!$A:$K,9,FALSE())),"") -> mL
A84: VII. Flex v2 (fixation → GEM load) | B84: Item | C84: Nuclease-free Water | D84: R001 | E84: per Flex sample | F84: 1.5 | G84: mL | H84: =Inputs!$B$20 -> 0.1 | I84: =VLOOKUP(E84,Inputs!$D$5:$E$23,2,FALSE()) -> 0 | J84: =F84*I84*(1+H84) -> 0 | K84: =IF(ISNUMBER(MATCH(G84,{"tube","each","plate","vial","kit","bottle","aliquot","strainer","cap","lane-rxn","tip","strip","lane","channel","library","sample"},0)),ROUNDUP(J84,0),ROUND(J84,2)) -> 0 | L84: =IFERROR(IF(OR(D84="",P84="",Q84="",Q84=0),"",IF(VLOOKUP(R84,Unit_Conversions!$A$5:$C$28,3,FALSE())=VLOOKUP(G84,Unit_Conversions!$A$5:$C$28,3,FALSE()),P84*VLOOKUP(G84,Unit_Conversions!$A$5:$C$28,2,FALSE())/(Q84*VLOOKUP(R84,Unit_Conversions!$A$5:$C$28,2,FALSE())),"")),"") -> 0.02772 | M84: =IFERROR(F84*L84,"") -> 0.04158 | N84: =IFERROR(J84*L84,"") -> 0 | O84: Buffers (fixation/quench/hyb/wash). AM9937 recommended. | P84: =IFERROR(IF(LEFT(D84,1)="K",VLOOKUP(D84,Kit_Catalog!$A:$K,8,FALSE()),VLOOKUP(D84,Additional_Supply_Catalog!$A:$K,7,FALSE())),"") -> 13.86 | Q84: =IFERROR(IF(LEFT(D84,1)="K",VLOOKUP(D84,Kit_Catalog!$A:$K,7,FALSE()),VLOOKUP(D84,Additional_Supply_Catalog!$A:$K,8,FALSE())),"") -> 500 | R84: =IFERROR(IF(LEFT(D84,1)="K","rxn",VLOOKUP(D84,Additional_Supply_Catalog!$A:$K,9,FALSE())),"") -> mL
A85: VII. Flex v2 (fixation → GEM load) | B85: Item | C85: Glycerol (for 50% soln) | D85: R036 | E85: per Flex pool | F85: 0.5 | G85: mL | H85: =Inputs!$B$20 -> 0.1 | I85: =VLOOKUP(E85,Inputs!$D$5:$E$23,2,FALSE()) -> 0 | J85: =F85*I85*(1+H85) -> 0 | K85: =IF(ISNUMBER(MATCH(G85,{"tube","each","plate","vial","kit","bottle","aliquot","strainer","cap","lane-rxn","tip","strip","lane","channel","library","sample"},0)),ROUNDUP(J85,0),ROUND(J85,2)) -> 0 | L85: =IFERROR(IF(OR(D85="",P85="",Q85="",Q85=0),"",IF(VLOOKUP(R85,Unit_Conversions!$A$5:$C$28,3,FALSE())=VLOOKUP(G85,Unit_Conversions!$A$5:$C$28,3,FALSE()),P85*VLOOKUP(G85,Unit_Conversions!$A$5:$C$28,2,FALSE())/(Q85*VLOOKUP(R85,Unit_Conversions!$A$5:$C$28,2,FALSE())),"")),"") -> 0.6279 | M85: =IFERROR(F85*L85,"") -> 0.31395 | N85: =IFERROR(J85*L85,"") -> 0 | O85: 50% glycerol for -80C storage / unused chip wells. | P85: =IFERROR(IF(LEFT(D85,1)="K",VLOOKUP(D85,Kit_Catalog!$A:$K,8,FALSE()),VLOOKUP(D85,Additional_Supply_Catalog!$A:$K,7,FALSE())),"") -> 62.79 | Q85: =IFERROR(IF(LEFT(D85,1)="K",VLOOKUP(D85,Kit_Catalog!$A:$K,7,FALSE()),VLOOKUP(D85,Additional_Supply_Catalog!$A:$K,8,FALSE())),"") -> 100 | R85: =IFERROR(IF(LEFT(D85,1)="K","rxn",VLOOKUP(D85,Additional_Supply_Catalog!$A:$K,9,FALSE())),"") -> mL
A86: VII. Flex v2 (fixation → GEM load) | B86: Item | C86: DNA LoBind Tubes 1.5mL | D86: S004 | E86: per Flex sample | F86: 1 | G86: tube | H86: =Inputs!$B$20 -> 0.1 | I86: =VLOOKUP(E86,Inputs!$D$5:$E$23,2,FALSE()) -> 0 | J86: =F86*I86*(1+H86) -> 0 | K86: =IF(ISNUMBER(MATCH(G86,{"tube","each","plate","vial","kit","bottle","aliquot","strainer","cap","lane-rxn","tip","strip","lane","channel","library","sample"},0)),ROUNDUP(J86,0),ROUND(J86,2)) -> 0 | L86: =IFERROR(IF(OR(D86="",P86="",Q86="",Q86=0),"",IF(VLOOKUP(R86,Unit_Conversions!$A$5:$C$28,3,FALSE())=VLOOKUP(G86,Unit_Conversions!$A$5:$C$28,3,FALSE()),P86*VLOOKUP(G86,Unit_Conversions!$A$5:$C$28,2,FALSE())/(Q86*VLOOKUP(R86,Unit_Conversions!$A$5:$C$28,2,FALSE())),"")),"") -> 0.17956 | M86: =IFERROR(F86*L86,"") -> 0.17956 | N86: =IFERROR(J86*L86,"") -> 0 | O86: Hybridization / handling. | P86: =IFERROR(IF(LEFT(D86,1)="K",VLOOKUP(D86,Kit_Catalog!$A:$K,8,FALSE()),VLOOKUP(D86,Additional_Supply_Catalog!$A:$K,7,FALSE())),"") -> 44.89 | Q86: =IFERROR(IF(LEFT(D86,1)="K",VLOOKUP(D86,Kit_Catalog!$A:$K,7,FALSE()),VLOOKUP(D86,Additional_Supply_Catalog!$A:$K,8,FALSE())),"") -> 250 | R86: =IFERROR(IF(LEFT(D86,1)="K","rxn",VLOOKUP(D86,Additional_Supply_Catalog!$A:$K,9,FALSE())),"") -> tube
A87: VII. Flex v2 (fixation → GEM load) | B87: Item | C87: PCR 8-Tube Strips (0.2 mL) | D87: S008 | E87: per Flex sample | F87: 0.125 | G87: strip | H87: =Inputs!$B$20 -> 0.1 | I87: =VLOOKUP(E87,Inputs!$D$5:$E$23,2,FALSE()) -> 0 | J87: =F87*I87*(1+H87) -> 0 | K87: =IF(ISNUMBER(MATCH(G87,{"tube","each","plate","vial","kit","bottle","aliquot","strainer","cap","lane-rxn","tip","strip","lane","channel","library","sample"},0)),ROUNDUP(J87,0),ROUND(J87,2)) -> 0 | L87: =IFERROR(IF(OR(D87="",P87="",Q87="",Q87=0),"",IF(VLOOKUP(R87,Unit_Conversions!$A$5:$C$28,3,FALSE())=VLOOKUP(G87,Unit_Conversions!$A$5:$C$28,3,FALSE()),P87*VLOOKUP(G87,Unit_Conversions!$A$5:$C$28,2,FALSE())/(Q87*VLOOKUP(R87,Unit_Conversions!$A$5:$C$28,2,FALSE())),"")),"") -> 0.7804 | M87: =IFERROR(F87*L87,"") -> 0.09755 | N87: =IFERROR(J87*L87,"") -> 0 | O87: Hyb / GEM / PCR (strip shared across steps). 1 PCR tube per reaction; 8 tubes per strip. | P87: =IFERROR(IF(LEFT(D87,1)="K",VLOOKUP(D87,Kit_Catalog!$A:$K,8,FALSE()),VLOOKUP(D87,Additional_Supply_Catalog!$A:$K,7,FALSE())),"") -> 97.55 | Q87: =IFERROR(IF(LEFT(D87,1)="K",VLOOKUP(D87,Kit_Catalog!$A:$K,7,FALSE()),VLOOKUP(D87,Additional_Supply_Catalog!$A:$K,8,FALSE())),"") -> 125 | R87: =IFERROR(IF(LEFT(D87,1)="K","rxn",VLOOKUP(D87,Additional_Supply_Catalog!$A:$K,9,FALSE())),"") -> strip
A88: VII. Flex v2 (fixation → GEM load) | B88: Item | C88: 200 uL pipette tips | D88: S002 | E88: per Flex sample | F88: 6 | G88: tip | H88: =Inputs!$B$20 -> 0.1 | I88: =VLOOKUP(E88,Inputs!$D$5:$E$23,2,FALSE()) -> 0 | J88: =F88*I88*(1+H88) -> 0 | K88: =IF(ISNUMBER(MATCH(G88,{"tube","each","plate","vial","kit","bottle","aliquot","strainer","cap","lane-rxn","tip","strip","lane","channel","library","sample"},0)),ROUNDUP(J88,0),ROUND(J88,2)) -> 0 | L88: =IFERROR(IF(OR(D88="",P88="",Q88="",Q88=0),"",IF(VLOOKUP(R88,Unit_Conversions!$A$5:$C$28,3,FALSE())=VLOOKUP(G88,Unit_Conversions!$A$5:$C$28,3,FALSE()),P88*VLOOKUP(G88,Unit_Conversions!$A$5:$C$28,2,FALSE())/(Q88*VLOOKUP(R88,Unit_Conversions!$A$5:$C$28,2,FALSE())),"")),"") -> 0.018791667 | M88: =IFERROR(F88*L88,"") -> 0.11275 | N88: =IFERROR(J88*L88,"") -> 0 | O88: Estimate across fixation->load steps. | P88: =IFERROR(IF(LEFT(D88,1)="K",VLOOKUP(D88,Kit_Catalog!$A:$K,8,FALSE()),VLOOKUP(D88,Additional_Supply_Catalog!$A:$K,7,FALSE())),"") -> 180.4 | Q88: =IFERROR(IF(LEFT(D88,1)="K",VLOOKUP(D88,Kit_Catalog!$A:$K,7,FALSE()),VLOOKUP(D88,Additional_Supply_Catalog!$A:$K,8,FALSE())),"") -> 9600 | R88: =IFERROR(IF(LEFT(D88,1)="K","rxn",VLOOKUP(D88,Additional_Supply_Catalog!$A:$K,9,FALSE())),"") -> tip
A103: V. Sort stain | B103: Item | C103: TotalseqC HTO (sort) | D103: R018 | E103: per genetic pool | F103: 5 | G103: uL | H103: =Inputs!$B$20 -> 0.1 | I103: =VLOOKUP(E103,Inputs!$D$5:$E$23,2,FALSE()) -> 6 | J103: =F103*I103*(1+H103) -> 33 | K103: =IF(ISNUMBER(MATCH(G103,{"tube","each","plate","vial","kit","bottle","aliquot","strainer","cap","lane-rxn","tip","strip","lane","channel","library","sample"},0)),ROUNDUP(J103,0),ROUND(J103,2)) -> 33 | L103: =IFERROR(IF(OR(D103="",P103="",Q103="",Q103=0),"",IF(VLOOKUP(R103,Unit_Conversions!$A$5:$C$28,3,FALSE())=VLOOKUP(G103,Unit_Conversions!$A$5:$C$28,3,FALSE()),P103*VLOOKUP(G103,Unit_Conversions!$A$5:$C$28,2,FALSE())/(Q103*VLOOKUP(R103,Unit_Conversions!$A$5:$C$28,2,FALSE())),"")),"") -> 25.85 | M103: =IFERROR(F103*L103,"") -> 129.25 | N103: =IFERROR(J103*L103,"") -> 853.05 | O103: ADDED: source adds 5 uL TotalSeq-C HTO per sort pool (distinct hashtag/pool). | P103: =IFERROR(IF(LEFT(D103,1)="K",VLOOKUP(D103,Kit_Catalog!$A:$K,8,FALSE()),VLOOKUP(D103,Additional_Supply_Catalog!$A:$K,7,FALSE())),"") -> 517 | Q103: =IFERROR(IF(LEFT(D103,1)="K",VLOOKUP(D103,Kit_Catalog!$A:$K,7,FALSE()),VLOOKUP(D103,Additional_Supply_Catalog!$A:$K,8,FALSE())),"") -> 20 | R103: =IFERROR(IF(LEFT(D103,1)="K","rxn",VLOOKUP(D103,Additional_Supply_Catalog!$A:$K,9,FALSE())),"") -> uL
A104: V. Sort stain | B104: Item | C104: BSA (powder) | D104: R026 | E104: per genetic pool | F104: 0.04 | G104: g | H104: =Inputs!$B$20 -> 0.1 | I104: =VLOOKUP(E104,Inputs!$D$5:$E$23,2,FALSE()) -> 6 | J104: =F104*I104*(1+H104) -> 0.264 | K104: =IF(ISNUMBER(MATCH(G104,{"tube","each","plate","vial","kit","bottle","aliquot","strainer","cap","lane-rxn","tip","strip","lane","channel","library","sample"},0)),ROUNDUP(J104,0),ROUND(J104,2)) -> 0.26 | L104: =IFERROR(IF(OR(D104="",P104="",Q104="",Q104=0),"",IF(VLOOKUP(R104,Unit_Conversions!$A$5:$C$28,3,FALSE())=VLOOKUP(G104,Unit_Conversions!$A$5:$C$28,3,FALSE()),P104*VLOOKUP(G104,Unit_Conversions!$A$5:$C$28,2,FALSE())/(Q104*VLOOKUP(R104,Unit_Conversions!$A$5:$C$28,2,FALSE())),"")),"") -> 4.152 | M104: =IFERROR(F104*L104,"") -> 0.16608 | N104: =IFERROR(J104*L104,"") -> 1.096128 | O104: ADDED: 2 mL staining buffer wash/pool (source line 742) = 0.04 g BSA (2%). PBS for it is in the 6 mL sort PBS row. | P104: =IFERROR(IF(LEFT(D104,1)="K",VLOOKUP(D104,Kit_Catalog!$A:$K,8,FALSE()),VLOOKUP(D104,Additional_Supply_Catalog!$A:$K,7,FALSE())),"") -> 103.8 | Q104: =IFERROR(IF(LEFT(D104,1)="K",VLOOKUP(D104,Kit_Catalog!$A:$K,7,FALSE()),VLOOKUP(D104,Additional_Supply_Catalog!$A:$K,8,FALSE())),"") -> 25 | R104: =IFERROR(IF(LEFT(D104,1)="K","rxn",VLOOKUP(D104,Additional_Supply_Catalog!$A:$K,9,FALSE())),"") -> g
A105: IV. ASAP-seq | B105: Item | C105: 1X PBS | D105: R002 | E105: per super-pool | F105: 9 | G105: mL | H105: =Inputs!$B$20 -> 0.1 | I105: =VLOOKUP(E105,Inputs!$D$5:$E$23,2,FALSE()) -> 1 | J105: =F105*I105*(1+H105) -> 9.9 | K105: =IF(ISNUMBER(MATCH(G105,{"tube","each","plate","vial","kit","bottle","aliquot","strainer","cap","lane-rxn","tip","strip","lane","channel","library","sample"},0)),ROUNDUP(J105,0),ROUND(J105,2)) -> 9.9 | L105: =IFERROR(IF(OR(D105="",P105="",Q105="",Q105=0),"",IF(VLOOKUP(R105,Unit_Conversions!$A$5:$C$28,3,FALSE())=VLOOKUP(G105,Unit_Conversions!$A$5:$C$28,3,FALSE()),P105*VLOOKUP(G105,Unit_Conversions!$A$5:$C$28,2,FALSE())/(Q105*VLOOKUP(R105,Unit_Conversions!$A$5:$C$28,2,FALSE())),"")),"") -> 0.03804 | M105: =IFERROR(F105*L105,"") -> 0.34236 | N105: =IFERROR(J105*L105,"") -> 0.376596 | O105: ADDED: lyo-panel staining PBS for ASAP super-pool = CITE super-pool (9 mL). Fixation-wash PBS stays on the 2.45 mL row. | P105: =IFERROR(IF(LEFT(D105,1)="K",VLOOKUP(D105,Kit_Catalog!$A:$K,8,FALSE()),VLOOKUP(D105,Additional_Supply_Catalog!$A:$K,7,FALSE())),"") -> 19.02 | Q105: =IFERROR(IF(LEFT(D105,1)="K",VLOOKUP(D105,Kit_Catalog!$A:$K,7,FALSE()),VLOOKUP(D105,Additional_Supply_Catalog!$A:$K,8,FALSE())),"") -> 500 | R105: =IFERROR(IF(LEFT(D105,1)="K","rxn",VLOOKUP(D105,Additional_Supply_Catalog!$A:$K,9,FALSE())),"") -> mL

Sheet Post_GEM_Consumables
A1: Section | B1: Type | C1: Item / supply | D1: Item ID | E1: Scaling basis | F1: Amount per unit | G1: Unit | H1: Overage | I1: Count (x) | J1: Total needed | K1: Order (rounded) | L1: Unit price ($) | M1: Cost per basis-unit ($) | N1: Total cost ($) | O1: Notes | P1: _price | Q1: _stock | R1: _stockUnit
A2: Post-GEM: 5'-GEM | B2: Item | C2: Chromium GEM-X Single Cell 5' Kit v3 | D2: K009 | E2: per 5' GEM channel | F2: 1 | G2: channels | H2: =Inputs!$B$20 -> 0.1 | I2: =VLOOKUP(E2,Inputs!$D$5:$E$23,2,FALSE()) -> 8 | J2: =F2*I2*(1+H2) -> 8.8 | K2: =IF(ISNUMBER(MATCH(G2,{"tube","each","plate","vial","kit","bottle","aliquot","strainer","cap","lane-rxn","tip","strip","lane","channel","library","sample"},0)),ROUNDUP(J2,0),ROUND(J2,2)) -> 8.8 | L2: =IFERROR(IF(OR(D2="",P2="",Q2="",Q2=0),"",IF(VLOOKUP(R2,Unit_Conversions!$A$5:$C$28,3,FALSE())=VLOOKUP(G2,Unit_Conversions!$A$5:$C$28,3,FALSE()),P2*VLOOKUP(G2,Unit_Conversions!$A$5:$C$28,2,FALSE())/(Q2*VLOOKUP(R2,Unit_Conversions!$A$5:$C$28,2,FALSE())),"")),"") -> 1479.375 | M2: =IFERROR(F2*L2,"") -> 1479.375 | N2: =IFERROR(J2*L2,"") -> 13018.5 | O2: KIT | P2: =IFERROR(IF(LEFT(D2,1)="K",VLOOKUP(D2,Kit_Catalog!$A:$K,8,FALSE()),VLOOKUP(D2,Additional_Supply_Catalog!$A:$K,7,FALSE())),"") -> 23670 | Q2: =IFERROR(IF(LEFT(D2,1)="K",VLOOKUP(D2,Kit_Catalog!$A:$K,7,FALSE()),VLOOKUP(D2,Additional_Supply_Catalog!$A:$K,8,FALSE())),"") -> 16 | R2: =IFERROR(IF(LEFT(D2,1)="K","rxn",VLOOKUP(D2,Additional_Supply_Catalog!$A:$K,9,FALSE())),"") -> rxn
A3: Post-GEM: 5'-GEM | B3: Item | C3: Chromium GEM-X Single Cell 5' Chip Kit | D3: K011 | E3: per 5' GEM channel | F3: 1 | G3: channels | H3: =Inputs!$B$20 -> 0.1 | I3: =VLOOKUP(E3,Inputs!$D$5:$E$23,2,FALSE()) -> 8 | J3: =F3*I3*(1+H3) -> 8.8 | K3: =IF(ISNUMBER(MATCH(G3,{"tube","each","plate","vial","kit","bottle","aliquot","strainer","cap","lane-rxn","tip","strip","lane","channel","library","sample"},0)),ROUNDUP(J3,0),ROUND(J3,2)) -> 8.8 | L3: =IFERROR(IF(OR(D3="",P3="",Q3="",Q3=0),"",IF(VLOOKUP(R3,Unit_Conversions!$A$5:$C$28,3,FALSE())=VLOOKUP(G3,Unit_Conversions!$A$5:$C$28,3,FALSE()),P3*VLOOKUP(G3,Unit_Conversions!$A$5:$C$28,2,FALSE())/(Q3*VLOOKUP(R3,Unit_Conversions!$A$5:$C$28,2,FALSE())),"")),"") -> 78.125 | M3: =IFERROR(F3*L3,"") -> 78.125 | N3: =IFERROR(J3*L3,"") -> 687.5 | O3: KIT | P3: =IFERROR(IF(LEFT(D3,1)="K",VLOOKUP(D3,Kit_Catalog!$A:$K,8,FALSE()),VLOOKUP(D3,Additional_Supply_Catalog!$A:$K,7,FALSE())),"") -> 1250 | Q3: =IFERROR(IF(LEFT(D3,1)="K",VLOOKUP(D3,Kit_Catalog!$A:$K,7,FALSE()),VLOOKUP(D3,Additional_Supply_Catalog!$A:$K,8,FALSE())),"") -> 16 | R3: =IFERROR(IF(LEFT(D3,1)="K","rxn",VLOOKUP(D3,Additional_Supply_Catalog!$A:$K,9,FALSE())),"") -> rxn
A4: Post-GEM: 5'-GEM | B4: Item | C4: Buffer EB | D4: R004 | E4: per 5' GEM channel | F4: 0.179 | G4: mL | H4: =Inputs!$B$20 -> 0.1 | I4: =VLOOKUP(E4,Inputs!$D$5:$E$23,2,FALSE()) -> 8 | J4: =F4*I4*(1+H4) -> 1.5752 | K4: =IF(ISNUMBER(MATCH(G4,{"tube","each","plate","vial","kit","bottle","aliquot","strainer","cap","lane-rxn","tip","strip","lane","channel","library","sample"},0)),ROUNDUP(J4,0),ROUND(J4,2)) -> 1.58 | L4: =IFERROR(IF(OR(D4="",P4="",Q4="",Q4=0),"",IF(VLOOKUP(R4,Unit_Conversions!$A$5:$C$28,3,FALSE())=VLOOKUP(G4,Unit_Conversions!$A$5:$C$28,3,FALSE()),P4*VLOOKUP(G4,Unit_Conversions!$A$5:$C$28,2,FALSE())/(Q4*VLOOKUP(R4,Unit_Conversions!$A$5:$C$28,2,FALSE())),"")),"") -> 0.1996 | M4: =IFERROR(F4*L4,"") -> 0.0357284 | N4: =IFERROR(J4*L4,"") -> 0.31440992 | O4: SUPPLY | P4: =IFERROR(IF(LEFT(D4,1)="K",VLOOKUP(D4,Kit_Catalog!$A:$K,8,FALSE()),VLOOKUP(D4,Additional_Supply_Catalog!$A:$K,7,FALSE())),"") -> 49.9 | Q4: =IFERROR(IF(LEFT(D4,1)="K",VLOOKUP(D4,Kit_Catalog!$A:$K,7,FALSE()),VLOOKUP(D4,Additional_Supply_Catalog!$A:$K,8,FALSE())),"") -> 250 | R4: =IFERROR(IF(LEFT(D4,1)="K","rxn",VLOOKUP(D4,Additional_Supply_Catalog!$A:$K,9,FALSE())),"") -> mL
A5: Post-GEM: 5'-GEM | B5: Item | C5: Ethanol | D5: R003 | E5: per 5' GEM channel | F5: 1.3 | G5: mL | H5: =Inputs!$B$20 -> 0.1 | I5: =VLOOKUP(E5,Inputs!$D$5:$E$23,2,FALSE()) -> 8 | J5: =F5*I5*(1+H5) -> 11.44 | K5: =IF(ISNUMBER(MATCH(G5,{"tube","each","plate","vial","kit","bottle","aliquot","strainer","cap","lane-rxn","tip","strip","lane","channel","library","sample"},0)),ROUNDUP(J5,0),ROUND(J5,2)) -> 11.44 | L5: =IFERROR(IF(OR(D5="",P5="",Q5="",Q5=0),"",IF(VLOOKUP(R5,Unit_Conversions!$A$5:$C$28,3,FALSE())=VLOOKUP(G5,Unit_Conversions!$A$5:$C$28,3,FALSE()),P5*VLOOKUP(G5,Unit_Conversions!$A$5:$C$28,2,FALSE())/(Q5*VLOOKUP(R5,Unit_Conversions!$A$5:$C$28,2,FALSE())),"")),"") -> 0.218 | M5: =IFERROR(F5*L5,"") -> 0.2834 | N5: =IFERROR(J5*L5,"") -> 2.49392 | O5: SUPPLY | P5: =IFERROR(IF(LEFT(D5,1)="K",VLOOKUP(D5,Kit_Catalog!$A:$K,8,FALSE()),VLOOKUP(D5,Additional_Supply_Catalog!$A:$K,7,FALSE())),"") -> 109 | Q5: =IFERROR(IF(LEFT(D5,1)="K",VLOOKUP(D5,Kit_Catalog!$A:$K,7,FALSE()),VLOOKUP(D5,Additional_Supply_Catalog!$A:$K,8,FALSE())),"") -> 500 | R5: =IFERROR(IF(LEFT(D5,1)="K","rxn",VLOOKUP(D5,Additional_Supply_Catalog!$A:$K,9,FALSE())),"") -> mL
A6: Post-GEM: 5'-GEM | B6: Item | C6: SPRISelect | D6: R005 | E6: per 5' GEM channel | F6: 0.13 | G6: mL | H6: =Inputs!$B$20 -> 0.1 | I6: =VLOOKUP(E6,Inputs!$D$5:$E$23,2,FALSE()) -> 8 | J6: =F6*I6*(1+H6) -> 1.144 | K6: =IF(ISNUMBER(MATCH(G6,{"tube","each","plate","vial","kit","bottle","aliquot","strainer","cap","lane-rxn","tip","strip","lane","channel","library","sample"},0)),ROUNDUP(J6,0),ROUND(J6,2)) -> 1.14 | L6: =IFERROR(IF(OR(D6="",P6="",Q6="",Q6=0),"",IF(VLOOKUP(R6,Unit_Conversions!$A$5:$C$28,3,FALSE())=VLOOKUP(G6,Unit_Conversions!$A$5:$C$28,3,FALSE()),P6*VLOOKUP(G6,Unit_Conversions!$A$5:$C$28,2,FALSE())/(Q6*VLOOKUP(R6,Unit_Conversions!$A$5:$C$28,2,FALSE())),"")),"") -> 27.265 | M6: =IFERROR(F6*L6,"") -> 3.54445 | N6: =IFERROR(J6*L6,"") -> 31.19116 | O6: SUPPLY | P6: =IFERROR(IF(LEFT(D6,1)="K",VLOOKUP(D6,Kit_Catalog!$A:$K,8,FALSE()),VLOOKUP(D6,Additional_Supply_Catalog!$A:$K,7,FALSE())),"") -> 1635.9 | Q6: =IFERROR(IF(LEFT(D6,1)="K",VLOOKUP(D6,Kit_Catalog!$A:$K,7,FALSE()),VLOOKUP(D6,Additional_Supply_Catalog!$A:$K,8,FALSE())),"") -> 60 | R6: =IFERROR(IF(LEFT(D6,1)="K","rxn",VLOOKUP(D6,Additional_Supply_Catalog!$A:$K,9,FALSE())),"") -> mL
A7: Post-GEM: 5'-GEM | B7: Item | C7: PCR strip tubes | D7: S008 | E7: per 5' GEM channel | F7: 0.125 | G7: strip | H7: =Inputs!$B$20 -> 0.1 | I7: =VLOOKUP(E7,Inputs!$D$5:$E$23,2,FALSE()) -> 8 | J7: =F7*I7*(1+H7) -> 1.1 | K7: =IF(ISNUMBER(MATCH(G7,{"tube","each","plate","vial","kit","bottle","aliquot","strainer","cap","lane-rxn","tip","strip","lane","channel","library","sample"},0)),ROUNDUP(J7,0),ROUND(J7,2)) -> 2 | L7: =IFERROR(IF(OR(D7="",P7="",Q7="",Q7=0),"",IF(VLOOKUP(R7,Unit_Conversions!$A$5:$C$28,3,FALSE())=VLOOKUP(G7,Unit_Conversions!$A$5:$C$28,3,FALSE()),P7*VLOOKUP(G7,Unit_Conversions!$A$5:$C$28,2,FALSE())/(Q7*VLOOKUP(R7,Unit_Conversions!$A$5:$C$28,2,FALSE())),"")),"") -> 0.7804 | M7: =IFERROR(F7*L7,"") -> 0.09755 | N7: =IFERROR(J7*L7,"") -> 0.85844 | O7: (manual) [no catalog price] 1 PCR tube per reaction; 8 tubes per strip. | P7: =IFERROR(IF(LEFT(D7,1)="K",VLOOKUP(D7,Kit_Catalog!$A:$K,8,FALSE()),VLOOKUP(D7,Additional_Supply_Catalog!$A:$K,7,FALSE())),"") -> 97.55 | Q7: =IFERROR(IF(LEFT(D7,1)="K",VLOOKUP(D7,Kit_Catalog!$A:$K,7,FALSE()),VLOOKUP(D7,Additional_Supply_Catalog!$A:$K,8,FALSE())),"") -> 125 | R7: =IFERROR(IF(LEFT(D7,1)="K","rxn",VLOOKUP(D7,Additional_Supply_Catalog!$A:$K,9,FALSE())),"") -> strip
A8: Post-GEM: 5'-GEM | B8: Item | C8: 1000uL pipette tips | D8: S001 | E8: per 5' GEM channel | F8: 1 | G8: tip | H8: =Inputs!$B$20 -> 0.1 | I8: =VLOOKUP(E8,Inputs!$D$5:$E$23,2,FALSE()) -> 8 | J8: =F8*I8*(1+H8) -> 8.8 | K8: =IF(ISNUMBER(MATCH(G8,{"tube","each","plate","vial","kit","bottle","aliquot","strainer","cap","lane-rxn","tip","strip","lane","channel","library","sample"},0)),ROUNDUP(J8,0),ROUND(J8,2)) -> 9 | L8: =IFERROR(IF(OR(D8="",P8="",Q8="",Q8=0),"",IF(VLOOKUP(R8,Unit_Conversions!$A$5:$C$28,3,FALSE())=VLOOKUP(G8,Unit_Conversions!$A$5:$C$28,3,FALSE()),P8*VLOOKUP(G8,Unit_Conversions!$A$5:$C$28,2,FALSE())/(Q8*VLOOKUP(R8,Unit_Conversions!$A$5:$C$28,2,FALSE())),"")),"") -> 0.030410156 | M8: =IFERROR(F8*L8,"") -> 0.030410156 | N8: =IFERROR(J8*L8,"") -> 0.26760937 | O8: (manual) [no catalog price] | P8: =IFERROR(IF(LEFT(D8,1)="K",VLOOKUP(D8,Kit_Catalog!$A:$K,8,FALSE()),VLOOKUP(D8,Additional_Supply_Catalog!$A:$K,7,FALSE())),"") -> 46.71 | Q8: =IFERROR(IF(LEFT(D8,1)="K",VLOOKUP(D8,Kit_Catalog!$A:$K,7,FALSE()),VLOOKUP(D8,Additional_Supply_Catalog!$A:$K,8,FALSE())),"") -> 1536 | R8: =IFERROR(IF(LEFT(D8,1)="K","rxn",VLOOKUP(D8,Additional_Supply_Catalog!$A:$K,9,FALSE())),"") -> tip
A9: Post-GEM: 5'-GEM | B9: Item | C9: 200uL pipette tips | D9: S002 | E9: per 5' GEM channel | F9: 2 | G9: tip | H9: =Inputs!$B$20 -> 0.1 | I9: =VLOOKUP(E9,Inputs!$D$5:$E$23,2,FALSE()) -> 8 | J9: =F9*I9*(1+H9) -> 17.6 | K9: =IF(ISNUMBER(MATCH(G9,{"tube","each","plate","vial","kit","bottle","aliquot","strainer","cap","lane-rxn","tip","strip","lane","channel","library","sample"},0)),ROUNDUP(J9,0),ROUND(J9,2)) -> 18 | L9: =IFERROR(IF(OR(D9="",P9="",Q9="",Q9=0),"",IF(VLOOKUP(R9,Unit_Conversions!$A$5:$C$28,3,FALSE())=VLOOKUP(G9,Unit_Conversions!$A$5:$C$28,3,FALSE()),P9*VLOOKUP(G9,Unit_Conversions!$A$5:$C$28,2,FALSE())/(Q9*VLOOKUP(R9,Unit_Conversions!$A$5:$C$28,2,FALSE())),"")),"") -> 0.018791667 | M9: =IFERROR(F9*L9,"") -> 0.037583333 | N9: =IFERROR(J9*L9,"") -> 0.33073333 | O9: (manual) [no catalog price] | P9: =IFERROR(IF(LEFT(D9,1)="K",VLOOKUP(D9,Kit_Catalog!$A:$K,8,FALSE()),VLOOKUP(D9,Additional_Supply_Catalog!$A:$K,7,FALSE())),"") -> 180.4 | Q9: =IFERROR(IF(LEFT(D9,1)="K",VLOOKUP(D9,Kit_Catalog!$A:$K,7,FALSE()),VLOOKUP(D9,Additional_Supply_Catalog!$A:$K,8,FALSE())),"") -> 9600 | R9: =IFERROR(IF(LEFT(D9,1)="K","rxn",VLOOKUP(D9,Additional_Supply_Catalog!$A:$K,9,FALSE())),"") -> tip
A10: Post-GEM: 5'-GEM | B10: Item | C10: 20uL pipette tips | D10: S003 | E10: per 5' GEM channel | F10: 2 | G10: tip | H10: =Inputs!$B$20 -> 0.1 | I10: =VLOOKUP(E10,Inputs!$D$5:$E$23,2,FALSE()) -> 8 | J10: =F10*I10*(1+H10) -> 17.6 | K10: =IF(ISNUMBER(MATCH(G10,{"tube","each","plate","vial","kit","bottle","aliquot","strainer","cap","lane-rxn","tip","strip","lane","channel","library","sample"},0)),ROUNDUP(J10,0),ROUND(J10,2)) -> 18 | L10: =IFERROR(IF(OR(D10="",P10="",Q10="",Q10=0),"",IF(VLOOKUP(R10,Unit_Conversions!$A$5:$C$28,3,FALSE())=VLOOKUP(G10,Unit_Conversions!$A$5:$C$28,3,FALSE()),P10*VLOOKUP(G10,Unit_Conversions!$A$5:$C$28,2,FALSE())/(Q10*VLOOKUP(R10,Unit_Conversions!$A$5:$C$28,2,FALSE())),"")),"") -> 0.018791667 | M10: =IFERROR(F10*L10,"") -> 0.037583333 | N10: =IFERROR(J10*L10,"") -> 0.33073333 | O10: (manual) [no catalog price] | P10: =IFERROR(IF(LEFT(D10,1)="K",VLOOKUP(D10,Kit_Catalog!$A:$K,8,FALSE()),VLOOKUP(D10,Additional_Supply_Catalog!$A:$K,7,FALSE())),"") -> 180.4 | Q10: =IFERROR(IF(LEFT(D10,1)="K",VLOOKUP(D10,Kit_Catalog!$A:$K,7,FALSE()),VLOOKUP(D10,Additional_Supply_Catalog!$A:$K,8,FALSE())),"") -> 9600 | R10: =IFERROR(IF(LEFT(D10,1)="K","rxn",VLOOKUP(D10,Additional_Supply_Catalog!$A:$K,9,FALSE())),"") -> tip
A11: Post-GEM: 5'-GEM | B11: Item | C11: Eppendorf Tubes | D11: S004 | E11: per 5' GEM channel | F11: 1 | G11: tube | H11: =Inputs!$B$20 -> 0.1 | I11: =VLOOKUP(E11,Inputs!$D$5:$E$23,2,FALSE()) -> 8 | J11: =F11*I11*(1+H11) -> 8.8 | K11: =IF(ISNUMBER(MATCH(G11,{"tube","each","plate","vial","kit","bottle","aliquot","strainer","cap","lane-rxn","tip","strip","lane","channel","library","sample"},0)),ROUNDUP(J11,0),ROUND(J11,2)) -> 9 | L11: =IFERROR(IF(OR(D11="",P11="",Q11="",Q11=0),"",IF(VLOOKUP(R11,Unit_Conversions!$A$5:$C$28,3,FALSE())=VLOOKUP(G11,Unit_Conversions!$A$5:$C$28,3,FALSE()),P11*VLOOKUP(G11,Unit_Conversions!$A$5:$C$28,2,FALSE())/(Q11*VLOOKUP(R11,Unit_Conversions!$A$5:$C$28,2,FALSE())),"")),"") -> 0.17956 | M11: =IFERROR(F11*L11,"") -> 0.17956 | N11: =IFERROR(J11*L11,"") -> 1.580128 | O11: (manual) [no catalog price] | P11: =IFERROR(IF(LEFT(D11,1)="K",VLOOKUP(D11,Kit_Catalog!$A:$K,8,FALSE()),VLOOKUP(D11,Additional_Supply_Catalog!$A:$K,7,FALSE())),"") -> 44.89 | Q11: =IFERROR(IF(LEFT(D11,1)="K",VLOOKUP(D11,Kit_Catalog!$A:$K,7,FALSE()),VLOOKUP(D11,Additional_Supply_Catalog!$A:$K,8,FALSE())),"") -> 250 | R11: =IFERROR(IF(LEFT(D11,1)="K","rxn",VLOOKUP(D11,Additional_Supply_Catalog!$A:$K,9,FALSE())),"") -> tube
A12: Post-GEM: 5'-GEM | B12: Item | C12: Sterile Water | D12: R001 | E12: per 5' GEM channel | F12: 0.005 | G12: mL | H12: =Inputs!$B$20 -> 0.1 | I12: =VLOOKUP(E12,Inputs!$D$5:$E$23,2,FALSE()) -> 8 | J12: =F12*I12*(1+H12) -> 0.044 | K12: =IF(ISNUMBER(MATCH(G12,{"tube","each","plate","vial","kit","bottle","aliquot","strainer","cap","lane-rxn","tip","strip","lane","channel","library","sample"},0)),ROUNDUP(J12,0),ROUND(J12,2)) -> 0.04 | L12: =IFERROR(IF(OR(D12="",P12="",Q12="",Q12=0),"",IF(VLOOKUP(R12,Unit_Conversions!$A$5:$C$28,3,FALSE())=VLOOKUP(G12,Unit_Conversions!$A$5:$C$28,3,FALSE()),P12*VLOOKUP(G12,Unit_Conversions!$A$5:$C$28,2,FALSE())/(Q12*VLOOKUP(R12,Unit_Conversions!$A$5:$C$28,2,FALSE())),"")),"") -> 0.02772 | M12: =IFERROR(F12*L12,"") -> 0.0001386 | N12: =IFERROR(J12*L12,"") -> 0.00121968 | O12: SUPPLY [no catalog price] | P12: =IFERROR(IF(LEFT(D12,1)="K",VLOOKUP(D12,Kit_Catalog!$A:$K,8,FALSE()),VLOOKUP(D12,Additional_Supply_Catalog!$A:$K,7,FALSE())),"") -> 13.86 | Q12: =IFERROR(IF(LEFT(D12,1)="K",VLOOKUP(D12,Kit_Catalog!$A:$K,7,FALSE()),VLOOKUP(D12,Additional_Supply_Catalog!$A:$K,8,FALSE())),"") -> 500 | R12: =IFERROR(IF(LEFT(D12,1)="K","rxn",VLOOKUP(D12,Additional_Supply_Catalog!$A:$K,9,FALSE())),"") -> mL
A13: Post-GEM: 5'-GEM | B13: Item | C13: TapeStation HS D5000 kit (cDNA/amplicon QC) | E13: per 5' GEM channel | F13: 1 | G13: sample | H13: =Inputs!$B$20 -> 0.1 | I13: =VLOOKUP(E13,Inputs!$D$5:$E$23,2,FALSE()) -> 8 | J13: =F13*I13*(1+H13) -> 8.8 | K13: =IF(ISNUMBER(MATCH(G13,{"tube","each","plate","vial","kit","bottle","aliquot","strainer","cap","lane-rxn","tip","strip","lane","channel","library","sample"},0)),ROUNDUP(J13,0),ROUND(J13,2)) -> 9 | L13: =IFERROR(IF(OR(D13="",P13="",Q13="",Q13=0),"",IF(VLOOKUP(R13,Unit_Conversions!$A$5:$C$28,3,FALSE())=VLOOKUP(G13,Unit_Conversions!$A$5:$C$28,3,FALSE()),P13*VLOOKUP(G13,Unit_Conversions!$A$5:$C$28,2,FALSE())/(Q13*VLOOKUP(R13,Unit_Conversions!$A$5:$C$28,2,FALSE())),"")),"") | M13: =IFERROR(F13*L13,"") | N13: =IFERROR(J13*L13,"") | O13: (manual) [no catalog price] | P13: =IFERROR(IF(LEFT(D13,1)="K",VLOOKUP(D13,Kit_Catalog!$A:$K,8,FALSE()),VLOOKUP(D13,Additional_Supply_Catalog!$A:$K,7,FALSE())),"") | Q13: =IFERROR(IF(LEFT(D13,1)="K",VLOOKUP(D13,Kit_Catalog!$A:$K,7,FALSE()),VLOOKUP(D13,Additional_Supply_Catalog!$A:$K,8,FALSE())),"") | R13: =IFERROR(IF(LEFT(D13,1)="K","rxn",VLOOKUP(D13,Additional_Supply_Catalog!$A:$K,9,FALSE())),"")
A14: Post-GEM: ATAC-GEM | B14: Item | C14: Chromium Next GEM Single Cell ATAC Kit v2 | D14: K030 | E14: per ATAC GEM channel | F14: 1 | G14: channels | H14: =Inputs!$B$20 -> 0.1 | I14: =VLOOKUP(E14,Inputs!$D$5:$E$23,2,FALSE()) -> 2 | J14: =F14*I14*(1+H14) -> 2.2 | K14: =IF(ISNUMBER(MATCH(G14,{"tube","each","plate","vial","kit","bottle","aliquot","strainer","cap","lane-rxn","tip","strip","lane","channel","library","sample"},0)),ROUNDUP(J14,0),ROUND(J14,2)) -> 2.2 | L14: =IFERROR(IF(OR(D14="",P14="",Q14="",Q14=0),"",IF(VLOOKUP(R14,Unit_Conversions!$A$5:$C$28,3,FALSE())=VLOOKUP(G14,Unit_Conversions!$A$5:$C$28,3,FALSE()),P14*VLOOKUP(G14,Unit_Conversions!$A$5:$C$28,2,FALSE())/(Q14*VLOOKUP(R14,Unit_Conversions!$A$5:$C$28,2,FALSE())),"")),"") -> 1562.5 | M14: =IFERROR(F14*L14,"") -> 1562.5 | N14: =IFERROR(J14*L14,"") -> 3437.5 | O14: KIT | P14: =IFERROR(IF(LEFT(D14,1)="K",VLOOKUP(D14,Kit_Catalog!$A:$K,8,FALSE()),VLOOKUP(D14,Additional_Supply_Catalog!$A:$K,7,FALSE())),"") -> 25000 | Q14: =IFERROR(IF(LEFT(D14,1)="K",VLOOKUP(D14,Kit_Catalog!$A:$K,7,FALSE()),VLOOKUP(D14,Additional_Supply_Catalog!$A:$K,8,FALSE())),"") -> 16 | R14: =IFERROR(IF(LEFT(D14,1)="K","rxn",VLOOKUP(D14,Additional_Supply_Catalog!$A:$K,9,FALSE())),"") -> rxn
A15: Post-GEM: ATAC-GEM | B15: Item | C15: Chromium Next GEM Chip H Single Cell Kit | D15: K031 | E15: per ATAC GEM channel | F15: 1 | G15: channels | H15: =Inputs!$B$20 -> 0.1 | I15: =VLOOKUP(E15,Inputs!$D$5:$E$23,2,FALSE()) -> 2 | J15: =F15*I15*(1+H15) -> 2.2 | K15: =IF(ISNUMBER(MATCH(G15,{"tube","each","plate","vial","kit","bottle","aliquot","strainer","cap","lane-rxn","tip","strip","lane","channel","library","sample"},0)),ROUNDUP(J15,0),ROUND(J15,2)) -> 2.2 | L15: =IFERROR(IF(OR(D15="",P15="",Q15="",Q15=0),"",IF(VLOOKUP(R15,Unit_Conversions!$A$5:$C$28,3,FALSE())=VLOOKUP(G15,Unit_Conversions!$A$5:$C$28,3,FALSE()),P15*VLOOKUP(G15,Unit_Conversions!$A$5:$C$28,2,FALSE())/(Q15*VLOOKUP(R15,Unit_Conversions!$A$5:$C$28,2,FALSE())),"")),"") -> 37.5 | M15: =IFERROR(F15*L15,"") -> 37.5 | N15: =IFERROR(J15*L15,"") -> 82.5 | O15: KIT | P15: =IFERROR(IF(LEFT(D15,1)="K",VLOOKUP(D15,Kit_Catalog!$A:$K,8,FALSE()),VLOOKUP(D15,Additional_Supply_Catalog!$A:$K,7,FALSE())),"") -> 1800 | Q15: =IFERROR(IF(LEFT(D15,1)="K",VLOOKUP(D15,Kit_Catalog!$A:$K,7,FALSE()),VLOOKUP(D15,Additional_Supply_Catalog!$A:$K,8,FALSE())),"") -> 48 | R15: =IFERROR(IF(LEFT(D15,1)="K","rxn",VLOOKUP(D15,Additional_Supply_Catalog!$A:$K,9,FALSE())),"") -> rxn
A16: Post-GEM: ATAC-GEM | B16: Item | C16: Single Index Kit N, Set A | D16: K033 | E16: per ATAC GEM channel | F16: 1 | G16: channels | H16: =Inputs!$B$20 -> 0.1 | I16: =VLOOKUP(E16,Inputs!$D$5:$E$23,2,FALSE()) -> 2 | J16: =F16*I16*(1+H16) -> 2.2 | K16: =IF(ISNUMBER(MATCH(G16,{"tube","each","plate","vial","kit","bottle","aliquot","strainer","cap","lane-rxn","tip","strip","lane","channel","library","sample"},0)),ROUNDUP(J16,0),ROUND(J16,2)) -> 2.2 | L16: =IFERROR(IF(OR(D16="",P16="",Q16="",Q16=0),"",IF(VLOOKUP(R16,Unit_Conversions!$A$5:$C$28,3,FALSE())=VLOOKUP(G16,Unit_Conversions!$A$5:$C$28,3,FALSE()),P16*VLOOKUP(G16,Unit_Conversions!$A$5:$C$28,2,FALSE())/(Q16*VLOOKUP(R16,Unit_Conversions!$A$5:$C$28,2,FALSE())),"")),"") -> 10 | M16: =IFERROR(F16*L16,"") -> 10 | N16: =IFERROR(J16*L16,"") -> 22 | O16: KIT | P16: =IFERROR(IF(LEFT(D16,1)="K",VLOOKUP(D16,Kit_Catalog!$A:$K,8,FALSE()),VLOOKUP(D16,Additional_Supply_Catalog!$A:$K,7,FALSE())),"") -> 960 | Q16: =IFERROR(IF(LEFT(D16,1)="K",VLOOKUP(D16,Kit_Catalog!$A:$K,7,FALSE()),VLOOKUP(D16,Additional_Supply_Catalog!$A:$K,8,FALSE())),"") -> 96 | R16: =IFERROR(IF(LEFT(D16,1)="K","rxn",VLOOKUP(D16,Additional_Supply_Catalog!$A:$K,9,FALSE())),"") -> rxn
A17: Post-GEM: 5'-GEX | B17: Item | C17: Library Construction Kit C | D17: K012 | E17: per 5'-GEX library | F17: 1 | G17: channels | H17: =Inputs!$B$20 -> 0.1 | I17: =VLOOKUP(E17,Inputs!$D$5:$E$23,2,FALSE()) -> 8 | J17: =F17*I17*(1+H17) -> 8.8 | K17: =IF(ISNUMBER(MATCH(G17,{"tube","each","plate","vial","kit","bottle","aliquot","strainer","cap","lane-rxn","tip","strip","lane","channel","library","sample"},0)),ROUNDUP(J17,0),ROUND(J17,2)) -> 8.8 | L17: =IFERROR(IF(OR(D17="",P17="",Q17="",Q17=0),"",IF(VLOOKUP(R17,Unit_Conversions!$A$5:$C$28,3,FALSE())=VLOOKUP(G17,Unit_Conversions!$A$5:$C$28,3,FALSE()),P17*VLOOKUP(G17,Unit_Conversions!$A$5:$C$28,2,FALSE())/(Q17*VLOOKUP(R17,Unit_Conversions!$A$5:$C$28,2,FALSE())),"")),"") -> 78.125 | M17: =IFERROR(F17*L17,"") -> 78.125 | N17: =IFERROR(J17*L17,"") -> 687.5 | O17: KIT | P17: =IFERROR(IF(LEFT(D17,1)="K",VLOOKUP(D17,Kit_Catalog!$A:$K,8,FALSE()),VLOOKUP(D17,Additional_Supply_Catalog!$A:$K,7,FALSE())),"") -> 1250 | Q17: =IFERROR(IF(LEFT(D17,1)="K",VLOOKUP(D17,Kit_Catalog!$A:$K,7,FALSE()),VLOOKUP(D17,Additional_Supply_Catalog!$A:$K,8,FALSE())),"") -> 16 | R17: =IFERROR(IF(LEFT(D17,1)="K","rxn",VLOOKUP(D17,Additional_Supply_Catalog!$A:$K,9,FALSE())),"") -> rxn
A18: Post-GEM: 5'-GEX | B18: Item | C18: Dual Index Kit TT, Set A | D18: K013 | E18: per 5'-GEX library | F18: 1 | G18: channels | H18: =Inputs!$B$20 -> 0.1 | I18: =VLOOKUP(E18,Inputs!$D$5:$E$23,2,FALSE()) -> 8 | J18: =F18*I18*(1+H18) -> 8.8 | K18: =IF(ISNUMBER(MATCH(G18,{"tube","each","plate","vial","kit","bottle","aliquot","strainer","cap","lane-rxn","tip","strip","lane","channel","library","sample"},0)),ROUNDUP(J18,0),ROUND(J18,2)) -> 8.8 | L18: =IFERROR(IF(OR(D18="",P18="",Q18="",Q18=0),"",IF(VLOOKUP(R18,Unit_Conversions!$A$5:$C$28,3,FALSE())=VLOOKUP(G18,Unit_Conversions!$A$5:$C$28,3,FALSE()),P18*VLOOKUP(G18,Unit_Conversions!$A$5:$C$28,2,FALSE())/(Q18*VLOOKUP(R18,Unit_Conversions!$A$5:$C$28,2,FALSE())),"")),"") -> 10 | M18: =IFERROR(F18*L18,"") -> 10 | N18: =IFERROR(J18*L18,"") -> 88 | O18: KIT | P18: =IFERROR(IF(LEFT(D18,1)="K",VLOOKUP(D18,Kit_Catalog!$A:$K,8,FALSE()),VLOOKUP(D18,Additional_Supply_Catalog!$A:$K,7,FALSE())),"") -> 960 | Q18: =IFERROR(IF(LEFT(D18,1)="K",VLOOKUP(D18,Kit_Catalog!$A:$K,7,FALSE()),VLOOKUP(D18,Additional_Supply_Catalog!$A:$K,8,FALSE())),"") -> 96 | R18: =IFERROR(IF(LEFT(D18,1)="K","rxn",VLOOKUP(D18,Additional_Supply_Catalog!$A:$K,9,FALSE())),"") -> rxn
A19: Post-GEM: 5'-GEX | B19: Item | C19: Buffer EB | D19: R004 | E19: per 5'-GEX library | F19: 0.1415 | G19: mL | H19: =Inputs!$B$20 -> 0.1 | I19: =VLOOKUP(E19,Inputs!$D$5:$E$23,2,FALSE()) -> 8 | J19: =F19*I19*(1+H19) -> 1.2452 | K19: =IF(ISNUMBER(MATCH(G19,{"tube","each","plate","vial","kit","bottle","aliquot","strainer","cap","lane-rxn","tip","strip","lane","channel","library","sample"},0)),ROUNDUP(J19,0),ROUND(J19,2)) -> 1.25 | L19: =IFERROR(IF(OR(D19="",P19="",Q19="",Q19=0),"",IF(VLOOKUP(R19,Unit_Conversions!$A$5:$C$28,3,FALSE())=VLOOKUP(G19,Unit_Conversions!$A$5:$C$28,3,FALSE()),P19*VLOOKUP(G19,Unit_Conversions!$A$5:$C$28,2,FALSE())/(Q19*VLOOKUP(R19,Unit_Conversions!$A$5:$C$28,2,FALSE())),"")),"") -> 0.1996 | M19: =IFERROR(F19*L19,"") -> 0.0282434 | N19: =IFERROR(J19*L19,"") -> 0.24854192 | O19: SUPPLY | P19: =IFERROR(IF(LEFT(D19,1)="K",VLOOKUP(D19,Kit_Catalog!$A:$K,8,FALSE()),VLOOKUP(D19,Additional_Supply_Catalog!$A:$K,7,FALSE())),"") -> 49.9 | Q19: =IFERROR(IF(LEFT(D19,1)="K",VLOOKUP(D19,Kit_Catalog!$A:$K,7,FALSE()),VLOOKUP(D19,Additional_Supply_Catalog!$A:$K,8,FALSE())),"") -> 250 | R19: =IFERROR(IF(LEFT(D19,1)="K","rxn",VLOOKUP(D19,Additional_Supply_Catalog!$A:$K,9,FALSE())),"") -> mL
A20: Post-GEM: 5'-GEX | B20: Item | C20: Ethanol | D20: R003 | E20: per 5'-GEX library | F20: 1.05 | G20: mL | H20: =Inputs!$B$20 -> 0.1 | I20: =VLOOKUP(E20,Inputs!$D$5:$E$23,2,FALSE()) -> 8 | J20: =F20*I20*(1+H20) -> 9.24 | K20: =IF(ISNUMBER(MATCH(G20,{"tube","each","plate","vial","kit","bottle","aliquot","strainer","cap","lane-rxn","tip","strip","lane","channel","library","sample"},0)),ROUNDUP(J20,0),ROUND(J20,2)) -> 9.24 | L20: =IFERROR(IF(OR(D20="",P20="",Q20="",Q20=0),"",IF(VLOOKUP(R20,Unit_Conversions!$A$5:$C$28,3,FALSE())=VLOOKUP(G20,Unit_Conversions!$A$5:$C$28,3,FALSE()),P20*VLOOKUP(G20,Unit_Conversions!$A$5:$C$28,2,FALSE())/(Q20*VLOOKUP(R20,Unit_Conversions!$A$5:$C$28,2,FALSE())),"")),"") -> 0.218 | M20: =IFERROR(F20*L20,"") -> 0.2289 | N20: =IFERROR(J20*L20,"") -> 2.01432 | O20: SUPPLY | P20: =IFERROR(IF(LEFT(D20,1)="K",VLOOKUP(D20,Kit_Catalog!$A:$K,8,FALSE()),VLOOKUP(D20,Additional_Supply_Catalog!$A:$K,7,FALSE())),"") -> 109 | Q20: =IFERROR(IF(LEFT(D20,1)="K",VLOOKUP(D20,Kit_Catalog!$A:$K,7,FALSE()),VLOOKUP(D20,Additional_Supply_Catalog!$A:$K,8,FALSE())),"") -> 500 | R20: =IFERROR(IF(LEFT(D20,1)="K","rxn",VLOOKUP(D20,Additional_Supply_Catalog!$A:$K,9,FALSE())),"") -> mL
A21: Post-GEM: 5'-GEX | B21: Item | C21: SPRISelect | D21: R005 | E21: per 5'-GEX library | F21: 0.2 | G21: mL | H21: =Inputs!$B$20 -> 0.1 | I21: =VLOOKUP(E21,Inputs!$D$5:$E$23,2,FALSE()) -> 8 | J21: =F21*I21*(1+H21) -> 1.76 | K21: =IF(ISNUMBER(MATCH(G21,{"tube","each","plate","vial","kit","bottle","aliquot","strainer","cap","lane-rxn","tip","strip","lane","channel","library","sample"},0)),ROUNDUP(J21,0),ROUND(J21,2)) -> 1.76 | L21: =IFERROR(IF(OR(D21="",P21="",Q21="",Q21=0),"",IF(VLOOKUP(R21,Unit_Conversions!$A$5:$C$28,3,FALSE())=VLOOKUP(G21,Unit_Conversions!$A$5:$C$28,3,FALSE()),P21*VLOOKUP(G21,Unit_Conversions!$A$5:$C$28,2,FALSE())/(Q21*VLOOKUP(R21,Unit_Conversions!$A$5:$C$28,2,FALSE())),"")),"") -> 27.265 | M21: =IFERROR(F21*L21,"") -> 5.453 | N21: =IFERROR(J21*L21,"") -> 47.9864 | O21: SUPPLY | P21: =IFERROR(IF(LEFT(D21,1)="K",VLOOKUP(D21,Kit_Catalog!$A:$K,8,FALSE()),VLOOKUP(D21,Additional_Supply_Catalog!$A:$K,7,FALSE())),"") -> 1635.9 | Q21: =IFERROR(IF(LEFT(D21,1)="K",VLOOKUP(D21,Kit_Catalog!$A:$K,7,FALSE()),VLOOKUP(D21,Additional_Supply_Catalog!$A:$K,8,FALSE())),"") -> 60 | R21: =IFERROR(IF(LEFT(D21,1)="K","rxn",VLOOKUP(D21,Additional_Supply_Catalog!$A:$K,9,FALSE())),"") -> mL
A22: Post-GEM: 5'-GEX | B22: Item | C22: Tapestation HS D1000 kit | D22: R007 | E22: per 5'-GEX library | F22: 1 | G22: library | H22: =Inputs!$B$20 -> 0.1 | I22: =VLOOKUP(E22,Inputs!$D$5:$E$23,2,FALSE()) -> 8 | J22: =F22*I22*(1+H22) -> 8.8 | K22: =IF(ISNUMBER(MATCH(G22,{"tube","each","plate","vial","kit","bottle","aliquot","strainer","cap","lane-rxn","tip","strip","lane","channel","library","sample"},0)),ROUNDUP(J22,0),ROUND(J22,2)) -> 9 | L22: =IFERROR(IF(OR(D22="",P22="",Q22="",Q22=0),"",IF(VLOOKUP(R22,Unit_Conversions!$A$5:$C$28,3,FALSE())=VLOOKUP(G22,Unit_Conversions!$A$5:$C$28,3,FALSE()),P22*VLOOKUP(G22,Unit_Conversions!$A$5:$C$28,2,FALSE())/(Q22*VLOOKUP(R22,Unit_Conversions!$A$5:$C$28,2,FALSE())),"")),"") | M22: =IFERROR(F22*L22,"") | N22: =IFERROR(J22*L22,"") | O22: (manual) [no catalog price] | P22: =IFERROR(IF(LEFT(D22,1)="K",VLOOKUP(D22,Kit_Catalog!$A:$K,8,FALSE()),VLOOKUP(D22,Additional_Supply_Catalog!$A:$K,7,FALSE())),"") -> 606.25 | Q22: =IFERROR(IF(LEFT(D22,1)="K",VLOOKUP(D22,Kit_Catalog!$A:$K,7,FALSE()),VLOOKUP(D22,Additional_Supply_Catalog!$A:$K,8,FALSE())),"") -> 1 | R22: =IFERROR(IF(LEFT(D22,1)="K","rxn",VLOOKUP(D22,Additional_Supply_Catalog!$A:$K,9,FALSE())),"") -> kit
A23: Post-GEM: 5'-GEX | B23: Item | C23: Qubit Assay Reagent | D23: R006 | E23: per 5'-GEX library | F23: 1 | G23: library | H23: =Inputs!$B$20 -> 0.1 | I23: =VLOOKUP(E23,Inputs!$D$5:$E$23,2,FALSE()) -> 8 | J23: =F23*I23*(1+H23) -> 8.8 | K23: =IF(ISNUMBER(MATCH(G23,{"tube","each","plate","vial","kit","bottle","aliquot","strainer","cap","lane-rxn","tip","strip","lane","channel","library","sample"},0)),ROUNDUP(J23,0),ROUND(J23,2)) -> 9 | L23: =IFERROR(IF(OR(D23="",P23="",Q23="",Q23=0),"",IF(VLOOKUP(R23,Unit_Conversions!$A$5:$C$28,3,FALSE())=VLOOKUP(G23,Unit_Conversions!$A$5:$C$28,3,FALSE()),P23*VLOOKUP(G23,Unit_Conversions!$A$5:$C$28,2,FALSE())/(Q23*VLOOKUP(R23,Unit_Conversions!$A$5:$C$28,2,FALSE())),"")),"") -> 0.8533 | M23: =IFERROR(F23*L23,"") -> 0.8533 | N23: =IFERROR(J23*L23,"") -> 7.50904 | O23: SUPPLY | P23: =IFERROR(IF(LEFT(D23,1)="K",VLOOKUP(D23,Kit_Catalog!$A:$K,8,FALSE()),VLOOKUP(D23,Additional_Supply_Catalog!$A:$K,7,FALSE())),"") -> 426.65 | Q23: =IFERROR(IF(LEFT(D23,1)="K",VLOOKUP(D23,Kit_Catalog!$A:$K,7,FALSE()),VLOOKUP(D23,Additional_Supply_Catalog!$A:$K,8,FALSE())),"") -> 500 | R23: =IFERROR(IF(LEFT(D23,1)="K","rxn",VLOOKUP(D23,Additional_Supply_Catalog!$A:$K,9,FALSE())),"") -> sample
A24: Post-GEM: 5'-GEX | B24: Item | C24: Qubit Assay Tubes | D24: S012 | E24: per 5'-GEX library | F24: 1 | G24: tube | H24: =Inputs!$B$20 -> 0.1 | I24: =VLOOKUP(E24,Inputs!$D$5:$E$23,2,FALSE()) -> 8 | J24: =F24*I24*(1+H24) -> 8.8 | K24: =IF(ISNUMBER(MATCH(G24,{"tube","each","plate","vial","kit","bottle","aliquot","strainer","cap","lane-rxn","tip","strip","lane","channel","library","sample"},0)),ROUNDUP(J24,0),ROUND(J24,2)) -> 9 | L24: =IFERROR(IF(OR(D24="",P24="",Q24="",Q24=0),"",IF(VLOOKUP(R24,Unit_Conversions!$A$5:$C$28,3,FALSE())=VLOOKUP(G24,Unit_Conversions!$A$5:$C$28,3,FALSE()),P24*VLOOKUP(G24,Unit_Conversions!$A$5:$C$28,2,FALSE())/(Q24*VLOOKUP(R24,Unit_Conversions!$A$5:$C$28,2,FALSE())),"")),"") -> 0.27 | M24: =IFERROR(F24*L24,"") -> 0.27 | N24: =IFERROR(J24*L24,"") -> 2.376 | O24: (manual) [no catalog price] | P24: =IFERROR(IF(LEFT(D24,1)="K",VLOOKUP(D24,Kit_Catalog!$A:$K,8,FALSE()),VLOOKUP(D24,Additional_Supply_Catalog!$A:$K,7,FALSE())),"") -> 135 | Q24: =IFERROR(IF(LEFT(D24,1)="K",VLOOKUP(D24,Kit_Catalog!$A:$K,7,FALSE()),VLOOKUP(D24,Additional_Supply_Catalog!$A:$K,8,FALSE())),"") -> 500 | R24: =IFERROR(IF(LEFT(D24,1)="K","rxn",VLOOKUP(D24,Additional_Supply_Catalog!$A:$K,9,FALSE())),"") -> tube
A25: Post-GEM: 5'-GEX | B25: Item | C25: PCR strip tubes | D25: S008 | E25: per 5'-GEX library | F25: 0.125 | G25: strip | H25: =Inputs!$B$20 -> 0.1 | I25: =VLOOKUP(E25,Inputs!$D$5:$E$23,2,FALSE()) -> 8 | J25: =F25*I25*(1+H25) -> 1.1 | K25: =IF(ISNUMBER(MATCH(G25,{"tube","each","plate","vial","kit","bottle","aliquot","strainer","cap","lane-rxn","tip","strip","lane","channel","library","sample"},0)),ROUNDUP(J25,0),ROUND(J25,2)) -> 2 | L25: =IFERROR(IF(OR(D25="",P25="",Q25="",Q25=0),"",IF(VLOOKUP(R25,Unit_Conversions!$A$5:$C$28,3,FALSE())=VLOOKUP(G25,Unit_Conversions!$A$5:$C$28,3,FALSE()),P25*VLOOKUP(G25,Unit_Conversions!$A$5:$C$28,2,FALSE())/(Q25*VLOOKUP(R25,Unit_Conversions!$A$5:$C$28,2,FALSE())),"")),"") -> 0.7804 | M25: =IFERROR(F25*L25,"") -> 0.09755 | N25: =IFERROR(J25*L25,"") -> 0.85844 | O25: (manual) [no catalog price] 1 PCR tube per reaction; 8 tubes per strip. | P25: =IFERROR(IF(LEFT(D25,1)="K",VLOOKUP(D25,Kit_Catalog!$A:$K,8,FALSE()),VLOOKUP(D25,Additional_Supply_Catalog!$A:$K,7,FALSE())),"") -> 97.55 | Q25: =IFERROR(IF(LEFT(D25,1)="K",VLOOKUP(D25,Kit_Catalog!$A:$K,7,FALSE()),VLOOKUP(D25,Additional_Supply_Catalog!$A:$K,8,FALSE())),"") -> 125 | R25: =IFERROR(IF(LEFT(D25,1)="K","rxn",VLOOKUP(D25,Additional_Supply_Catalog!$A:$K,9,FALSE())),"") -> strip
... A43: Post-GEM: 5'-VDJ | B43: Item | C43: Eppendorf Tubes | D43: S004 | E43: per 5'-VDJ library | F43: 1 | G43: tube | H43: =Inputs!$B$20 -> 0.1 | I43: =VLOOKUP(E43,Inputs!$D$5:$E$23,2,FALSE()) -> 8 | J43: =F43*I43*(1+H43) -> 8.8 | K43: =IF(ISNUMBER(MATCH(G43,{"tube","each","plate","vial","kit","bottle","aliquot","strainer","cap","lane-rxn","tip","strip","lane","channel","library","sample"},0)),ROUNDUP(J43,0),ROUND(J43,2)) -> 9 | L43: =IFERROR(IF(OR(D43="",P43="",Q43="",Q43=0),"",IF(VLOOKUP(R43,Unit_Conversions!$A$5:$C$28,3,FALSE())=VLOOKUP(G43,Unit_Conversions!$A$5:$C$28,3,FALSE()),P43*VLOOKUP(G43,Unit_Conversions!$A$5:$C$28,2,FALSE())/(Q43*VLOOKUP(R43,Unit_Conversions!$A$5:$C$28,2,FALSE())),"")),"") -> 0.17956 | M43: =IFERROR(F43*L43,"") -> 0.17956 | N43: =IFERROR(J43*L43,"") -> 1.580128 | O43: (manual) [no catalog price] | P43: =IFERROR(IF(LEFT(D43,1)="K",VLOOKUP(D43,Kit_Catalog!$A:$K,8,FALSE()),VLOOKUP(D43,Additional_Supply_Catalog!$A:$K,7,FALSE())),"") -> 44.89 | Q43: =IFERROR(IF(LEFT(D43,1)="K",VLOOKUP(D43,Kit_Catalog!$A:$K,7,FALSE()),VLOOKUP(D43,Additional_Supply_Catalog!$A:$K,8,FALSE())),"") -> 250 | R43: =IFERROR(IF(LEFT(D43,1)="K","rxn",VLOOKUP(D43,Additional_Supply_Catalog!$A:$K,9,FALSE())),"") -> tube
A44: Post-GEM: 5'-VDJ | B44: Item | C44: TapeStation HS D5000 kit (cDNA/amplicon QC) | E44: per 5'-VDJ library | F44: 1 | G44: sample | H44: =Inputs!$B$20 -> 0.1 | I44: =VLOOKUP(E44,Inputs!$D$5:$E$23,2,FALSE()) -> 8 | J44: =F44*I44*(1+H44) -> 8.8 | K44: =IF(ISNUMBER(MATCH(G44,{"tube","each","plate","vial","kit","bottle","aliquot","strainer","cap","lane-rxn","tip","strip","lane","channel","library","sample"},0)),ROUNDUP(J44,0),ROUND(J44,2)) -> 9 | L44: =IFERROR(IF(OR(D44="",P44="",Q44="",Q44=0),"",IF(VLOOKUP(R44,Unit_Conversions!$A$5:$C$28,3,FALSE())=VLOOKUP(G44,Unit_Conversions!$A$5:$C$28,3,FALSE()),P44*VLOOKUP(G44,Unit_Conversions!$A$5:$C$28,2,FALSE())/(Q44*VLOOKUP(R44,Unit_Conversions!$A$5:$C$28,2,FALSE())),"")),"") | M44: =IFERROR(F44*L44,"") | N44: =IFERROR(J44*L44,"") | O44: (manual) [no catalog price] | P44: =IFERROR(IF(LEFT(D44,1)="K",VLOOKUP(D44,Kit_Catalog!$A:$K,8,FALSE()),VLOOKUP(D44,Additional_Supply_Catalog!$A:$K,7,FALSE())),"") | Q44: =IFERROR(IF(LEFT(D44,1)="K",VLOOKUP(D44,Kit_Catalog!$A:$K,7,FALSE()),VLOOKUP(D44,Additional_Supply_Catalog!$A:$K,8,FALSE())),"") | R44: =IFERROR(IF(LEFT(D44,1)="K","rxn",VLOOKUP(D44,Additional_Supply_Catalog!$A:$K,9,FALSE())),"")
A45: Post-GEM: 5'-VDJ | B45: Item | C45: KAPA Library Quant (qPCR) | D45: R009 | E45: per 5'-VDJ library | F45: 1 | G45: library | H45: =Inputs!$B$20 -> 0.1 | I45: =VLOOKUP(E45,Inputs!$D$5:$E$23,2,FALSE()) -> 8 | J45: =F45*I45*(1+H45) -> 8.8 | K45: =IF(ISNUMBER(MATCH(G45,{"tube","each","plate","vial","kit","bottle","aliquot","strainer","cap","lane-rxn","tip","strip","lane","channel","library","sample"},0)),ROUNDUP(J45,0),ROUND(J45,2)) -> 9 | L45: =IFERROR(IF(OR(D45="",P45="",Q45="",Q45=0),"",IF(VLOOKUP(R45,Unit_Conversions!$A$5:$C$28,3,FALSE())=VLOOKUP(G45,Unit_Conversions!$A$5:$C$28,3,FALSE()),P45*VLOOKUP(G45,Unit_Conversions!$A$5:$C$28,2,FALSE())/(Q45*VLOOKUP(R45,Unit_Conversions!$A$5:$C$28,2,FALSE())),"")),"") | M45: =IFERROR(F45*L45,"") | N45: =IFERROR(J45*L45,"") | O45: SUPPLY [no catalog price] | P45: =IFERROR(IF(LEFT(D45,1)="K",VLOOKUP(D45,Kit_Catalog!$A:$K,8,FALSE()),VLOOKUP(D45,Additional_Supply_Catalog!$A:$K,7,FALSE())),"") -> 0 | Q45: =IFERROR(IF(LEFT(D45,1)="K",VLOOKUP(D45,Kit_Catalog!$A:$K,7,FALSE()),VLOOKUP(D45,Additional_Supply_Catalog!$A:$K,8,FALSE())),"") -> 0 | R45: =IFERROR(IF(LEFT(D45,1)="K","rxn",VLOOKUP(D45,Additional_Supply_Catalog!$A:$K,9,FALSE())),"") -> 0
A46: Post-GEM: 5'-ADT | B46: Item | C46: Feature Barcode Kit v3 | D46: K016 | E46: per 5'-ADT library | F46: 1 | G46: channels | H46: =Inputs!$B$20 -> 0.1 | I46: =VLOOKUP(E46,Inputs!$D$5:$E$23,2,FALSE()) -> 8 | J46: =F46*I46*(1+H46) -> 8.8 | K46: =IF(ISNUMBER(MATCH(G46,{"tube","each","plate","vial","kit","bottle","aliquot","strainer","cap","lane-rxn","tip","strip","lane","channel","library","sample"},0)),ROUNDUP(J46,0),ROUND(J46,2)) -> 8.8 | L46: =IFERROR(IF(OR(D46="",P46="",Q46="",Q46=0),"",IF(VLOOKUP(R46,Unit_Conversions!$A$5:$C$28,3,FALSE())=VLOOKUP(G46,Unit_Conversions!$A$5:$C$28,3,FALSE()),P46*VLOOKUP(G46,Unit_Conversions!$A$5:$C$28,2,FALSE())/(Q46*VLOOKUP(R46,Unit_Conversions!$A$5:$C$28,2,FALSE())),"")),"") -> 41.875 | M46: =IFERROR(F46*L46,"") -> 41.875 | N46: =IFERROR(J46*L46,"") -> 368.5 | O46: KIT | P46: =IFERROR(IF(LEFT(D46,1)="K",VLOOKUP(D46,Kit_Catalog!$A:$K,8,FALSE()),VLOOKUP(D46,Additional_Supply_Catalog!$A:$K,7,FALSE())),"") -> 670 | Q46: =IFERROR(IF(LEFT(D46,1)="K",VLOOKUP(D46,Kit_Catalog!$A:$K,7,FALSE()),VLOOKUP(D46,Additional_Supply_Catalog!$A:$K,8,FALSE())),"") -> 16 | R46: =IFERROR(IF(LEFT(D46,1)="K","rxn",VLOOKUP(D46,Additional_Supply_Catalog!$A:$K,9,FALSE())),"") -> rxn
A47: Post-GEM: 5'-ADT | B47: Item | C47: Dual Index Kit TN, Set A | D47: K017 | E47: per 5'-ADT library | F47: 1 | G47: channels | H47: =Inputs!$B$20 -> 0.1 | I47: =VLOOKUP(E47,Inputs!$D$5:$E$23,2,FALSE()) -> 8 | J47: =F47*I47*(1+H47) -> 8.8 | K47: =IF(ISNUMBER(MATCH(G47,{"tube","each","plate","vial","kit","bottle","aliquot","strainer","cap","lane-rxn","tip","strip","lane","channel","library","sample"},0)),ROUNDUP(J47,0),ROUND(J47,2)) -> 8.8 | L47: =IFERROR(IF(OR(D47="",P47="",Q47="",Q47=0),"",IF(VLOOKUP(R47,Unit_Conversions!$A$5:$C$28,3,FALSE())=VLOOKUP(G47,Unit_Conversions!$A$5:$C$28,3,FALSE()),P47*VLOOKUP(G47,Unit_Conversions!$A$5:$C$28,2,FALSE())/(Q47*VLOOKUP(R47,Unit_Conversions!$A$5:$C$28,2,FALSE())),"")),"") -> 10 | M47: =IFERROR(F47*L47,"") -> 10 | N47: =IFERROR(J47*L47,"") -> 88 | O47: KIT | P47: =IFERROR(IF(LEFT(D47,1)="K",VLOOKUP(D47,Kit_Catalog!$A:$K,8,FALSE()),VLOOKUP(D47,Additional_Supply_Catalog!$A:$K,7,FALSE())),"") -> 960 | Q47: =IFERROR(IF(LEFT(D47,1)="K",VLOOKUP(D47,Kit_Catalog!$A:$K,7,FALSE()),VLOOKUP(D47,Additional_Supply_Catalog!$A:$K,8,FALSE())),"") -> 96 | R47: =IFERROR(IF(LEFT(D47,1)="K","rxn",VLOOKUP(D47,Additional_Supply_Catalog!$A:$K,9,FALSE())),"") -> rxn
A48: Post-GEM: 5'-ADT | B48: Item | C48: Buffer EB | D48: R004 | E48: per 5'-ADT library | F48: 0.0605 | G48: mL | H48: =Inputs!$B$20 -> 0.1 | I48: =VLOOKUP(E48,Inputs!$D$5:$E$23,2,FALSE()) -> 8 | J48: =F48*I48*(1+H48) -> 0.5324 | K48: =IF(ISNUMBER(MATCH(G48,{"tube","each","plate","vial","kit","bottle","aliquot","strainer","cap","lane-rxn","tip","strip","lane","channel","library","sample"},0)),ROUNDUP(J48,0),ROUND(J48,2)) -> 0.53 | L48: =IFERROR(IF(OR(D48="",P48="",Q48="",Q48=0),"",IF(VLOOKUP(R48,Unit_Conversions!$A$5:$C$28,3,FALSE())=VLOOKUP(G48,Unit_Conversions!$A$5:$C$28,3,FALSE()),P48*VLOOKUP(G48,Unit_Conversions!$A$5:$C$28,2,FALSE())/(Q48*VLOOKUP(R48,Unit_Conversions!$A$5:$C$28,2,FALSE())),"")),"") -> 0.1996 | M48: =IFERROR(F48*L48,"") -> 0.0120758 | N48: =IFERROR(J48*L48,"") -> 0.10626704 | O48: SUPPLY | P48: =IFERROR(IF(LEFT(D48,1)="K",VLOOKUP(D48,Kit_Catalog!$A:$K,8,FALSE()),VLOOKUP(D48,Additional_Supply_Catalog!$A:$K,7,FALSE())),"") -> 49.9 | Q48: =IFERROR(IF(LEFT(D48,1)="K",VLOOKUP(D48,Kit_Catalog!$A:$K,7,FALSE()),VLOOKUP(D48,Additional_Supply_Catalog!$A:$K,8,FALSE())),"") -> 250 | R48: =IFERROR(IF(LEFT(D48,1)="K","rxn",VLOOKUP(D48,Additional_Supply_Catalog!$A:$K,9,FALSE())),"") -> mL
A49: Post-GEM: 5'-ADT | B49: Item | C49: Ethanol | D49: R003 | E49: per 5'-ADT library | F49: 0.5 | G49: mL | H49: =Inputs!$B$20 -> 0.1 | I49: =VLOOKUP(E49,Inputs!$D$5:$E$23,2,FALSE()) -> 8 | J49: =F49*I49*(1+H49) -> 4.4 | K49: =IF(ISNUMBER(MATCH(G49,{"tube","each","plate","vial","kit","bottle","aliquot","strainer","cap","lane-rxn","tip","strip","lane","channel","library","sample"},0)),ROUNDUP(J49,0),ROUND(J49,2)) -> 4.4 | L49: =IFERROR(IF(OR(D49="",P49="",Q49="",Q49=0),"",IF(VLOOKUP(R49,Unit_Conversions!$A$5:$C$28,3,FALSE())=VLOOKUP(G49,Unit_Conversions!$A$5:$C$28,3,FALSE()),P49*VLOOKUP(G49,Unit_Conversions!$A$5:$C$28,2,FALSE())/(Q49*VLOOKUP(R49,Unit_Conversions!$A$5:$C$28,2,FALSE())),"")),"") -> 0.218 | M49: =IFERROR(F49*L49,"") -> 0.109 | N49: =IFERROR(J49*L49,"") -> 0.9592 | O49: SUPPLY | P49: =IFERROR(IF(LEFT(D49,1)="K",VLOOKUP(D49,Kit_Catalog!$A:$K,8,FALSE()),VLOOKUP(D49,Additional_Supply_Catalog!$A:$K,7,FALSE())),"") -> 109 | Q49: =IFERROR(IF(LEFT(D49,1)="K",VLOOKUP(D49,Kit_Catalog!$A:$K,7,FALSE()),VLOOKUP(D49,Additional_Supply_Catalog!$A:$K,8,FALSE())),"") -> 500 | R49: =IFERROR(IF(LEFT(D49,1)="K","rxn",VLOOKUP(D49,Additional_Supply_Catalog!$A:$K,9,FALSE())),"") -> mL
A50: Post-GEM: 5'-ADT | B50: Item | C50: SPRISelect | D50: R005 | E50: per 5'-ADT library | F50: 0.12 | G50: mL | H50: =Inputs!$B$20 -> 0.1 | I50: =VLOOKUP(E50,Inputs!$D$5:$E$23,2,FALSE()) -> 8 | J50: =F50*I50*(1+H50) -> 1.056 | K50: =IF(ISNUMBER(MATCH(G50,{"tube","each","plate","vial","kit","bottle","aliquot","strainer","cap","lane-rxn","tip","strip","lane","channel","library","sample"},0)),ROUNDUP(J50,0),ROUND(J50,2)) -> 1.06 | L50: =IFERROR(IF(OR(D50="",P50="",Q50="",Q50=0),"",IF(VLOOKUP(R50,Unit_Conversions!$A$5:$C$28,3,FALSE())=VLOOKUP(G50,Unit_Conversions!$A$5:$C$28,3,FALSE()),P50*VLOOKUP(G50,Unit_Conversions!$A$5:$C$28,2,FALSE())/(Q50*VLOOKUP(R50,Unit_Conversions!$A$5:$C$28,2,FALSE())),"")),"") -> 27.265 | M50: =IFERROR(F50*L50,"") -> 3.2718 | N50: =IFERROR(J50*L50,"") -> 28.79184 | O50: SUPPLY | P50: =IFERROR(IF(LEFT(D50,1)="K",VLOOKUP(D50,Kit_Catalog!$A:$K,8,FALSE()),VLOOKUP(D50,Additional_Supply_Catalog!$A:$K,7,FALSE())),"") -> 1635.9 | Q50: =IFERROR(IF(LEFT(D50,1)="K",VLOOKUP(D50,Kit_Catalog!$A:$K,7,FALSE()),VLOOKUP(D50,Additional_Supply_Catalog!$A:$K,8,FALSE())),"") -> 60 | R50: =IFERROR(IF(LEFT(D50,1)="K","rxn",VLOOKUP(D50,Additional_Supply_Catalog!$A:$K,9,FALSE())),"") -> mL
A51: Post-GEM: 5'-ADT | B51: Item | C51: Tapestation HS D1000 kit | D51: R007 | E51: per 5'-ADT library | F51: 1 | G51: library | H51: =Inputs!$B$20 -> 0.1 | I51: =VLOOKUP(E51,Inputs!$D$5:$E$23,2,FALSE()) -> 8 | J51: =F51*I51*(1+H51) -> 8.8 | K51: =IF(ISNUMBER(MATCH(G51,{"tube","each","plate","vial","kit","bottle","aliquot","strainer","cap","lane-rxn","tip","strip","lane","channel","library","sample"},0)),ROUNDUP(J51,0),ROUND(J51,2)) -> 9 | L51: =IFERROR(IF(OR(D51="",P51="",Q51="",Q51=0),"",IF(VLOOKUP(R51,Unit_Conversions!$A$5:$C$28,3,FALSE())=VLOOKUP(G51,Unit_Conversions!$A$5:$C$28,3,FALSE()),P51*VLOOKUP(G51,Unit_Conversions!$A$5:$C$28,2,FALSE())/(Q51*VLOOKUP(R51,Unit_Conversions!$A$5:$C$28,2,FALSE())),"")),"") | M51: =IFERROR(F51*L51,"") | N51: =IFERROR(J51*L51,"") | O51: (manual) [no catalog price] | P51: =IFERROR(IF(LEFT(D51,1)="K",VLOOKUP(D51,Kit_Catalog!$A:$K,8,FALSE()),VLOOKUP(D51,Additional_Supply_Catalog!$A:$K,7,FALSE())),"") -> 606.25 | Q51: =IFERROR(IF(LEFT(D51,1)="K",VLOOKUP(D51,Kit_Catalog!$A:$K,7,FALSE()),VLOOKUP(D51,Additional_Supply_Catalog!$A:$K,8,FALSE())),"") -> 1 | R51: =IFERROR(IF(LEFT(D51,1)="K","rxn",VLOOKUP(D51,Additional_Supply_Catalog!$A:$K,9,FALSE())),"") -> kit
A52: Post-GEM: 5'-ADT | B52: Item | C52: Qubit Assay Reagent | D52: R006 | E52: per 5'-ADT library | F52: 1 | G52: library | H52: =Inputs!$B$20 -> 0.1 | I52: =VLOOKUP(E52,Inputs!$D$5:$E$23,2,FALSE()) -> 8 | J52: =F52*I52*(1+H52) -> 8.8 | K52: =IF(ISNUMBER(MATCH(G52,{"tube","each","plate","vial","kit","bottle","aliquot","strainer","cap","lane-rxn","tip","strip","lane","channel","library","sample"},0)),ROUNDUP(J52,0),ROUND(J52,2)) -> 9 | L52: =IFERROR(IF(OR(D52="",P52="",Q52="",Q52=0),"",IF(VLOOKUP(R52,Unit_Conversions!$A$5:$C$28,3,FALSE())=VLOOKUP(G52,Unit_Conversions!$A$5:$C$28,3,FALSE()),P52*VLOOKUP(G52,Unit_Conversions!$A$5:$C$28,2,FALSE())/(Q52*VLOOKUP(R52,Unit_Conversions!$A$5:$C$28,2,FALSE())),"")),"") -> 0.8533 | M52: =IFERROR(F52*L52,"") -> 0.8533 | N52: =IFERROR(J52*L52,"") -> 7.50904 | O52: SUPPLY | P52: =IFERROR(IF(LEFT(D52,1)="K",VLOOKUP(D52,Kit_Catalog!$A:$K,8,FALSE()),VLOOKUP(D52,Additional_Supply_Catalog!$A:$K,7,FALSE())),"") -> 426.65 | Q52: =IFERROR(IF(LEFT(D52,1)="K",VLOOKUP(D52,Kit_Catalog!$A:$K,7,FALSE()),VLOOKUP(D52,Additional_Supply_Catalog!$A:$K,8,FALSE())),"") -> 500 | R52: =IFERROR(IF(LEFT(D52,1)="K","rxn",VLOOKUP(D52,Additional_Supply_Catalog!$A:$K,9,FALSE())),"") -> sample
A53: Post-GEM: 5'-ADT | B53: Item | C53: Qubit Assay Tubes | D53: S012 | E53: per 5'-ADT library | F53: 1 | G53: tube | H53: =Inputs!$B$20 -> 0.1 | I53: =VLOOKUP(E53,Inputs!$D$5:$E$23,2,FALSE()) -> 8 | J53: =F53*I53*(1+H53) -> 8.8 | K53: =IF(ISNUMBER(MATCH(G53,{"tube","each","plate","vial","kit","bottle","aliquot","strainer","cap","lane-rxn","tip","strip","lane","channel","library","sample"},0)),ROUNDUP(J53,0),ROUND(J53,2)) -> 9 | L53: =IFERROR(IF(OR(D53="",P53="",Q53="",Q53=0),"",IF(VLOOKUP(R53,Unit_Conversions!$A$5:$C$28,3,FALSE())=VLOOKUP(G53,Unit_Conversions!$A$5:$C$28,3,FALSE()),P53*VLOOKUP(G53,Unit_Conversions!$A$5:$C$28,2,FALSE())/(Q53*VLOOKUP(R53,Unit_Conversions!$A$5:$C$28,2,FALSE())),"")),"") -> 0.27 | M53: =IFERROR(F53*L53,"") -> 0.27 | N53: =IFERROR(J53*L53,"") -> 2.376 | O53: (manual) [no catalog price] | P53: =IFERROR(IF(LEFT(D53,1)="K",VLOOKUP(D53,Kit_Catalog!$A:$K,8,FALSE()),VLOOKUP(D53,Additional_Supply_Catalog!$A:$K,7,FALSE())),"") -> 135 | Q53: =IFERROR(IF(LEFT(D53,1)="K",VLOOKUP(D53,Kit_Catalog!$A:$K,7,FALSE()),VLOOKUP(D53,Additional_Supply_Catalog!$A:$K,8,FALSE())),"") -> 500 | R53: =IFERROR(IF(LEFT(D53,1)="K","rxn",VLOOKUP(D53,Additional_Supply_Catalog!$A:$K,9,FALSE())),"") -> tube
A54: Post-GEM: 5'-ADT | B54: Item | C54: PCR strip tubes | D54: S008 | E54: per 5'-ADT library | F54: 0.125 | G54: strip | H54: =Inputs!$B$20 -> 0.1 | I54: =VLOOKUP(E54,Inputs!$D$5:$E$23,2,FALSE()) -> 8 | J54: =F54*I54*(1+H54) -> 1.1 | K54: =IF(ISNUMBER(MATCH(G54,{"tube","each","plate","vial","kit","bottle","aliquot","strainer","cap","lane-rxn","tip","strip","lane","channel","library","sample"},0)),ROUNDUP(J54,0),ROUND(J54,2)) -> 2 | L54: =IFERROR(IF(OR(D54="",P54="",Q54="",Q54=0),"",IF(VLOOKUP(R54,Unit_Conversions!$A$5:$C$28,3,FALSE())=VLOOKUP(G54,Unit_Conversions!$A$5:$C$28,3,FALSE()),P54*VLOOKUP(G54,Unit_Conversions!$A$5:$C$28,2,FALSE())/(Q54*VLOOKUP(R54,Unit_Conversions!$A$5:$C$28,2,FALSE())),"")),"") -> 0.7804 | M54: =IFERROR(F54*L54,"") -> 0.09755 | N54: =IFERROR(J54*L54,"") -> 0.85844 | O54: (manual) [no catalog price] 1 PCR tube per reaction; 8 tubes per strip. | P54: =IFERROR(IF(LEFT(D54,1)="K",VLOOKUP(D54,Kit_Catalog!$A:$K,8,FALSE()),VLOOKUP(D54,Additional_Supply_Catalog!$A:$K,7,FALSE())),"") -> 97.55 | Q54: =IFERROR(IF(LEFT(D54,1)="K",VLOOKUP(D54,Kit_Catalog!$A:$K,7,FALSE()),VLOOKUP(D54,Additional_Supply_Catalog!$A:$K,8,FALSE())),"") -> 125 | R54: =IFERROR(IF(LEFT(D54,1)="K","rxn",VLOOKUP(D54,Additional_Supply_Catalog!$A:$K,9,FALSE())),"") -> strip
A55: Post-GEM: 5'-ADT | B55: Item | C55: 200uL pipette tips | D55: S002 | E55: per 5'-ADT library | F55: 3 | G55: tip | H55: =Inputs!$B$20 -> 0.1 | I55: =VLOOKUP(E55,Inputs!$D$5:$E$23,2,FALSE()) -> 8 | J55: =F55*I55*(1+H55) -> 26.4 | K55: =IF(ISNUMBER(MATCH(G55,{"tube","each","plate","vial","kit","bottle","aliquot","strainer","cap","lane-rxn","tip","strip","lane","channel","library","sample"},0)),ROUNDUP(J55,0),ROUND(J55,2)) -> 27 | L55: =IFERROR(IF(OR(D55="",P55="",Q55="",Q55=0),"",IF(VLOOKUP(R55,Unit_Conversions!$A$5:$C$28,3,FALSE())=VLOOKUP(G55,Unit_Conversions!$A$5:$C$28,3,FALSE()),P55*VLOOKUP(G55,Unit_Conversions!$A$5:$C$28,2,FALSE())/(Q55*VLOOKUP(R55,Unit_Conversions!$A$5:$C$28,2,FALSE())),"")),"") -> 0.018791667 | M55: =IFERROR(F55*L55,"") -> 0.056375 | N55: =IFERROR(J55*L55,"") -> 0.4961 | O55: (manual) [no catalog price] | P55: =IFERROR(IF(LEFT(D55,1)="K",VLOOKUP(D55,Kit_Catalog!$A:$K,8,FALSE()),VLOOKUP(D55,Additional_Supply_Catalog!$A:$K,7,FALSE())),"") -> 180.4 | Q55: =IFERROR(IF(LEFT(D55,1)="K",VLOOKUP(D55,Kit_Catalog!$A:$K,7,FALSE()),VLOOKUP(D55,Additional_Supply_Catalog!$A:$K,8,FALSE())),"") -> 9600 | R55: =IFERROR(IF(LEFT(D55,1)="K","rxn",VLOOKUP(D55,Additional_Supply_Catalog!$A:$K,9,FALSE())),"") -> tip
A56: Post-GEM: 5'-ADT | B56: Item | C56: 20uL pipette tips | D56: S003 | E56: per 5'-ADT library | F56: 1 | G56: tip | H56: =Inputs!$B$20 -> 0.1 | I56: =VLOOKUP(E56,Inputs!$D$5:$E$23,2,FALSE()) -> 8 | J56: =F56*I56*(1+H56) -> 8.8 | K56: =IF(ISNUMBER(MATCH(G56,{"tube","each","plate","vial","kit","bottle","aliquot","strainer","cap","lane-rxn","tip","strip","lane","channel","library","sample"},0)),ROUNDUP(J56,0),ROUND(J56,2)) -> 9 | L56: =IFERROR(IF(OR(D56="",P56="",Q56="",Q56=0),"",IF(VLOOKUP(R56,Unit_Conversions!$A$5:$C$28,3,FALSE())=VLOOKUP(G56,Unit_Conversions!$A$5:$C$28,3,FALSE()),P56*VLOOKUP(G56,Unit_Conversions!$A$5:$C$28,2,FALSE())/(Q56*VLOOKUP(R56,Unit_Conversions!$A$5:$C$28,2,FALSE())),"")),"") -> 0.018791667 | M56: =IFERROR(F56*L56,"") -> 0.018791667 | N56: =IFERROR(J56*L56,"") -> 0.16536667 | O56: (manual) [no catalog price] | P56: =IFERROR(IF(LEFT(D56,1)="K",VLOOKUP(D56,Kit_Catalog!$A:$K,8,FALSE()),VLOOKUP(D56,Additional_Supply_Catalog!$A:$K,7,FALSE())),"") -> 180.4 | Q56: =IFERROR(IF(LEFT(D56,1)="K",VLOOKUP(D56,Kit_Catalog!$A:$K,7,FALSE()),VLOOKUP(D56,Additional_Supply_Catalog!$A:$K,8,FALSE())),"") -> 9600 | R56: =IFERROR(IF(LEFT(D56,1)="K","rxn",VLOOKUP(D56,Additional_Supply_Catalog!$A:$K,9,FALSE())),"") -> tip
... A84: Post-GEM: ATAC | B84: Item | C84: Eppendorf Tubes | D84: S004 | E84: per ATAC library | F84: 1 | G84: tube | H84: =Inputs!$B$20 -> 0.1 | I84: =VLOOKUP(E84,Inputs!$D$5:$E$23,2,FALSE()) -> 2 | J84: =F84*I84*(1+H84) -> 2.2 | K84: =IF(ISNUMBER(MATCH(G84,{"tube","each","plate","vial","kit","bottle","aliquot","strainer","cap","lane-rxn","tip","strip","lane","channel","library","sample"},0)),ROUNDUP(J84,0),ROUND(J84,2)) -> 3 | L84: =IFERROR(IF(OR(D84="",P84="",Q84="",Q84=0),"",IF(VLOOKUP(R84,Unit_Conversions!$A$5:$C$28,3,FALSE())=VLOOKUP(G84,Unit_Conversions!$A$5:$C$28,3,FALSE()),P84*VLOOKUP(G84,Unit_Conversions!$A$5:$C$28,2,FALSE())/(Q84*VLOOKUP(R84,Unit_Conversions!$A$5:$C$28,2,FALSE())),"")),"") -> 0.17956 | M84: =IFERROR(F84*L84,"") -> 0.17956 | N84: =IFERROR(J84*L84,"") -> 0.395032 | O84: (manual) [no catalog price] | P84: =IFERROR(IF(LEFT(D84,1)="K",VLOOKUP(D84,Kit_Catalog!$A:$K,8,FALSE()),VLOOKUP(D84,Additional_Supply_Catalog!$A:$K,7,FALSE())),"") -> 44.89 | Q84: =IFERROR(IF(LEFT(D84,1)="K",VLOOKUP(D84,Kit_Catalog!$A:$K,7,FALSE()),VLOOKUP(D84,Additional_Supply_Catalog!$A:$K,8,FALSE())),"") -> 250 | R84: =IFERROR(IF(LEFT(D84,1)="K","rxn",VLOOKUP(D84,Additional_Supply_Catalog!$A:$K,9,FALSE())),"") -> tube
A85: Post-GEM: Flex v2 | B85: BUFFER ▸ prepare | C85: Pre-Amplification Mix | E85: (prep total) | G85: mL | J85: =(0.035*Inputs!$B$22)*(1+Inputs!$B$20) -> 0 | O85: Per GEM reaction (CG000834 Step 5.2): Amp Mix C 25 + Pre-Amp Primers B 10 = 35 uL. Components in GEM & Library Kit.
A86: Post-GEM: Flex v2 | B86: BUFFER ▸ prepare | C86: Sample Index PCR Mix | E86: (prep total) | G86: mL | J86: =(0.06*Inputs!$B$23)*(1+Inputs!$B$20) -> 0 | O86: Per library (CG000834 Step 6.1, <=320k cells): Amp Mix C 50 + NF water 10 = 60 uL. + 20 uL Dual Index TS.
A87: Post-GEM: Flex v2 | B87: Item | C87: Dual Index Plate TS, Set A | D87: K039 | E87: per Flex library | F87: 1 | G87: library | H87: =Inputs!$B$20 -> 0.1 | I87: =VLOOKUP(E87,Inputs!$D$5:$E$23,2,FALSE()) -> 0 | J87: =F87*I87*(1+H87) -> 0 | K87: =IF(ISNUMBER(MATCH(G87,{"tube","each","plate","vial","kit","bottle","aliquot","strainer","cap","lane-rxn","tip","strip","lane","channel","library","sample"},0)),ROUNDUP(J87,0),ROUND(J87,2)) -> 0 | L87: =IFERROR(IF(OR(D87="",P87="",Q87="",Q87=0),"",IF(VLOOKUP(R87,Unit_Conversions!$A$5:$C$28,3,FALSE())=VLOOKUP(G87,Unit_Conversions!$A$5:$C$28,3,FALSE()),P87*VLOOKUP(G87,Unit_Conversions!$A$5:$C$28,2,FALSE())/(Q87*VLOOKUP(R87,Unit_Conversions!$A$5:$C$28,2,FALSE())),"")),"") -> 10 | M87: =IFERROR(F87*L87,"") -> 10 | N87: =IFERROR(J87*L87,"") -> 0 | O87: KIT (PN-1000251 / plate PN-3000511). One unique index well per library. 96 rxn/kit. | P87: =IFERROR(IF(LEFT(D87,1)="K",VLOOKUP(D87,Kit_Catalog!$A:$K,8,FALSE()),VLOOKUP(D87,Additional_Supply_Catalog!$A:$K,7,FALSE())),"") -> 960 | Q87: =IFERROR(IF(LEFT(D87,1)="K",VLOOKUP(D87,Kit_Catalog!$A:$K,7,FALSE()),VLOOKUP(D87,Additional_Supply_Catalog!$A:$K,8,FALSE())),"") -> 96 | R87: =IFERROR(IF(LEFT(D87,1)="K","rxn",VLOOKUP(D87,Additional_Supply_Catalog!$A:$K,9,FALSE())),"") -> rxn
A88: Post-GEM: Flex v2 | B88: Item | C88: SPRIselect Reagent Kit | D88: R005 | E88: per Flex library | F88: 0.16 | G88: mL | H88: =Inputs!$B$20 -> 0.1 | I88: =VLOOKUP(E88,Inputs!$D$5:$E$23,2,FALSE()) -> 0 | J88: =F88*I88*(1+H88) -> 0 | K88: =IF(ISNUMBER(MATCH(G88,{"tube","each","plate","vial","kit","bottle","aliquot","strainer","cap","lane-rxn","tip","strip","lane","channel","library","sample"},0)),ROUNDUP(J88,0),ROUND(J88,2)) -> 0 | L88: =IFERROR(IF(OR(D88="",P88="",Q88="",Q88=0),"",IF(VLOOKUP(R88,Unit_Conversions!$A$5:$C$28,3,FALSE())=VLOOKUP(G88,Unit_Conversions!$A$5:$C$28,3,FALSE()),P88*VLOOKUP(G88,Unit_Conversions!$A$5:$C$28,2,FALSE())/(Q88*VLOOKUP(R88,Unit_Conversions!$A$5:$C$28,2,FALSE())),"")),"") -> 27.265 | M88: =IFERROR(F88*L88,"") -> 4.3624 | N88: =IFERROR(J88*L88,"") -> 0 | O88: Pre-amp cleanup + post-SI-PCR size selection (SI-PCR 1.0X = 100 uL/library). | P88: =IFERROR(IF(LEFT(D88,1)="K",VLOOKUP(D88,Kit_Catalog!$A:$K,8,FALSE()),VLOOKUP(D88,Additional_Supply_Catalog!$A:$K,7,FALSE())),"") -> 1635.9 | Q88: =IFERROR(IF(LEFT(D88,1)="K",VLOOKUP(D88,Kit_Catalog!$A:$K,7,FALSE()),VLOOKUP(D88,Additional_Supply_Catalog!$A:$K,8,FALSE())),"") -> 60 | R88: =IFERROR(IF(LEFT(D88,1)="K","rxn",VLOOKUP(D88,Additional_Supply_Catalog!$A:$K,9,FALSE())),"") -> mL
A89: Post-GEM: Flex v2 | B89: Item | C89: Buffer EB | D89: R004 | E89: per Flex library | F89: 0.081 | G89: mL | H89: =Inputs!$B$20 -> 0.1 | I89: =VLOOKUP(E89,Inputs!$D$5:$E$23,2,FALSE()) -> 0 | J89: =F89*I89*(1+H89) -> 0 | K89: =IF(ISNUMBER(MATCH(G89,{"tube","each","plate","vial","kit","bottle","aliquot","strainer","cap","lane-rxn","tip","strip","lane","channel","library","sample"},0)),ROUNDUP(J89,0),ROUND(J89,2)) -> 0 | L89: =IFERROR(IF(OR(D89="",P89="",Q89="",Q89=0),"",IF(VLOOKUP(R89,Unit_Conversions!$A$5:$C$28,3,FALSE())=VLOOKUP(G89,Unit_Conversions!$A$5:$C$28,3,FALSE()),P89*VLOOKUP(G89,Unit_Conversions!$A$5:$C$28,2,FALSE())/(Q89*VLOOKUP(R89,Unit_Conversions!$A$5:$C$28,2,FALSE())),"")),"") -> 0.1996 | M89: =IFERROR(F89*L89,"") -> 0.0161676 | N89: =IFERROR(J89*L89,"") -> 0 | O89: Elution (pre-amp cleanup + SI-PCR 41 uL). | P89: =IFERROR(IF(LEFT(D89,1)="K",VLOOKUP(D89,Kit_Catalog!$A:$K,8,FALSE()),VLOOKUP(D89,Additional_Supply_Catalog!$A:$K,7,FALSE())),"") -> 49.9 | Q89: =IFERROR(IF(LEFT(D89,1)="K",VLOOKUP(D89,Kit_Catalog!$A:$K,7,FALSE()),VLOOKUP(D89,Additional_Supply_Catalog!$A:$K,8,FALSE())),"") -> 250 | R89: =IFERROR(IF(LEFT(D89,1)="K","rxn",VLOOKUP(D89,Additional_Supply_Catalog!$A:$K,9,FALSE())),"") -> mL
A90: Post-GEM: Flex v2 | B90: Item | C90: Ethanol, 200 proof anhydrous | D90: R003 | E90: per Flex library | F90: 0.8 | G90: mL | H90: =Inputs!$B$20 -> 0.1 | I90: =VLOOKUP(E90,Inputs!$D$5:$E$23,2,FALSE()) -> 0 | J90: =F90*I90*(1+H90) -> 0 | K90: =IF(ISNUMBER(MATCH(G90,{"tube","each","plate","vial","kit","bottle","aliquot","strainer","cap","lane-rxn","tip","strip","lane","channel","library","sample"},0)),ROUNDUP(J90,0),ROUND(J90,2)) -> 0 | L90: =IFERROR(IF(OR(D90="",P90="",Q90="",Q90=0),"",IF(VLOOKUP(R90,Unit_Conversions!$A$5:$C$28,3,FALSE())=VLOOKUP(G90,Unit_Conversions!$A$5:$C$28,3,FALSE()),P90*VLOOKUP(G90,Unit_Conversions!$A$5:$C$28,2,FALSE())/(Q90*VLOOKUP(R90,Unit_Conversions!$A$5:$C$28,2,FALSE())),"")),"") -> 0.218 | M90: =IFERROR(F90*L90,"") -> 0.1744 | N90: =IFERROR(J90*L90,"") -> 0 | O90: 80% ethanol washes (pre-amp + SI-PCR, 2x200 uL each). | P90: =IFERROR(IF(LEFT(D90,1)="K",VLOOKUP(D90,Kit_Catalog!$A:$K,8,FALSE()),VLOOKUP(D90,Additional_Supply_Catalog!$A:$K,7,FALSE())),"") -> 109 | Q90: =IFERROR(IF(LEFT(D90,1)="K",VLOOKUP(D90,Kit_Catalog!$A:$K,7,FALSE()),VLOOKUP(D90,Additional_Supply_Catalog!$A:$K,8,FALSE())),"") -> 500 | R90: =IFERROR(IF(LEFT(D90,1)="K","rxn",VLOOKUP(D90,Additional_Supply_Catalog!$A:$K,9,FALSE())),"") -> mL
A91: Post-GEM: Flex v2 | B91: Item | C91: Qubit dsDNA HS Assay kit | D91: R006 | E91: per Flex library | F91: 1 | G91: sample | H91: =Inputs!$B$20 -> 0.1 | I91: =VLOOKUP(E91,Inputs!$D$5:$E$23,2,FALSE()) -> 0 | J91: =F91*I91*(1+H91) -> 0 | K91: =IF(ISNUMBER(MATCH(G91,{"tube","each","plate","vial","kit","bottle","aliquot","strainer","cap","lane-rxn","tip","strip","lane","channel","library","sample"},0)),ROUNDUP(J91,0),ROUND(J91,2)) -> 0 | L91: =IFERROR(IF(OR(D91="",P91="",Q91="",Q91=0),"",IF(VLOOKUP(R91,Unit_Conversions!$A$5:$C$28,3,FALSE())=VLOOKUP(G91,Unit_Conversions!$A$5:$C$28,3,FALSE()),P91*VLOOKUP(G91,Unit_Conversions!$A$5:$C$28,2,FALSE())/(Q91*VLOOKUP(R91,Unit_Conversions!$A$5:$C$28,2,FALSE())),"")),"") -> 0.8533 | M91: =IFERROR(F91*L91,"") -> 0.8533 | N91: =IFERROR(J91*L91,"") -> 0 | O91: Post-library QC. | P91: =IFERROR(IF(LEFT(D91,1)="K",VLOOKUP(D91,Kit_Catalog!$A:$K,8,FALSE()),VLOOKUP(D91,Additional_Supply_Catalog!$A:$K,7,FALSE())),"") -> 426.65 | Q91: =IFERROR(IF(LEFT(D91,1)="K",VLOOKUP(D91,Kit_Catalog!$A:$K,7,FALSE()),VLOOKUP(D91,Additional_Supply_Catalog!$A:$K,8,FALSE())),"") -> 500 | R91: =IFERROR(IF(LEFT(D91,1)="K","rxn",VLOOKUP(D91,Additional_Supply_Catalog!$A:$K,9,FALSE())),"") -> sample
A92: Post-GEM: Flex v2 | B92: Item | C92: Qubit Assay Tubes | D92: S012 | E92: per Flex library | F92: 1 | G92: tube | H92: =Inputs!$B$20 -> 0.1 | I92: =VLOOKUP(E92,Inputs!$D$5:$E$23,2,FALSE()) -> 0 | J92: =F92*I92*(1+H92) -> 0 | K92: =IF(ISNUMBER(MATCH(G92,{"tube","each","plate","vial","kit","bottle","aliquot","strainer","cap","lane-rxn","tip","strip","lane","channel","library","sample"},0)),ROUNDUP(J92,0),ROUND(J92,2)) -> 0 | L92: =IFERROR(IF(OR(D92="",P92="",Q92="",Q92=0),"",IF(VLOOKUP(R92,Unit_Conversions!$A$5:$C$28,3,FALSE())=VLOOKUP(G92,Unit_Conversions!$A$5:$C$28,3,FALSE()),P92*VLOOKUP(G92,Unit_Conversions!$A$5:$C$28,2,FALSE())/(Q92*VLOOKUP(R92,Unit_Conversions!$A$5:$C$28,2,FALSE())),"")),"") -> 0.27 | M92: =IFERROR(F92*L92,"") -> 0.27 | N92: =IFERROR(J92*L92,"") -> 0 | O92: Post-library QC. | P92: =IFERROR(IF(LEFT(D92,1)="K",VLOOKUP(D92,Kit_Catalog!$A:$K,8,FALSE()),VLOOKUP(D92,Additional_Supply_Catalog!$A:$K,7,FALSE())),"") -> 135 | Q92: =IFERROR(IF(LEFT(D92,1)="K",VLOOKUP(D92,Kit_Catalog!$A:$K,7,FALSE()),VLOOKUP(D92,Additional_Supply_Catalog!$A:$K,8,FALSE())),"") -> 500 | R92: =IFERROR(IF(LEFT(D92,1)="K","rxn",VLOOKUP(D92,Additional_Supply_Catalog!$A:$K,9,FALSE())),"") -> tube
